Workbook
Name __ISC01: #REF!
Name __ISC01: #REF!
Name __ISC2: #REF!
Name __ISC2: #REF!
Name __ISC3: #REF!+#REF!
Name __ISC3: #REF!+#REF!
Name __ISC567: #REF!
Name __ISC567: #REF!
Name _10000: #REF!
Name _10000: #REF!
Name _10000: #REF!
Name _10000: #REF!
Name _1080: #REF!
Name _1080: #REF!
Name _1080: #REF!
Name _1080: #REF!
Name _1090: #REF!
Name _1090: #REF!
Name _1090: #REF!
Name _1090: #REF!
Name _1100: #REF!
Name _1100: #REF!
Name _1100: #REF!
Name _1100: #REF!
Name _1110: #REF!
Name _1110: #REF!
Name _1110: #REF!
Name _1110: #REF!
Name _2: #REF!
Name _2: #REF!
Name _2: #REF!
Name _2: #REF!
Name _2010: #REF!
Name _2010: #REF!
Name _2010: #REF!
Name _2010: #REF!
Name _2080: #REF!
Name _2080: #REF!
Name _2080: #REF!
Name _2080: #REF!
Name _2090: #REF!
Name _2090: #REF!
Name _2090: #REF!
Name _2090: #REF!
Name _2100: #REF!
Name _2100: #REF!
Name _2100: #REF!
Name _2100: #REF!
Name _2110: #REF!
Name _2110: #REF!
Name _2110: #REF!
Name _2110: #REF!
Name _3080: #REF!
Name _3080: #REF!
Name _3080: #REF!
Name _3080: #REF!
Name _3090: #REF!
Name _3090: #REF!
Name _3090: #REF!
Name _3090: #REF!

Sheet E5t_fix
A1: Income Tax Schedules (Effective Tax Rates): Series for Stata Import | O1: After-tax income | AB1: Marginal tax rates
AA2: Non-monotonic marginal tax rates
A3: year | B3: ty1 | C3: ty2 | D3: ty3 | E3: ty4 | F3: ty5 | G3: ty6 | H3: ty7 | I3: ty8 | J3: ty9 | K3: ty10 | L3: ty11 | M3: ty12
A4: 2026 | B4: =TE5f!$C7 -> 0 | C4: =TE5f!$C8 -> 0 | D4: =TE5f!$C9 -> 0.05 | E4: =TE5f!$C10 -> 0.1 | F4: =TE5f!$C11 -> 0.15 | G4: =TE5f!$C12 -> 0.2 | H4: =TE5f!$C13 -> 0.4 | I4: =TE5f!$C14 -> 0.5 | J4: =TE5f!$C15 -> 0.6 | K4: =TE5f!$C16 -> 0.7 | L4: =TE5f!$C17 -> 0.8 | M4: =TE5f!$C18 -> 0.9 | O4: =(1-B4)*E4b!B4 -> 5 | P4: =(1-C4)*E5b!C4 -> 7 | Q4: =(1-D4)*E5b!D4 -> 9.5 | R4: =(1-E4)*E5b!E4 -> 10.8 | S4: =(1-F4)*E5b!F4 -> 12.75 | T4: =(1-G4)*E5b!G4 -> 16 | U4: =(1-H4)*E5b!H4 -> 30 | V4: =(1-I4)*E5b!I4 -> 50 | W4: =(1-J4)*E5b!J4 -> 80 | ... Z4: =(1-M4)*E5b!M4 -> 500 | AB4: =(E5b!C4-P4-(E5b!B4-O4))/(E5b!C4-E5b!B4) -> 0 | AC4: =(E5b!D4-Q4-(E5b!C4-P4))/(E5b!D4-E5b!C4) -> 0.16666667 | AD4: =(E5b!E4-R4-(E5b!D4-Q4))/(E5b!E4-E5b!D4) -> 0.35 | AE4: =(E5b!F4-S4-(E5b!E4-R4))/(E5b!F4-E5b!E4) -> 0.35 | AF4: =(E5b!G4-T4-(E5b!F4-S4))/(E5b!G4-E5b!F4) -> 0.35 | AG4: =(E5b!H4-U4-(E5b!G4-T4))/(E5b!H4-E5b!G4) -> 0.53333333 | AH4: =(E5b!I4-V4-(E5b!H4-U4))/(E5b!I4-E5b!H4) -> 0.6 | AI4: =(E5b!J4-W4-(E5b!I4-V4))/(E5b!J4-E5b!I4) -> 0.7 | ... AL4: =(E5b!M4-Z4-(E5b!L4-Y4))/(E5b!M4-E5b!L4) -> 0.925
A5: 2027 | B5: =B4+(B$13-B$4)/9 -> 0 | C5: =C4+(C$13-C$4)/9 -> 0 | D5: =D4+(D$13-D$4)/9 -> 0.061111111 | E5: =E4+(E$13-E$4)/9 -> 0.11111111 | F5: =F4+(F$13-F$4)/9 -> 0.16111111 | G5: =G4+(G$13-G$4)/9 -> 0.21111111 | H5: =H4+(H$13-H$4)/9 -> 0.4 | I5: =I4+(I$13-I$4)/9 -> 0.5 | ... M5: =M4+(M$13-M$4)/9 -> 0.9 | O5: =(1-B5)*E5b!B5 -> 4.8888889 | P5: =(1-C5)*E5b!C5 -> 6.8888889 | Q5: =(1-D5)*E5b!D5 -> 9.1802469 | R5: =(1-E5)*E5b!E5 -> 10.469136 | S5: =(1-F5)*E5b!F5 -> 12.583333 | T5: =(1-G5)*E5b!G5 -> 15.777778 | U5: =(1-H5)*E5b!H5 -> 30 | V5: =(1-I5)*E5b!I5 -> 50 | ... Z5: =(1-M5)*E5b!M5 -> 500 | AA5: 1 | AB5: =(E5b!C5-P5-(E5b!B5-O5))/(E5b!C5-E5b!B5) -> 0 | AC5: =(E5b!D5-Q5-(E5b!C5-P5))/(E5b!D5-E5b!C5) -> 0.20683761 | AD5: =(E5b!E5-R5-(E5b!D5-Q5))/(E5b!E5-E5b!D5) -> 0.35555556 | AE5: =(E5b!F5-S5-(E5b!E5-R5))/(E5b!F5-E5b!E5) -> 0.34386973 | AF5: =(E5b!G5-T5-(E5b!F5-S5))/(E5b!G5-E5b!F5) -> 0.36111111 | AG5: =(E5b!H5-U5-(E5b!G5-T5))/(E5b!H5-E5b!G5) -> 0.52592593 | AH5: =(E5b!I5-V5-(E5b!H5-U5))/(E5b!I5-E5b!H5) -> 0.6 | AI5: =(E5b!J5-W5-(E5b!I5-V5))/(E5b!J5-E5b!I5) -> 0.7 | ... AL5: =(E5b!M5-Z5-(E5b!L5-Y5))/(E5b!M5-E5b!L5) -> 0.925
A6: 2028 | B6: =B5+(B$13-B$4)/9 -> 0 | C6: =C5+(C$13-C$4)/9 -> 0 | D6: =D5+(D$13-D$4)/9 -> 0.072222222 | E6: =E5+(E$13-E$4)/9 -> 0.12222222 | F6: =F5+(F$13-F$4)/9 -> 0.17222222 | G6: =G5+(G$13-G$4)/9 -> 0.22222222 | H6: =H5+(H$13-H$4)/9 -> 0.4 | I6: =I5+(I$13-I$4)/9 -> 0.5 | ... M6: =M5+(M$13-M$4)/9 -> 0.9 | O6: =(1-B6)*E5b!B6 -> 4.7777778 | P6: =(1-C6)*E5b!C6 -> 6.7777778 | Q6: =(1-D6)*E5b!D6 -> 8.8654321 | R6: =(1-E6)*E5b!E6 -> 10.14321 | S6: =(1-F6)*E5b!F6 -> 12.416667 | T6: =(1-G6)*E5b!G6 -> 15.555556 | U6: =(1-H6)*E5b!H6 -> 30 | V6: =(1-I6)*E5b!I6 -> 50 | ... Z6: =(1-M6)*E5b!M6 -> 500 | AA6: 1 | AB6: =(E5b!C6-P6-(E5b!B6-O6))/(E5b!C6-E5b!B6) -> 0 | AC6: =(E5b!D6-Q6-(E5b!C6-P6))/(E5b!D6-E5b!C6) -> 0.24844444 | AD6: =(E5b!E6-R6-(E5b!D6-Q6))/(E5b!E6-E5b!D6) -> 0.36111111 | AE6: =(E5b!F6-S6-(E5b!E6-R6))/(E5b!F6-E5b!E6) -> 0.33996416 | AF6: =(E5b!G6-T6-(E5b!F6-S6))/(E5b!G6-E5b!F6) -> 0.37222222 | AG6: =(E5b!H6-U6-(E5b!G6-T6))/(E5b!H6-E5b!G6) -> 0.51851852 | AH6: =(E5b!I6-V6-(E5b!H6-U6))/(E5b!I6-E5b!H6) -> 0.6 | AI6: =(E5b!J6-W6-(E5b!I6-V6))/(E5b!J6-E5b!I6) -> 0.7 | ... AL6: =(E5b!M6-Z6-(E5b!L6-Y6))/(E5b!M6-E5b!L6) -> 0.925
A7: 2029 | B7: =B6+(B$13-B$4)/9 -> 0 | C7: =C6+(C$13-C$4)/9 -> 0 | D7: =D6+(D$13-D$4)/9 -> 0.083333333 | E7: =E6+(E$13-E$4)/9 -> 0.13333333 | F7: =F6+(F$13-F$4)/9 -> 0.18333333 | G7: =G6+(G$13-G$4)/9 -> 0.23333333 | H7: =H6+(H$13-H$4)/9 -> 0.4 | I7: =I6+(I$13-I$4)/9 -> 0.5 | ... M7: =M6+(M$13-M$4)/9 -> 0.9 | O7: =(1-B7)*E5b!B7 -> 4.6666667 | P7: =(1-C7)*E5b!C7 -> 6.6666667 | Q7: =(1-D7)*E5b!D7 -> 8.5555556 | R7: =(1-E7)*E5b!E7 -> 9.8222222 | S7: =(1-F7)*E5b!F7 -> 12.25 | T7: =(1-G7)*E5b!G7 -> 15.333333 | U7: =(1-H7)*E5b!H7 -> 30 | V7: =(1-I7)*E5b!I7 -> 50 | ... Z7: =(1-M7)*E5b!M7 -> 500 | AA7: 1 | AB7: =(E5b!C7-P7-(E5b!B7-O7))/(E5b!C7-E5b!B7) -> 0 | AC7: =(E5b!D7-Q7-(E5b!C7-P7))/(E5b!D7-E5b!C7) -> 0.29166667 | AD7: =(E5b!E7-R7-(E5b!D7-Q7))/(E5b!E7-E5b!D7) -> 0.36666667 | AE7: =(E5b!F7-S7-(E5b!E7-R7))/(E5b!F7-E5b!E7) -> 0.33787879 | AF7: =(E5b!G7-T7-(E5b!F7-S7))/(E5b!G7-E5b!F7) -> 0.38333333 | AG7: =(E5b!H7-U7-(E5b!G7-T7))/(E5b!H7-E5b!G7) -> 0.51111111 | AH7: =(E5b!I7-V7-(E5b!H7-U7))/(E5b!I7-E5b!H7) -> 0.6 | AI7: =(E5b!J7-W7-(E5b!I7-V7))/(E5b!J7-E5b!I7) -> 0.7 | ... AL7: =(E5b!M7-Z7-(E5b!L7-Y7))/(E5b!M7-E5b!L7) -> 0.925
A8: 2030 | B8: =B7+(B$13-B$4)/9 -> 0 | C8: =C7+(C$13-C$4)/9 -> 0 | D8: =D7+(D$13-D$4)/9 -> 0.094444444 | E8: =E7+(E$13-E$4)/9 -> 0.14444444 | F8: =F7+(F$13-F$4)/9 -> 0.19444444 | G8: =G7+(G$13-G$4)/9 -> 0.24444444 | H8: =H7+(H$13-H$4)/9 -> 0.4 | I8: =I7+(I$13-I$4)/9 -> 0.5 | ... M8: =M7+(M$13-M$4)/9 -> 0.9 | O8: =(1-B8)*E5b!B8 -> 4.5555556 | P8: =(1-C8)*E5b!C8 -> 6.5555556 | Q8: =(1-D8)*E5b!D8 -> 8.2506173 | R8: =(1-E8)*E5b!E8 -> 9.5061728 | S8: =(1-F8)*E5b!F8 -> 12.083333 | T8: =(1-G8)*E5b!G8 -> 15.111111 | U8: =(1-H8)*E5b!H8 -> 30 | V8: =(1-I8)*E5b!I8 -> 50 | ... Z8: =(1-M8)*E5b!M8 -> 500 | AA8: 1 | AB8: =(E5b!C8-P8-(E5b!B8-O8))/(E5b!C8-E5b!B8) -> 0 | AC8: =(E5b!D8-Q8-(E5b!C8-P8))/(E5b!D8-E5b!C8) -> 0.33671498 | AD8: =(E5b!E8-R8-(E5b!D8-Q8))/(E5b!E8-E5b!D8) -> 0.37222222 | AE8: =(E5b!F8-S8-(E5b!E8-R8))/(E5b!F8-E5b!E8) -> 0.33730159 | AF8: =(E5b!G8-T8-(E5b!F8-S8))/(E5b!G8-E5b!F8) -> 0.39444444 | AG8: =(E5b!H8-U8-(E5b!G8-T8))/(E5b!H8-E5b!G8) -> 0.5037037 | AH8: =(E5b!I8-V8-(E5b!H8-U8))/(E5b!I8-E5b!H8) -> 0.6 | AI8: =(E5b!J8-W8-(E5b!I8-V8))/(E5b!J8-E5b!I8) -> 0.7 | ... AL8: =(E5b!M8-Z8-(E5b!L8-Y8))/(E5b!M8-E5b!L8) -> 0.925
A9: 2031 | B9: =B8+(B$13-B$4)/9 -> 0 | C9: =C8+(C$13-C$4)/9 -> 0 | D9: =D8+(D$13-D$4)/9 -> 0.10555556 | E9: =E8+(E$13-E$4)/9 -> 0.15555556 | F9: =F8+(F$13-F$4)/9 -> 0.20555556 | G9: =G8+(G$13-G$4)/9 -> 0.25555556 | H9: =H8+(H$13-H$4)/9 -> 0.4 | I9: =I8+(I$13-I$4)/9 -> 0.5 | ... M9: =M8+(M$13-M$4)/9 -> 0.9 | O9: =(1-B9)*E5b!B9 -> 4.4444444 | P9: =(1-C9)*E5b!C9 -> 6.4444444 | Q9: =(1-D9)*E5b!D9 -> 7.9506173 | R9: =(1-E9)*E5b!E9 -> 9.1950617 | S9: =(1-F9)*E5b!F9 -> 11.916667 | T9: =(1-G9)*E5b!G9 -> 14.888889 | U9: =(1-H9)*E5b!H9 -> 30 | V9: =(1-I9)*E5b!I9 -> 50 | ... Z9: =(1-M9)*E5b!M9 -> 500 | AA9: 1 | AB9: =(E5b!C9-P9-(E5b!B9-O9))/(E5b!C9-E5b!B9) -> 0 | AC9: =(E5b!D9-Q9-(E5b!C9-P9))/(E5b!D9-E5b!C9) -> 0.38383838 | AD9: =(E5b!E9-R9-(E5b!D9-Q9))/(E5b!E9-E5b!D9) -> 0.37777778 | AE9: =(E5b!F9-S9-(E5b!E9-R9))/(E5b!F9-E5b!E9) -> 0.33798799 | AF9: =(E5b!G9-T9-(E5b!F9-S9))/(E5b!G9-E5b!F9) -> 0.40555556 | AG9: =(E5b!H9-U9-(E5b!G9-T9))/(E5b!H9-E5b!G9) -> 0.4962963 | AH9: =(E5b!I9-V9-(E5b!H9-U9))/(E5b!I9-E5b!H9) -> 0.6 | AI9: =(E5b!J9-W9-(E5b!I9-V9))/(E5b!J9-E5b!I9) -> 0.7 | ... AL9: =(E5b!M9-Z9-(E5b!L9-Y9))/(E5b!M9-E5b!L9) -> 0.925
A10: 2032 | B10: =B9+(B$13-B$4)/9 -> 0 | C10: =C9+(C$13-C$4)/9 -> 0 | D10: =D9+(D$13-D$4)/9 -> 0.11666667 | E10: =E9+(E$13-E$4)/9 -> 0.16666667 | F10: =F9+(F$13-F$4)/9 -> 0.21666667 | G10: =G9+(G$13-G$4)/9 -> 0.26666667 | H10: =H9+(H$13-H$4)/9 -> 0.4 | I10: =I9+(I$13-I$4)/9 -> 0.5 | ... M10: =M9+(M$13-M$4)/9 -> 0.9 | O10: =(1-B10)*E5b!B10 -> 4.3333333 | P10: =(1-C10)*E5b!C10 -> 6.3333333 | Q10: =(1-D10)*E5b!D10 -> 7.6555556 | R10: =(1-E10)*E5b!E10 -> 8.8888889 | S10: =(1-F10)*E5b!F10 -> 11.75 | T10: =(1-G10)*E5b!G10 -> 14.666667 | U10: =(1-H10)*E5b!H10 -> 30 | V10: =(1-I10)*E5b!I10 -> 50 | ... Z10: =(1-M10)*E5b!M10 -> 500 | AA10: 2 | AB10: =(E5b!C10-P10-(E5b!B10-O10))/(E5b!C10-E5b!B10) -> 0 | AC10: =(E5b!D10-Q10-(E5b!C10-P10))/(E5b!D10-E5b!C10) -> 0.43333333 | AD10: =(E5b!E10-R10-(E5b!D10-Q10))/(E5b!E10-E5b!D10) -> 0.38333333 | AE10: =(E5b!F10-S10-(E5b!E10-R10))/(E5b!F10-E5b!E10) -> 0.33974359 | AF10: =(E5b!G10-T10-(E5b!F10-S10))/(E5b!G10-E5b!F10) -> 0.41666667 | AG10: =(E5b!H10-U10-(E5b!G10-T10))/(E5b!H10-E5b!G10) -> 0.48888889 | AH10: =(E5b!I10-V10-(E5b!H10-U10))/(E5b!I10-E5b!H10) -> 0.6 | AI10: =(E5b!J10-W10-(E5b!I10-V10))/(E5b!J10-E5b!I10) -> 0.7 | ... AL10: =(E5b!M10-Z10-(E5b!L10-Y10))/(E5b!M10-E5b!L10) -> 0.925
A11: 2033 | B11: =B10+(B$13-B$4)/9 -> 0 | C11: =C10+(C$13-C$4)/9 -> 0 | D11: =D10+(D$13-D$4)/9 -> 0.12777778 | E11: =E10+(E$13-E$4)/9 -> 0.17777778 | F11: =F10+(F$13-F$4)/9 -> 0.22777778 | G11: =G10+(G$13-G$4)/9 -> 0.27777778 | H11: =H10+(H$13-H$4)/9 -> 0.4 | I11: =I10+(I$13-I$4)/9 -> 0.5 | ... M11: =M10+(M$13-M$4)/9 -> 0.9 | O11: =(1-B11)*E5b!B11 -> 4.2222222 | P11: =(1-C11)*E5b!C11 -> 6.2222222 | Q11: =(1-D11)*E5b!D11 -> 7.3654321 | R11: =(1-E11)*E5b!E11 -> 8.5876543 | S11: =(1-F11)*E5b!F11 -> 11.583333 | T11: =(1-G11)*E5b!G11 -> 14.444444 | U11: =(1-H11)*E5b!H11 -> 30 | V11: =(1-I11)*E5b!I11 -> 50 | ... Z11: =(1-M11)*E5b!M11 -> 500 | AA11: 2 | AB11: =(E5b!C11-P11-(E5b!B11-O11))/(E5b!C11-E5b!B11) -> 0 | AC11: =(E5b!D11-Q11-(E5b!C11-P11))/(E5b!D11-E5b!C11) -> 0.48555556 | AD11: =(E5b!E11-R11-(E5b!D11-Q11))/(E5b!E11-E5b!D11) -> 0.38888889 | AE11: =(E5b!F11-S11-(E5b!E11-R11))/(E5b!F11-E5b!E11) -> 0.34241192 | AF11: =(E5b!G11-T11-(E5b!F11-S11))/(E5b!G11-E5b!F11) -> 0.42777778 | AG11: =(E5b!H11-U11-(E5b!G11-T11))/(E5b!H11-E5b!G11) -> 0.48148148 | AH11: =(E5b!I11-V11-(E5b!H11-U11))/(E5b!I11-E5b!H11) -> 0.6 | AI11: =(E5b!J11-W11-(E5b!I11-V11))/(E5b!J11-E5b!I11) -> 0.7 | ... AL11: =(E5b!M11-Z11-(E5b!L11-Y11))/(E5b!M11-E5b!L11) -> 0.925
A12: 2034 | B12: =B11+(B$13-B$4)/9 -> 0 | C12: =C11+(C$13-C$4)/9 -> 0 | D12: =D11+(D$13-D$4)/9 -> 0.13888889 | E12: =E11+(E$13-E$4)/9 -> 0.18888889 | F12: =F11+(F$13-F$4)/9 -> 0.23888889 | G12: =G11+(G$13-G$4)/9 -> 0.28888889 | H12: =H11+(H$13-H$4)/9 -> 0.4 | I12: =I11+(I$13-I$4)/9 -> 0.5 | ... M12: =M11+(M$13-M$4)/9 -> 0.9 | O12: =(1-B12)*E5b!B12 -> 4.1111111 | P12: =(1-C12)*E5b!C12 -> 6.1111111 | Q12: =(1-D12)*E5b!D12 -> 7.0802469 | R12: =(1-E12)*E5b!E12 -> 8.291358 | S12: =(1-F12)*E5b!F12 -> 11.416667 | T12: =(1-G12)*E5b!G12 -> 14.222222 | U12: =(1-H12)*E5b!H12 -> 30 | V12: =(1-I12)*E5b!I12 -> 50 | ... Z12: =(1-M12)*E5b!M12 -> 500 | AA12: 2 | AB12: =(E5b!C12-P12-(E5b!B12-O12))/(E5b!C12-E5b!B12) -> 0 | AC12: =(E5b!D12-Q12-(E5b!C12-P12))/(E5b!D12-E5b!C12) -> 0.54093567 | AD12: =(E5b!E12-R12-(E5b!D12-Q12))/(E5b!E12-E5b!D12) -> 0.39444444 | AE12: =(E5b!F12-S12-(E5b!E12-R12))/(E5b!F12-E5b!E12) -> 0.34586563 | AF12: =(E5b!G12-T12-(E5b!F12-S12))/(E5b!G12-E5b!F12) -> 0.43888889 | AG12: =(E5b!H12-U12-(E5b!G12-T12))/(E5b!H12-E5b!G12) -> 0.47407407 | AH12: =(E5b!I12-V12-(E5b!H12-U12))/(E5b!I12-E5b!H12) -> 0.6 | AI12: =(E5b!J12-W12-(E5b!I12-V12))/(E5b!J12-E5b!I12) -> 0.7 | ... AL12: =(E5b!M12-Z12-(E5b!L12-Y12))/(E5b!M12-E5b!L12) -> 0.925
A13: 2035 | B13: 0 | C13: 0 | D13: 0.15 | E13: 0.2 | F13: 0.25 | G13: 0.3 | H13: 0.4 | I13: 0.5 | J13: 0.6 | K13: 0.7 | L13: 0.8 | M13: 0.9 | O13: =(1-B13)*E5b!B13 -> 4 | P13: =(1-C13)*E5b!C13 -> 6 | Q13: =(1-D13)*E5b!D13 -> 6.8 | R13: =(1-E13)*E5b!E13 -> 8 | S13: =(1-F13)*E5b!F13 -> 11.25 | T13: =(1-G13)*E5b!G13 -> 14 | U13: =(1-H13)*E5b!H13 -> 30 | V13: =(1-I13)*E5b!I13 -> 50 | ... Z13: =(1-M13)*E5b!M13 -> 500 | AA13: 2 | AB13: =(E5b!C13-P13-(E5b!B13-O13))/(E5b!C13-E5b!B13) -> 0 | AC13: =(E5b!D13-Q13-(E5b!C13-P13))/(E5b!D13-E5b!C13) -> 0.6 | AD13: =(E5b!E13-R13-(E5b!D13-Q13))/(E5b!E13-E5b!D13) -> 0.4 | AE13: =(E5b!F13-S13-(E5b!E13-R13))/(E5b!F13-E5b!E13) -> 0.35 | AF13: =(E5b!G13-T13-(E5b!F13-S13))/(E5b!G13-E5b!F13) -> 0.45 | AG13: =(E5b!H13-U13-(E5b!G13-T13))/(E5b!H13-E5b!G13) -> 0.46666667 | AH13: =(E5b!I13-V13-(E5b!H13-U13))/(E5b!I13-E5b!H13) -> 0.6 | AI13: =(E5b!J13-W13-(E5b!I13-V13))/(E5b!J13-E5b!I13) -> 0.7 | ... AL13: =(E5b!M13-Z13-(E5b!L13-Y13))/(E5b!M13-E5b!L13) -> 0.925
A14: 2036 | B14: =B13+(B$28-B$13)/15 -> 0 | C14: =C13+(C$28-C$13)/15 -> 0 | D14: =D13+(D$28-D$13)/15 -> 0.15 | E14: =E13+(E$28-E$13)/15 -> 0.2 | F14: =F13+(F$28-F$13)/15 -> 0.25 | G14: =G13+(G$28-G$13)/15 -> 0.3 | H14: =H13+(H$28-H$13)/15 -> 0.4 | I14: =I13+(I$28-I$13)/15 -> 0.5 | ... M14: =M13+(M$28-M$13)/15 -> 0.9 | O14: =(1-B14)*E5b!B14 -> 3.9333333 | P14: =(1-C14)*E5b!C14 -> 5.8666667 | Q14: =(1-D14)*E5b!D14 -> 6.6866667 | R14: =(1-E14)*E5b!E14 -> 7.8933333 | S14: =(1-F14)*E5b!F14 -> 11.1 | T14: =(1-G14)*E5b!G14 -> 14 | U14: =(1-H14)*E5b!H14 -> 30 | V14: =(1-I14)*E5b!I14 -> 50 | ... Z14: =(1-M14)*E5b!M14 -> 500 | AA14: 2 | AB14: =(E5b!C14-P14-(E5b!B14-O14))/(E5b!C14-E5b!B14) -> 0 | AC14: =(E5b!D14-Q14-(E5b!C14-P14))/(E5b!D14-E5b!C14) -> 0.59 | AD14: =(E5b!E14-R14-(E5b!D14-Q14))/(E5b!E14-E5b!D14) -> 0.39666667 | AE14: =(E5b!F14-S14-(E5b!E14-R14))/(E5b!F14-E5b!E14) -> 0.35 | AF14: =(E5b!G14-T14-(E5b!F14-S14))/(E5b!G14-E5b!F14) -> 0.44230769 | AG14: =(E5b!H14-U14-(E5b!G14-T14))/(E5b!H14-E5b!G14) -> 0.46666667 | AH14: =(E5b!I14-V14-(E5b!H14-U14))/(E5b!I14-E5b!H14) -> 0.6 | AI14: =(E5b!J14-W14-(E5b!I14-V14))/(E5b!J14-E5b!I14) -> 0.7 | ... AL14: =(E5b!M14-Z14-(E5b!L14-Y14))/(E5b!M14-E5b!L14) -> 0.925
A15: 2037 | B15: =B14+(B$28-B$13)/15 -> 0 | C15: =C14+(C$28-C$13)/15 -> 0 | D15: =D14+(D$28-D$13)/15 -> 0.15 | E15: =E14+(E$28-E$13)/15 -> 0.2 | F15: =F14+(F$28-F$13)/15 -> 0.25 | G15: =G14+(G$28-G$13)/15 -> 0.3 | H15: =H14+(H$28-H$13)/15 -> 0.4 | I15: =I14+(I$28-I$13)/15 -> 0.5 | ... M15: =M14+(M$28-M$13)/15 -> 0.9 | O15: =(1-B15)*E5b!B15 -> 3.8666667 | P15: =(1-C15)*E5b!C15 -> 5.7333333 | Q15: =(1-D15)*E5b!D15 -> 6.5733333 | R15: =(1-E15)*E5b!E15 -> 7.7866667 | S15: =(1-F15)*E5b!F15 -> 10.95 | T15: =(1-G15)*E5b!G15 -> 14 | U15: =(1-H15)*E5b!H15 -> 30 | V15: =(1-I15)*E5b!I15 -> 50 | ... Z15: =(1-M15)*E5b!M15 -> 500 | AA15: 2 | AB15: =(E5b!C15-P15-(E5b!B15-O15))/(E5b!C15-E5b!B15) -> 0 | AC15: =(E5b!D15-Q15-(E5b!C15-P15))/(E5b!D15-E5b!C15) -> 0.58 | AD15: =(E5b!E15-R15-(E5b!D15-Q15))/(E5b!E15-E5b!D15) -> 0.39333333 | AE15: =(E5b!F15-S15-(E5b!E15-R15))/(E5b!F15-E5b!E15) -> 0.35 | AF15: =(E5b!G15-T15-(E5b!F15-S15))/(E5b!G15-E5b!F15) -> 0.43518519 | AG15: =(E5b!H15-U15-(E5b!G15-T15))/(E5b!H15-E5b!G15) -> 0.46666667 | AH15: =(E5b!I15-V15-(E5b!H15-U15))/(E5b!I15-E5b!H15) -> 0.6 | AI15: =(E5b!J15-W15-(E5b!I15-V15))/(E5b!J15-E5b!I15) -> 0.7 | ... AL15: =(E5b!M15-Z15-(E5b!L15-Y15))/(E5b!M15-E5b!L15) -> 0.925
A16: 2038 | B16: =B15+(B$28-B$13)/15 -> 0 | C16: =C15+(C$28-C$13)/15 -> 0 | D16: =D15+(D$28-D$13)/15 -> 0.15 | E16: =E15+(E$28-E$13)/15 -> 0.2 | F16: =F15+(F$28-F$13)/15 -> 0.25 | G16: =G15+(G$28-G$13)/15 -> 0.3 | H16: =H15+(H$28-H$13)/15 -> 0.4 | I16: =I15+(I$28-I$13)/15 -> 0.5 | ... M16: =M15+(M$28-M$13)/15 -> 0.9 | O16: =(1-B16)*E5b!B16 -> 3.8 | P16: =(1-C16)*E5b!C16 -> 5.6 | Q16: =(1-D16)*E5b!D16 -> 6.46 | R16: =(1-E16)*E5b!E16 -> 7.68 | S16: =(1-F16)*E5b!F16 -> 10.8 | T16: =(1-G16)*E5b!G16 -> 14 | U16: =(1-H16)*E5b!H16 -> 30 | V16: =(1-I16)*E5b!I16 -> 50 | ... Z16: =(1-M16)*E5b!M16 -> 500 | AA16: 2 | AB16: =(E5b!C16-P16-(E5b!B16-O16))/(E5b!C16-E5b!B16) -> 0 | AC16: =(E5b!D16-Q16-(E5b!C16-P16))/(E5b!D16-E5b!C16) -> 0.57 | AD16: =(E5b!E16-R16-(E5b!D16-Q16))/(E5b!E16-E5b!D16) -> 0.39 | AE16: =(E5b!F16-S16-(E5b!E16-R16))/(E5b!F16-E5b!E16) -> 0.35 | AF16: =(E5b!G16-T16-(E5b!F16-S16))/(E5b!G16-E5b!F16) -> 0.42857143 | AG16: =(E5b!H16-U16-(E5b!G16-T16))/(E5b!H16-E5b!G16) -> 0.46666667 | AH16: =(E5b!I16-V16-(E5b!H16-U16))/(E5b!I16-E5b!H16) -> 0.6 | AI16: =(E5b!J16-W16-(E5b!I16-V16))/(E5b!J16-E5b!I16) -> 0.7 | ... AL16: =(E5b!M16-Z16-(E5b!L16-Y16))/(E5b!M16-E5b!L16) -> 0.925
A17: 2039 | B17: =B16+(B$28-B$13)/15 -> 0 | C17: =C16+(C$28-C$13)/15 -> 0 | D17: =D16+(D$28-D$13)/15 -> 0.15 | E17: =E16+(E$28-E$13)/15 -> 0.2 | F17: =F16+(F$28-F$13)/15 -> 0.25 | G17: =G16+(G$28-G$13)/15 -> 0.3 | H17: =H16+(H$28-H$13)/15 -> 0.4 | I17: =I16+(I$28-I$13)/15 -> 0.5 | ... M17: =M16+(M$28-M$13)/15 -> 0.9 | O17: =(1-B17)*E5b!B17 -> 3.7333333 | P17: =(1-C17)*E5b!C17 -> 5.4666667 | Q17: =(1-D17)*E5b!D17 -> 6.3466667 | R17: =(1-E17)*E5b!E17 -> 7.5733333 | S17: =(1-F17)*E5b!F17 -> 10.65 | T17: =(1-G17)*E5b!G17 -> 14 | U17: =(1-H17)*E5b!H17 -> 30 | V17: =(1-I17)*E5b!I17 -> 50 | ... Z17: =(1-M17)*E5b!M17 -> 500 | AA17: 2 | AB17: =(E5b!C17-P17-(E5b!B17-O17))/(E5b!C17-E5b!B17) -> 0 | AC17: =(E5b!D17-Q17-(E5b!C17-P17))/(E5b!D17-E5b!C17) -> 0.56 | AD17: =(E5b!E17-R17-(E5b!D17-Q17))/(E5b!E17-E5b!D17) -> 0.38666667 | AE17: =(E5b!F17-S17-(E5b!E17-R17))/(E5b!F17-E5b!E17) -> 0.35 | AF17: =(E5b!G17-T17-(E5b!F17-S17))/(E5b!G17-E5b!F17) -> 0.42241379 | AG17: =(E5b!H17-U17-(E5b!G17-T17))/(E5b!H17-E5b!G17) -> 0.46666667 | AH17: =(E5b!I17-V17-(E5b!H17-U17))/(E5b!I17-E5b!H17) -> 0.6 | AI17: =(E5b!J17-W17-(E5b!I17-V17))/(E5b!J17-E5b!I17) -> 0.7 | ... AL17: =(E5b!M17-Z17-(E5b!L17-Y17))/(E5b!M17-E5b!L17) -> 0.925
A18: 2040 | B18: =B17+(B$28-B$13)/15 -> 0 | C18: =C17+(C$28-C$13)/15 -> 0 | D18: =D17+(D$28-D$13)/15 -> 0.15 | E18: =E17+(E$28-E$13)/15 -> 0.2 | F18: =F17+(F$28-F$13)/15 -> 0.25 | G18: =G17+(G$28-G$13)/15 -> 0.3 | H18: =H17+(H$28-H$13)/15 -> 0.4 | I18: =I17+(I$28-I$13)/15 -> 0.5 | ... M18: =M17+(M$28-M$13)/15 -> 0.9 | O18: =(1-B18)*E5b!B18 -> 3.6666667 | P18: =(1-C18)*E5b!C18 -> 5.3333333 | Q18: =(1-D18)*E5b!D18 -> 6.2333333 | R18: =(1-E18)*E5b!E18 -> 7.4666667 | S18: =(1-F18)*E5b!F18 -> 10.5 | T18: =(1-G18)*E5b!G18 -> 14 | U18: =(1-H18)*E5b!H18 -> 30 | V18: =(1-I18)*E5b!I18 -> 50 | ... Z18: =(1-M18)*E5b!M18 -> 500 | AA18: 2 | AB18: =(E5b!C18-P18-(E5b!B18-O18))/(E5b!C18-E5b!B18) -> 0 | AC18: =(E5b!D18-Q18-(E5b!C18-P18))/(E5b!D18-E5b!C18) -> 0.55 | AD18: =(E5b!E18-R18-(E5b!D18-Q18))/(E5b!E18-E5b!D18) -> 0.38333333 | AE18: =(E5b!F18-S18-(E5b!E18-R18))/(E5b!F18-E5b!E18) -> 0.35 | AF18: =(E5b!G18-T18-(E5b!F18-S18))/(E5b!G18-E5b!F18) -> 0.41666667 | AG18: =(E5b!H18-U18-(E5b!G18-T18))/(E5b!H18-E5b!G18) -> 0.46666667 | AH18: =(E5b!I18-V18-(E5b!H18-U18))/(E5b!I18-E5b!H18) -> 0.6 | AI18: =(E5b!J18-W18-(E5b!I18-V18))/(E5b!J18-E5b!I18) -> 0.7 | ... AL18: =(E5b!M18-Z18-(E5b!L18-Y18))/(E5b!M18-E5b!L18) -> 0.925
A19: 2041 | B19: =B18+(B$28-B$13)/15 -> 0 | C19: =C18+(C$28-C$13)/15 -> 0 | D19: =D18+(D$28-D$13)/15 -> 0.15 | E19: =E18+(E$28-E$13)/15 -> 0.2 | F19: =F18+(F$28-F$13)/15 -> 0.25 | G19: =G18+(G$28-G$13)/15 -> 0.3 | H19: =H18+(H$28-H$13)/15 -> 0.4 | I19: =I18+(I$28-I$13)/15 -> 0.5 | ... M19: =M18+(M$28-M$13)/15 -> 0.9 | O19: =(1-B19)*E5b!B19 -> 3.6 | P19: =(1-C19)*E5b!C19 -> 5.2 | Q19: =(1-D19)*E5b!D19 -> 6.12 | R19: =(1-E19)*E5b!E19 -> 7.36 | S19: =(1-F19)*E5b!F19 -> 10.35 | T19: =(1-G19)*E5b!G19 -> 14 | U19: =(1-H19)*E5b!H19 -> 30 | V19: =(1-I19)*E5b!I19 -> 50 | ... Z19: =(1-M19)*E5b!M19 -> 500 | AA19: 2 | AB19: =(E5b!C19-P19-(E5b!B19-O19))/(E5b!C19-E5b!B19) -> 0 | AC19: =(E5b!D19-Q19-(E5b!C19-P19))/(E5b!D19-E5b!C19) -> 0.54 | AD19: =(E5b!E19-R19-(E5b!D19-Q19))/(E5b!E19-E5b!D19) -> 0.38 | AE19: =(E5b!F19-S19-(E5b!E19-R19))/(E5b!F19-E5b!E19) -> 0.35 | AF19: =(E5b!G19-T19-(E5b!F19-S19))/(E5b!G19-E5b!F19) -> 0.41129032 | AG19: =(E5b!H19-U19-(E5b!G19-T19))/(E5b!H19-E5b!G19) -> 0.46666667 | AH19: =(E5b!I19-V19-(E5b!H19-U19))/(E5b!I19-E5b!H19) -> 0.6 | AI19: =(E5b!J19-W19-(E5b!I19-V19))/(E5b!J19-E5b!I19) -> 0.7 | ... AL19: =(E5b!M19-Z19-(E5b!L19-Y19))/(E5b!M19-E5b!L19) -> 0.925
A20: 2042 | B20: =B19+(B$28-B$13)/15 -> 0 | C20: =C19+(C$28-C$13)/15 -> 0 | D20: =D19+(D$28-D$13)/15 -> 0.15 | E20: =E19+(E$28-E$13)/15 -> 0.2 | F20: =F19+(F$28-F$13)/15 -> 0.25 | G20: =G19+(G$28-G$13)/15 -> 0.3 | H20: =H19+(H$28-H$13)/15 -> 0.4 | I20: =I19+(I$28-I$13)/15 -> 0.5 | ... M20: =M19+(M$28-M$13)/15 -> 0.9 | O20: =(1-B20)*E5b!B20 -> 3.5333333 | P20: =(1-C20)*E5b!C20 -> 5.0666667 | Q20: =(1-D20)*E5b!D20 -> 6.0066667 | R20: =(1-E20)*E5b!E20 -> 7.2533333 | S20: =(1-F20)*E5b!F20 -> 10.2 | T20: =(1-G20)*E5b!G20 -> 14 | U20: =(1-H20)*E5b!H20 -> 30 | V20: =(1-I20)*E5b!I20 -> 50 | ... Z20: =(1-M20)*E5b!M20 -> 500 | AA20: 2 | AB20: =(E5b!C20-P20-(E5b!B20-O20))/(E5b!C20-E5b!B20) -> 0 | AC20: =(E5b!D20-Q20-(E5b!C20-P20))/(E5b!D20-E5b!C20) -> 0.53 | AD20: =(E5b!E20-R20-(E5b!D20-Q20))/(E5b!E20-E5b!D20) -> 0.37666667 | AE20: =(E5b!F20-S20-(E5b!E20-R20))/(E5b!F20-E5b!E20) -> 0.35 | AF20: =(E5b!G20-T20-(E5b!F20-S20))/(E5b!G20-E5b!F20) -> 0.40625 | AG20: =(E5b!H20-U20-(E5b!G20-T20))/(E5b!H20-E5b!G20) -> 0.46666667 | AH20: =(E5b!I20-V20-(E5b!H20-U20))/(E5b!I20-E5b!H20) -> 0.6 | AI20: =(E5b!J20-W20-(E5b!I20-V20))/(E5b!J20-E5b!I20) -> 0.7 | ... AL20: =(E5b!M20-Z20-(E5b!L20-Y20))/(E5b!M20-E5b!L20) -> 0.925
A21: 2043 | B21: =B20+(B$28-B$13)/15 -> 0 | C21: =C20+(C$28-C$13)/15 -> 0 | D21: =D20+(D$28-D$13)/15 -> 0.15 | E21: =E20+(E$28-E$13)/15 -> 0.2 | F21: =F20+(F$28-F$13)/15 -> 0.25 | G21: =G20+(G$28-G$13)/15 -> 0.3 | H21: =H20+(H$28-H$13)/15 -> 0.4 | I21: =I20+(I$28-I$13)/15 -> 0.5 | ... M21: =M20+(M$28-M$13)/15 -> 0.9 | O21: =(1-B21)*E5b!B21 -> 3.4666667 | P21: =(1-C21)*E5b!C21 -> 4.9333333 | Q21: =(1-D21)*E5b!D21 -> 5.8933333 | R21: =(1-E21)*E5b!E21 -> 7.1466667 | S21: =(1-F21)*E5b!F21 -> 10.05 | T21: =(1-G21)*E5b!G21 -> 14 | U21: =(1-H21)*E5b!H21 -> 30 | V21: =(1-I21)*E5b!I21 -> 50 | ... Z21: =(1-M21)*E5b!M21 -> 500 | AA21: 2 | AB21: =(E5b!C21-P21-(E5b!B21-O21))/(E5b!C21-E5b!B21) -> 0 | AC21: =(E5b!D21-Q21-(E5b!C21-P21))/(E5b!D21-E5b!C21) -> 0.52 | AD21: =(E5b!E21-R21-(E5b!D21-Q21))/(E5b!E21-E5b!D21) -> 0.37333333 | AE21: =(E5b!F21-S21-(E5b!E21-R21))/(E5b!F21-E5b!E21) -> 0.35 | AF21: =(E5b!G21-T21-(E5b!F21-S21))/(E5b!G21-E5b!F21) -> 0.40151515 | AG21: =(E5b!H21-U21-(E5b!G21-T21))/(E5b!H21-E5b!G21) -> 0.46666667 | AH21: =(E5b!I21-V21-(E5b!H21-U21))/(E5b!I21-E5b!H21) -> 0.6 | AI21: =(E5b!J21-W21-(E5b!I21-V21))/(E5b!J21-E5b!I21) -> 0.7 | ... AL21: =(E5b!M21-Z21-(E5b!L21-Y21))/(E5b!M21-E5b!L21) -> 0.925
A22: 2044 | B22: =B21+(B$28-B$13)/15 -> 0 | C22: =C21+(C$28-C$13)/15 -> 0 | D22: =D21+(D$28-D$13)/15 -> 0.15 | E22: =E21+(E$28-E$13)/15 -> 0.2 | F22: =F21+(F$28-F$13)/15 -> 0.25 | G22: =G21+(G$28-G$13)/15 -> 0.3 | H22: =H21+(H$28-H$13)/15 -> 0.4 | I22: =I21+(I$28-I$13)/15 -> 0.5 | ... M22: =M21+(M$28-M$13)/15 -> 0.9 | O22: =(1-B22)*E5b!B22 -> 3.4 | P22: =(1-C22)*E5b!C22 -> 4.8 | Q22: =(1-D22)*E5b!D22 -> 5.78 | R22: =(1-E22)*E5b!E22 -> 7.04 | S22: =(1-F22)*E5b!F22 -> 9.9 | T22: =(1-G22)*E5b!G22 -> 14 | U22: =(1-H22)*E5b!H22 -> 30 | V22: =(1-I22)*E5b!I22 -> 50 | ... Z22: =(1-M22)*E5b!M22 -> 500 | AA22: 2 | AB22: =(E5b!C22-P22-(E5b!B22-O22))/(E5b!C22-E5b!B22) -> 0 | AC22: =(E5b!D22-Q22-(E5b!C22-P22))/(E5b!D22-E5b!C22) -> 0.51 | AD22: =(E5b!E22-R22-(E5b!D22-Q22))/(E5b!E22-E5b!D22) -> 0.37 | AE22: =(E5b!F22-S22-(E5b!E22-R22))/(E5b!F22-E5b!E22) -> 0.35 | AF22: =(E5b!G22-T22-(E5b!F22-S22))/(E5b!G22-E5b!F22) -> 0.39705882 | AG22: =(E5b!H22-U22-(E5b!G22-T22))/(E5b!H22-E5b!G22) -> 0.46666667 | AH22: =(E5b!I22-V22-(E5b!H22-U22))/(E5b!I22-E5b!H22) -> 0.6 | AI22: =(E5b!J22-W22-(E5b!I22-V22))/(E5b!J22-E5b!I22) -> 0.7 | ... AL22: =(E5b!M22-Z22-(E5b!L22-Y22))/(E5b!M22-E5b!L22) -> 0.925
A23: 2045 | B23: =B22+(B$28-B$13)/15 -> 0 | C23: =C22+(C$28-C$13)/15 -> 0 | D23: =D22+(D$28-D$13)/15 -> 0.15 | E23: =E22+(E$28-E$13)/15 -> 0.2 | F23: =F22+(F$28-F$13)/15 -> 0.25 | G23: =G22+(G$28-G$13)/15 -> 0.3 | H23: =H22+(H$28-H$13)/15 -> 0.4 | I23: =I22+(I$28-I$13)/15 -> 0.5 | ... M23: =M22+(M$28-M$13)/15 -> 0.9 | O23: =(1-B23)*E5b!B23 -> 3.3333333 | P23: =(1-C23)*E5b!C23 -> 4.6666667 | Q23: =(1-D23)*E5b!D23 -> 5.6666667 | R23: =(1-E23)*E5b!E23 -> 6.9333333 | S23: =(1-F23)*E5b!F23 -> 9.75 | T23: =(1-G23)*E5b!G23 -> 14 | U23: =(1-H23)*E5b!H23 -> 30 | V23: =(1-I23)*E5b!I23 -> 50 | ... Z23: =(1-M23)*E5b!M23 -> 500 | AA23: 2 | AB23: =(E5b!C23-P23-(E5b!B23-O23))/(E5b!C23-E5b!B23) -> 0 | AC23: =(E5b!D23-Q23-(E5b!C23-P23))/(E5b!D23-E5b!C23) -> 0.5 | AD23: =(E5b!E23-R23-(E5b!D23-Q23))/(E5b!E23-E5b!D23) -> 0.36666667 | AE23: =(E5b!F23-S23-(E5b!E23-R23))/(E5b!F23-E5b!E23) -> 0.35 | AF23: =(E5b!G23-T23-(E5b!F23-S23))/(E5b!G23-E5b!F23) -> 0.39285714 | AG23: =(E5b!H23-U23-(E5b!G23-T23))/(E5b!H23-E5b!G23) -> 0.46666667 | AH23: =(E5b!I23-V23-(E5b!H23-U23))/(E5b!I23-E5b!H23) -> 0.6 | AI23: =(E5b!J23-W23-(E5b!I23-V23))/(E5b!J23-E5b!I23) -> 0.7 | ... AL23: =(E5b!M23-Z23-(E5b!L23-Y23))/(E5b!M23-E5b!L23) -> 0.925
A24: 2046 | B24: =B23+(B$28-B$13)/15 -> 0 | C24: =C23+(C$28-C$13)/15 -> 0 | D24: =D23+(D$28-D$13)/15 -> 0.15 | E24: =E23+(E$28-E$13)/15 -> 0.2 | F24: =F23+(F$28-F$13)/15 -> 0.25 | G24: =G23+(G$28-G$13)/15 -> 0.3 | H24: =H23+(H$28-H$13)/15 -> 0.4 | I24: =I23+(I$28-I$13)/15 -> 0.5 | ... M24: =M23+(M$28-M$13)/15 -> 0.9 | O24: =(1-B24)*E5b!B24 -> 3.2666667 | P24: =(1-C24)*E5b!C24 -> 4.5333333 | Q24: =(1-D24)*E5b!D24 -> 5.5533333 | R24: =(1-E24)*E5b!E24 -> 6.8266667 | S24: =(1-F24)*E5b!F24 -> 9.6 | T24: =(1-G24)*E5b!G24 -> 14 | U24: =(1-H24)*E5b!H24 -> 30 | V24: =(1-I24)*E5b!I24 -> 50 | ... Z24: =(1-M24)*E5b!M24 -> 500 | AA24: 2 | AB24: =(E5b!C24-P24-(E5b!B24-O24))/(E5b!C24-E5b!B24) -> 0 | AC24: =(E5b!D24-Q24-(E5b!C24-P24))/(E5b!D24-E5b!C24) -> 0.49 | AD24: =(E5b!E24-R24-(E5b!D24-Q24))/(E5b!E24-E5b!D24) -> 0.36333333 | AE24: =(E5b!F24-S24-(E5b!E24-R24))/(E5b!F24-E5b!E24) -> 0.35 | AF24: =(E5b!G24-T24-(E5b!F24-S24))/(E5b!G24-E5b!F24) -> 0.38888889 | AG24: =(E5b!H24-U24-(E5b!G24-T24))/(E5b!H24-E5b!G24) -> 0.46666667 | AH24: =(E5b!I24-V24-(E5b!H24-U24))/(E5b!I24-E5b!H24) -> 0.6 | AI24: =(E5b!J24-W24-(E5b!I24-V24))/(E5b!J24-E5b!I24) -> 0.7 | ... AL24: =(E5b!M24-Z24-(E5b!L24-Y24))/(E5b!M24-E5b!L24) -> 0.925
A25: 2047 | B25: =B24+(B$28-B$13)/15 -> 0 | C25: =C24+(C$28-C$13)/15 -> 0 | D25: =D24+(D$28-D$13)/15 -> 0.15 | E25: =E24+(E$28-E$13)/15 -> 0.2 | F25: =F24+(F$28-F$13)/15 -> 0.25 | G25: =G24+(G$28-G$13)/15 -> 0.3 | H25: =H24+(H$28-H$13)/15 -> 0.4 | I25: =I24+(I$28-I$13)/15 -> 0.5 | ... M25: =M24+(M$28-M$13)/15 -> 0.9 | O25: =(1-B25)*E5b!B25 -> 3.2 | P25: =(1-C25)*E5b!C25 -> 4.4 | Q25: =(1-D25)*E5b!D25 -> 5.44 | R25: =(1-E25)*E5b!E25 -> 6.72 | S25: =(1-F25)*E5b!F25 -> 9.45 | T25: =(1-G25)*E5b!G25 -> 14 | U25: =(1-H25)*E5b!H25 -> 30 | V25: =(1-I25)*E5b!I25 -> 50 | ... Z25: =(1-M25)*E5b!M25 -> 500 | AA25: 2 | AB25: =(E5b!C25-P25-(E5b!B25-O25))/(E5b!C25-E5b!B25) -> 0 | AC25: =(E5b!D25-Q25-(E5b!C25-P25))/(E5b!D25-E5b!C25) -> 0.48 | AD25: =(E5b!E25-R25-(E5b!D25-Q25))/(E5b!E25-E5b!D25) -> 0.36 | AE25: =(E5b!F25-S25-(E5b!E25-R25))/(E5b!F25-E5b!E25) -> 0.35 | AF25: =(E5b!G25-T25-(E5b!F25-S25))/(E5b!G25-E5b!F25) -> 0.38513514 | AG25: =(E5b!H25-U25-(E5b!G25-T25))/(E5b!H25-E5b!G25) -> 0.46666667 | AH25: =(E5b!I25-V25-(E5b!H25-U25))/(E5b!I25-E5b!H25) -> 0.6 | AI25: =(E5b!J25-W25-(E5b!I25-V25))/(E5b!J25-E5b!I25) -> 0.7 | ... AL25: =(E5b!M25-Z25-(E5b!L25-Y25))/(E5b!M25-E5b!L25) -> 0.925
... A27: 2049 | B27: =B26+(B$28-B$13)/15 -> 0 | C27: =C26+(C$28-C$13)/15 -> 0 | D27: =D26+(D$28-D$13)/15 -> 0.15 | E27: =E26+(E$28-E$13)/15 -> 0.2 | F27: =F26+(F$28-F$13)/15 -> 0.25 | G27: =G26+(G$28-G$13)/15 -> 0.3 | H27: =H26+(H$28-H$13)/15 -> 0.4 | I27: =I26+(I$28-I$13)/15 -> 0.5 | ... M27: =M26+(M$28-M$13)/15 -> 0.9 | O27: =(1-B27)*E5b!B27 -> 3.0666667 | P27: =(1-C27)*E5b!C27 -> 4.1333333 | Q27: =(1-D27)*E5b!D27 -> 5.2133333 | R27: =(1-E27)*E5b!E27 -> 6.5066667 | S27: =(1-F27)*E5b!F27 -> 9.15 | T27: =(1-G27)*E5b!G27 -> 14 | U27: =(1-H27)*E5b!H27 -> 30 | V27: =(1-I27)*E5b!I27 -> 50 | ... Z27: =(1-M27)*E5b!M27 -> 500 | AA27: 2 | AB27: =(E5b!C27-P27-(E5b!B27-O27))/(E5b!C27-E5b!B27) -> 0 | AC27: =(E5b!D27-Q27-(E5b!C27-P27))/(E5b!D27-E5b!C27) -> 0.46 | AD27: =(E5b!E27-R27-(E5b!D27-Q27))/(E5b!E27-E5b!D27) -> 0.35333333 | AE27: =(E5b!F27-S27-(E5b!E27-R27))/(E5b!F27-E5b!E27) -> 0.35 | AF27: =(E5b!G27-T27-(E5b!F27-S27))/(E5b!G27-E5b!F27) -> 0.37820513 | AG27: =(E5b!H27-U27-(E5b!G27-T27))/(E5b!H27-E5b!G27) -> 0.46666667 | AH27: =(E5b!I27-V27-(E5b!H27-U27))/(E5b!I27-E5b!H27) -> 0.6 | AI27: =(E5b!J27-W27-(E5b!I27-V27))/(E5b!J27-E5b!I27) -> 0.7 | ... AL27: =(E5b!M27-Z27-(E5b!L27-Y27))/(E5b!M27-E5b!L27) -> 0.925
A28: 2050 | B28: 0 | C28: 0 | D28: 0.15 | E28: 0.2 | F28: 0.25 | G28: 0.3 | H28: 0.4 | I28: 0.5 | J28: 0.6 | K28: 0.7 | L28: 0.8 | M28: 0.9 | O28: =(1-B28)*E5b!B28 -> 3 | P28: =(1-C28)*E5b!C28 -> 4 | Q28: =(1-D28)*E5b!D28 -> 5.1 | R28: =(1-E28)*E5b!E28 -> 6.4 | S28: =(1-F28)*E5b!F28 -> 9 | T28: =(1-G28)*E5b!G28 -> 14 | U28: =(1-H28)*E5b!H28 -> 30 | V28: =(1-I28)*E5b!I28 -> 50 | ... Z28: =(1-M28)*E5b!M28 -> 500 | AA28: 1 | AB28: =(E5b!C28-P28-(E5b!B28-O28))/(E5b!C28-E5b!B28) -> 0 | AC28: =(E5b!D28-Q28-(E5b!C28-P28))/(E5b!D28-E5b!C28) -> 0.45 | AD28: =(E5b!E28-R28-(E5b!D28-Q28))/(E5b!E28-E5b!D28) -> 0.35 | AE28: =(E5b!F28-S28-(E5b!E28-R28))/(E5b!F28-E5b!E28) -> 0.35 | AF28: =(E5b!G28-T28-(E5b!F28-S28))/(E5b!G28-E5b!F28) -> 0.375 | AG28: =(E5b!H28-U28-(E5b!G28-T28))/(E5b!H28-E5b!G28) -> 0.46666667 | AH28: =(E5b!I28-V28-(E5b!H28-U28))/(E5b!I28-E5b!H28) -> 0.6 | AI28: =(E5b!J28-W28-(E5b!I28-V28))/(E5b!J28-E5b!I28) -> 0.7 | ... AL28: =(E5b!M28-Z28-(E5b!L28-Y28))/(E5b!M28-E5b!L28) -> 0.925
A29: 2051 | B29: =B28+(B$48-B$28)/20 -> 0 | C29: =C28+(C$48-C$28)/20 -> 0 | D29: =D28+(D$48-D$28)/20 -> 0.15 | E29: =E28+(E$48-E$28)/20 -> 0.2025 | F29: =F28+(F$48-F$28)/20 -> 0.2525 | G29: =G28+(G$48-G$28)/20 -> 0.305 | H29: =H28+(H$48-H$28)/20 -> 0.405 | I29: =I28+(I$48-I$28)/20 -> 0.505 | ... M29: =M28+(M$48-M$28)/20 -> 0.9 | O29: =(1-B29)*E5b!B29 -> 3 | P29: =(1-C29)*E5b!C29 -> 4 | Q29: =(1-D29)*E5b!D29 -> 5.0575 | R29: =(1-E29)*E5b!E29 -> 6.340125 | S29: =(1-F29)*E5b!F29 -> 8.89525 | T29: =(1-G29)*E5b!G29 -> 13.9 | U29: =(1-H29)*E5b!H29 -> 29.75 | V29: =(1-I29)*E5b!I29 -> 49.5 | ... Z29: =(1-M29)*E5b!M29 -> 500 | AA29: 1 | AB29: =(E5b!C29-P29-(E5b!B29-O29))/(E5b!C29-E5b!B29) -> 0 | AC29: =(E5b!D29-Q29-(E5b!C29-P29))/(E5b!D29-E5b!C29) -> 0.45769231 | AD29: =(E5b!E29-R29-(E5b!D29-Q29))/(E5b!E29-E5b!D29) -> 0.3586875 | AE29: =(E5b!F29-S29-(E5b!E29-R29))/(E5b!F29-E5b!E29) -> 0.35313291 | AF29: =(E5b!G29-T29-(E5b!F29-S29))/(E5b!G29-E5b!F29) -> 0.38212963 | AG29: =(E5b!H29-U29-(E5b!G29-T29))/(E5b!H29-E5b!G29) -> 0.47166667 | AH29: =(E5b!I29-V29-(E5b!H29-U29))/(E5b!I29-E5b!H29) -> 0.605 | AI29: =(E5b!J29-W29-(E5b!I29-V29))/(E5b!J29-E5b!I29) -> 0.705 | ... AL29: =(E5b!M29-Z29-(E5b!L29-Y29))/(E5b!M29-E5b!L29) -> 0.925
A30: 2052 | B30: =B29+(B$48-B$28)/20 -> 0 | C30: =C29+(C$48-C$28)/20 -> 0 | D30: =D29+(D$48-D$28)/20 -> 0.15 | E30: =E29+(E$48-E$28)/20 -> 0.205 | F30: =F29+(F$48-F$28)/20 -> 0.255 | G30: =G29+(G$48-G$28)/20 -> 0.31 | H30: =H29+(H$48-H$28)/20 -> 0.41 | I30: =I29+(I$48-I$28)/20 -> 0.51 | ... M30: =M29+(M$48-M$28)/20 -> 0.9 | O30: =(1-B30)*E5b!B30 -> 3 | P30: =(1-C30)*E5b!C30 -> 4 | Q30: =(1-D30)*E5b!D30 -> 5.015 | R30: =(1-E30)*E5b!E30 -> 6.2805 | S30: =(1-F30)*E5b!F30 -> 8.791 | T30: =(1-G30)*E5b!G30 -> 13.8 | U30: =(1-H30)*E5b!H30 -> 29.5 | V30: =(1-I30)*E5b!I30 -> 49 | ... Z30: =(1-M30)*E5b!M30 -> 500 | AA30: 1 | AB30: =(E5b!C30-P30-(E5b!B30-O30))/(E5b!C30-E5b!B30) -> 0 | AC30: =(E5b!D30-Q30-(E5b!C30-P30))/(E5b!D30-E5b!C30) -> 0.46578947 | AD30: =(E5b!E30-R30-(E5b!D30-Q30))/(E5b!E30-E5b!D30) -> 0.36725 | AE30: =(E5b!F30-S30-(E5b!E30-R30))/(E5b!F30-E5b!E30) -> 0.35628205 | AF30: =(E5b!G30-T30-(E5b!F30-S30))/(E5b!G30-E5b!F30) -> 0.38914634 | AG30: =(E5b!H30-U30-(E5b!G30-T30))/(E5b!H30-E5b!G30) -> 0.47666667 | AH30: =(E5b!I30-V30-(E5b!H30-U30))/(E5b!I30-E5b!H30) -> 0.61 | AI30: =(E5b!J30-W30-(E5b!I30-V30))/(E5b!J30-E5b!I30) -> 0.71 | ... AL30: =(E5b!M30-Z30-(E5b!L30-Y30))/(E5b!M30-E5b!L30) -> 0.925
A31: 2053 | B31: =B30+(B$48-B$28)/20 -> 0 | C31: =C30+(C$48-C$28)/20 -> 0 | D31: =D30+(D$48-D$28)/20 -> 0.15 | E31: =E30+(E$48-E$28)/20 -> 0.2075 | F31: =F30+(F$48-F$28)/20 -> 0.2575 | G31: =G30+(G$48-G$28)/20 -> 0.315 | H31: =H30+(H$48-H$28)/20 -> 0.415 | I31: =I30+(I$48-I$28)/20 -> 0.515 | ... M31: =M30+(M$48-M$28)/20 -> 0.9 | O31: =(1-B31)*E5b!B31 -> 3 | P31: =(1-C31)*E5b!C31 -> 4 | Q31: =(1-D31)*E5b!D31 -> 4.9725 | R31: =(1-E31)*E5b!E31 -> 6.221125 | S31: =(1-F31)*E5b!F31 -> 8.68725 | T31: =(1-G31)*E5b!G31 -> 13.7 | U31: =(1-H31)*E5b!H31 -> 29.25 | V31: =(1-I31)*E5b!I31 -> 48.5 | ... Z31: =(1-M31)*E5b!M31 -> 500 | AA31: 1 | AB31: =(E5b!C31-P31-(E5b!B31-O31))/(E5b!C31-E5b!B31) -> 0 | AC31: =(E5b!D31-Q31-(E5b!C31-P31))/(E5b!D31-E5b!C31) -> 0.47432432 | AD31: =(E5b!E31-R31-(E5b!D31-Q31))/(E5b!E31-E5b!D31) -> 0.3756875 | AE31: =(E5b!F31-S31-(E5b!E31-R31))/(E5b!F31-E5b!E31) -> 0.35944805 | AF31: =(E5b!G31-T31-(E5b!F31-S31))/(E5b!G31-E5b!F31) -> 0.39605422 | AG31: =(E5b!H31-U31-(E5b!G31-T31))/(E5b!H31-E5b!G31) -> 0.48166667 | AH31: =(E5b!I31-V31-(E5b!H31-U31))/(E5b!I31-E5b!H31) -> 0.615 | AI31: =(E5b!J31-W31-(E5b!I31-V31))/(E5b!J31-E5b!I31) -> 0.715 | ... AL31: =(E5b!M31-Z31-(E5b!L31-Y31))/(E5b!M31-E5b!L31) -> 0.925
A32: 2054 | B32: =B31+(B$48-B$28)/20 -> 0 | C32: =C31+(C$48-C$28)/20 -> 0 | D32: =D31+(D$48-D$28)/20 -> 0.15 | E32: =E31+(E$48-E$28)/20 -> 0.21 | F32: =F31+(F$48-F$28)/20 -> 0.26 | G32: =G31+(G$48-G$28)/20 -> 0.32 | H32: =H31+(H$48-H$28)/20 -> 0.42 | I32: =I31+(I$48-I$28)/20 -> 0.52 | ... M32: =M31+(M$48-M$28)/20 -> 0.9 | O32: =(1-B32)*E5b!B32 -> 3 | P32: =(1-C32)*E5b!C32 -> 4 | Q32: =(1-D32)*E5b!D32 -> 4.93 | R32: =(1-E32)*E5b!E32 -> 6.162 | S32: =(1-F32)*E5b!F32 -> 8.584 | T32: =(1-G32)*E5b!G32 -> 13.6 | U32: =(1-H32)*E5b!H32 -> 29 | V32: =(1-I32)*E5b!I32 -> 48 | ... Z32: =(1-M32)*E5b!M32 -> 500 | AA32: 1 | AB32: =(E5b!C32-P32-(E5b!B32-O32))/(E5b!C32-E5b!B32) -> 0 | AC32: =(E5b!D32-Q32-(E5b!C32-P32))/(E5b!D32-E5b!C32) -> 0.48333333 | AD32: =(E5b!E32-R32-(E5b!D32-Q32))/(E5b!E32-E5b!D32) -> 0.384 | AE32: =(E5b!F32-S32-(E5b!E32-R32))/(E5b!F32-E5b!E32) -> 0.36263158 | AF32: =(E5b!G32-T32-(E5b!F32-S32))/(E5b!G32-E5b!F32) -> 0.40285714 | AG32: =(E5b!H32-U32-(E5b!G32-T32))/(E5b!H32-E5b!G32) -> 0.48666667 | AH32: =(E5b!I32-V32-(E5b!H32-U32))/(E5b!I32-E5b!H32) -> 0.62 | AI32: =(E5b!J32-W32-(E5b!I32-V32))/(E5b!J32-E5b!I32) -> 0.72 | ... AL32: =(E5b!M32-Z32-(E5b!L32-Y32))/(E5b!M32-E5b!L32) -> 0.925
A33: 2055 | B33: =B32+(B$48-B$28)/20 -> 0 | C33: =C32+(C$48-C$28)/20 -> 0 | D33: =D32+(D$48-D$28)/20 -> 0.15 | E33: =E32+(E$48-E$28)/20 -> 0.2125 | F33: =F32+(F$48-F$28)/20 -> 0.2625 | G33: =G32+(G$48-G$28)/20 -> 0.325 | H33: =H32+(H$48-H$28)/20 -> 0.425 | I33: =I32+(I$48-I$28)/20 -> 0.525 | ... M33: =M32+(M$48-M$28)/20 -> 0.9 | O33: =(1-B33)*E5b!B33 -> 3 | P33: =(1-C33)*E5b!C33 -> 4 | Q33: =(1-D33)*E5b!D33 -> 4.8875 | R33: =(1-E33)*E5b!E33 -> 6.103125 | S33: =(1-F33)*E5b!F33 -> 8.48125 | T33: =(1-G33)*E5b!G33 -> 13.5 | U33: =(1-H33)*E5b!H33 -> 28.75 | V33: =(1-I33)*E5b!I33 -> 47.5 | ... Z33: =(1-M33)*E5b!M33 -> 500 | AA33: 1 | AB33: =(E5b!C33-P33-(E5b!B33-O33))/(E5b!C33-E5b!B33) -> 0 | AC33: =(E5b!D33-Q33-(E5b!C33-P33))/(E5b!D33-E5b!C33) -> 0.49285714 | AD33: =(E5b!E33-R33-(E5b!D33-Q33))/(E5b!E33-E5b!D33) -> 0.3921875 | AE33: =(E5b!F33-S33-(E5b!E33-R33))/(E5b!F33-E5b!E33) -> 0.36583333 | AF33: =(E5b!G33-T33-(E5b!F33-S33))/(E5b!G33-E5b!F33) -> 0.40955882 | AG33: =(E5b!H33-U33-(E5b!G33-T33))/(E5b!H33-E5b!G33) -> 0.49166667 | AH33: =(E5b!I33-V33-(E5b!H33-U33))/(E5b!I33-E5b!H33) -> 0.625 | AI33: =(E5b!J33-W33-(E5b!I33-V33))/(E5b!J33-E5b!I33) -> 0.725 | ... AL33: =(E5b!M33-Z33-(E5b!L33-Y33))/(E5b!M33-E5b!L33) -> 0.925
A34: 2056 | B34: =B33+(B$48-B$28)/20 -> 0 | C34: =C33+(C$48-C$28)/20 -> 0 | D34: =D33+(D$48-D$28)/20 -> 0.15 | E34: =E33+(E$48-E$28)/20 -> 0.215 | F34: =F33+(F$48-F$28)/20 -> 0.265 | G34: =G33+(G$48-G$28)/20 -> 0.33 | H34: =H33+(H$48-H$28)/20 -> 0.43 | I34: =I33+(I$48-I$28)/20 -> 0.53 | ... M34: =M33+(M$48-M$28)/20 -> 0.9 | O34: =(1-B34)*E5b!B34 -> 3 | P34: =(1-C34)*E5b!C34 -> 4 | Q34: =(1-D34)*E5b!D34 -> 4.845 | R34: =(1-E34)*E5b!E34 -> 6.0445 | S34: =(1-F34)*E5b!F34 -> 8.379 | T34: =(1-G34)*E5b!G34 -> 13.4 | U34: =(1-H34)*E5b!H34 -> 28.5 | V34: =(1-I34)*E5b!I34 -> 47 | ... Z34: =(1-M34)*E5b!M34 -> 500 | AA34: 1 | AB34: =(E5b!C34-P34-(E5b!B34-O34))/(E5b!C34-E5b!B34) -> 0 | AC34: =(E5b!D34-Q34-(E5b!C34-P34))/(E5b!D34-E5b!C34) -> 0.50294118 | AD34: =(E5b!E34-R34-(E5b!D34-Q34))/(E5b!E34-E5b!D34) -> 0.40025 | AE34: =(E5b!F34-S34-(E5b!E34-R34))/(E5b!F34-E5b!E34) -> 0.36905405 | AF34: =(E5b!G34-T34-(E5b!F34-S34))/(E5b!G34-E5b!F34) -> 0.41616279 | AG34: =(E5b!H34-U34-(E5b!G34-T34))/(E5b!H34-E5b!G34) -> 0.49666667 | AH34: =(E5b!I34-V34-(E5b!H34-U34))/(E5b!I34-E5b!H34) -> 0.63 | AI34: =(E5b!J34-W34-(E5b!I34-V34))/(E5b!J34-E5b!I34) -> 0.73 | ... AL34: =(E5b!M34-Z34-(E5b!L34-Y34))/(E5b!M34-E5b!L34) -> 0.925
A35: 2057 | B35: =B34+(B$48-B$28)/20 -> 0 | C35: =C34+(C$48-C$28)/20 -> 0 | D35: =D34+(D$48-D$28)/20 -> 0.15 | E35: =E34+(E$48-E$28)/20 -> 0.2175 | F35: =F34+(F$48-F$28)/20 -> 0.2675 | G35: =G34+(G$48-G$28)/20 -> 0.335 | H35: =H34+(H$48-H$28)/20 -> 0.435 | I35: =I34+(I$48-I$28)/20 -> 0.535 | ... M35: =M34+(M$48-M$28)/20 -> 0.9 | O35: =(1-B35)*E5b!B35 -> 3 | P35: =(1-C35)*E5b!C35 -> 4 | Q35: =(1-D35)*E5b!D35 -> 4.8025 | R35: =(1-E35)*E5b!E35 -> 5.986125 | S35: =(1-F35)*E5b!F35 -> 8.27725 | T35: =(1-G35)*E5b!G35 -> 13.3 | U35: =(1-H35)*E5b!H35 -> 28.25 | V35: =(1-I35)*E5b!I35 -> 46.5 | ... Z35: =(1-M35)*E5b!M35 -> 500 | AA35: 1 | AB35: =(E5b!C35-P35-(E5b!B35-O35))/(E5b!C35-E5b!B35) -> 0 | AC35: =(E5b!D35-Q35-(E5b!C35-P35))/(E5b!D35-E5b!C35) -> 0.51363636 | AD35: =(E5b!E35-R35-(E5b!D35-Q35))/(E5b!E35-E5b!D35) -> 0.4081875 | AE35: =(E5b!F35-S35-(E5b!E35-R35))/(E5b!F35-E5b!E35) -> 0.37229452 | AF35: =(E5b!G35-T35-(E5b!F35-S35))/(E5b!G35-E5b!F35) -> 0.42267241 | AG35: =(E5b!H35-U35-(E5b!G35-T35))/(E5b!H35-E5b!G35) -> 0.50166667 | AH35: =(E5b!I35-V35-(E5b!H35-U35))/(E5b!I35-E5b!H35) -> 0.635 | AI35: =(E5b!J35-W35-(E5b!I35-V35))/(E5b!J35-E5b!I35) -> 0.735 | ... AL35: =(E5b!M35-Z35-(E5b!L35-Y35))/(E5b!M35-E5b!L35) -> 0.925
A36: 2058 | B36: =B35+(B$48-B$28)/20 -> 0 | C36: =C35+(C$48-C$28)/20 -> 0 | D36: =D35+(D$48-D$28)/20 -> 0.15 | E36: =E35+(E$48-E$28)/20 -> 0.22 | F36: =F35+(F$48-F$28)/20 -> 0.27 | G36: =G35+(G$48-G$28)/20 -> 0.34 | H36: =H35+(H$48-H$28)/20 -> 0.44 | I36: =I35+(I$48-I$28)/20 -> 0.54 | ... M36: =M35+(M$48-M$28)/20 -> 0.9 | O36: =(1-B36)*E5b!B36 -> 3 | P36: =(1-C36)*E5b!C36 -> 4 | Q36: =(1-D36)*E5b!D36 -> 4.76 | R36: =(1-E36)*E5b!E36 -> 5.928 | S36: =(1-F36)*E5b!F36 -> 8.176 | T36: =(1-G36)*E5b!G36 -> 13.2 | U36: =(1-H36)*E5b!H36 -> 28 | V36: =(1-I36)*E5b!I36 -> 46 | ... Z36: =(1-M36)*E5b!M36 -> 500 | AA36: 1 | AB36: =(E5b!C36-P36-(E5b!B36-O36))/(E5b!C36-E5b!B36) -> 0 | AC36: =(E5b!D36-Q36-(E5b!C36-P36))/(E5b!D36-E5b!C36) -> 0.525 | AD36: =(E5b!E36-R36-(E5b!D36-Q36))/(E5b!E36-E5b!D36) -> 0.416 | AE36: =(E5b!F36-S36-(E5b!E36-R36))/(E5b!F36-E5b!E36) -> 0.37555556 | AF36: =(E5b!G36-T36-(E5b!F36-S36))/(E5b!G36-E5b!F36) -> 0.42909091 | AG36: =(E5b!H36-U36-(E5b!G36-T36))/(E5b!H36-E5b!G36) -> 0.50666667 | AH36: =(E5b!I36-V36-(E5b!H36-U36))/(E5b!I36-E5b!H36) -> 0.64 | AI36: =(E5b!J36-W36-(E5b!I36-V36))/(E5b!J36-E5b!I36) -> 0.74 | ... AL36: =(E5b!M36-Z36-(E5b!L36-Y36))/(E5b!M36-E5b!L36) -> 0.925
A37: 2059 | B37: =B36+(B$48-B$28)/20 -> 0 | C37: =C36+(C$48-C$28)/20 -> 0 | D37: =D36+(D$48-D$28)/20 -> 0.15 | E37: =E36+(E$48-E$28)/20 -> 0.2225 | F37: =F36+(F$48-F$28)/20 -> 0.2725 | G37: =G36+(G$48-G$28)/20 -> 0.345 | H37: =H36+(H$48-H$28)/20 -> 0.445 | I37: =I36+(I$48-I$28)/20 -> 0.545 | ... M37: =M36+(M$48-M$28)/20 -> 0.9 | O37: =(1-B37)*E5b!B37 -> 3 | P37: =(1-C37)*E5b!C37 -> 4 | Q37: =(1-D37)*E5b!D37 -> 4.7175 | R37: =(1-E37)*E5b!E37 -> 5.870125 | S37: =(1-F37)*E5b!F37 -> 8.07525 | T37: =(1-G37)*E5b!G37 -> 13.1 | U37: =(1-H37)*E5b!H37 -> 27.75 | V37: =(1-I37)*E5b!I37 -> 45.5 | ... Z37: =(1-M37)*E5b!M37 -> 500 | AA37: 1 | AB37: =(E5b!C37-P37-(E5b!B37-O37))/(E5b!C37-E5b!B37) -> 0 | AC37: =(E5b!D37-Q37-(E5b!C37-P37))/(E5b!D37-E5b!C37) -> 0.53709677 | AD37: =(E5b!E37-R37-(E5b!D37-Q37))/(E5b!E37-E5b!D37) -> 0.4236875 | AE37: =(E5b!F37-S37-(E5b!E37-R37))/(E5b!F37-E5b!E37) -> 0.37883803 | AF37: =(E5b!G37-T37-(E5b!F37-S37))/(E5b!G37-E5b!F37) -> 0.43542135 | AG37: =(E5b!H37-U37-(E5b!G37-T37))/(E5b!H37-E5b!G37) -> 0.51166667 | AH37: =(E5b!I37-V37-(E5b!H37-U37))/(E5b!I37-E5b!H37) -> 0.645 | AI37: =(E5b!J37-W37-(E5b!I37-V37))/(E5b!J37-E5b!I37) -> 0.745 | ... AL37: =(E5b!M37-Z37-(E5b!L37-Y37))/(E5b!M37-E5b!L37) -> 0.925
A38: 2060 | B38: =B37+(B$48-B$28)/20 -> 0 | C38: =C37+(C$48-C$28)/20 -> 0 | D38: =D37+(D$48-D$28)/20 -> 0.15 | E38: =E37+(E$48-E$28)/20 -> 0.225 | F38: =F37+(F$48-F$28)/20 -> 0.275 | G38: =G37+(G$48-G$28)/20 -> 0.35 | H38: =H37+(H$48-H$28)/20 -> 0.45 | I38: =I37+(I$48-I$28)/20 -> 0.55 | ... M38: =M37+(M$48-M$28)/20 -> 0.9 | O38: =(1-B38)*E5b!B38 -> 3 | P38: =(1-C38)*E5b!C38 -> 4 | Q38: =(1-D38)*E5b!D38 -> 4.675 | R38: =(1-E38)*E5b!E38 -> 5.8125 | S38: =(1-F38)*E5b!F38 -> 7.975 | T38: =(1-G38)*E5b!G38 -> 13 | U38: =(1-H38)*E5b!H38 -> 27.5 | V38: =(1-I38)*E5b!I38 -> 45 | ... Z38: =(1-M38)*E5b!M38 -> 500 | AA38: 1 | AB38: =(E5b!C38-P38-(E5b!B38-O38))/(E5b!C38-E5b!B38) -> 0 | AC38: =(E5b!D38-Q38-(E5b!C38-P38))/(E5b!D38-E5b!C38) -> 0.55 | AD38: =(E5b!E38-R38-(E5b!D38-Q38))/(E5b!E38-E5b!D38) -> 0.43125 | AE38: =(E5b!F38-S38-(E5b!E38-R38))/(E5b!F38-E5b!E38) -> 0.38214286 | AF38: =(E5b!G38-T38-(E5b!F38-S38))/(E5b!G38-E5b!F38) -> 0.44166667 | AG38: =(E5b!H38-U38-(E5b!G38-T38))/(E5b!H38-E5b!G38) -> 0.51666667 | AH38: =(E5b!I38-V38-(E5b!H38-U38))/(E5b!I38-E5b!H38) -> 0.65 | AI38: =(E5b!J38-W38-(E5b!I38-V38))/(E5b!J38-E5b!I38) -> 0.75 | ... AL38: =(E5b!M38-Z38-(E5b!L38-Y38))/(E5b!M38-E5b!L38) -> 0.925
A39: 2061 | B39: =B38+(B$48-B$28)/20 -> 0 | C39: =C38+(C$48-C$28)/20 -> 0 | D39: =D38+(D$48-D$28)/20 -> 0.15 | E39: =E38+(E$48-E$28)/20 -> 0.2275 | F39: =F38+(F$48-F$28)/20 -> 0.2775 | G39: =G38+(G$48-G$28)/20 -> 0.355 | H39: =H38+(H$48-H$28)/20 -> 0.455 | I39: =I38+(I$48-I$28)/20 -> 0.555 | ... M39: =M38+(M$48-M$28)/20 -> 0.9 | O39: =(1-B39)*E5b!B39 -> 3 | P39: =(1-C39)*E5b!C39 -> 4 | Q39: =(1-D39)*E5b!D39 -> 4.6325 | R39: =(1-E39)*E5b!E39 -> 5.755125 | S39: =(1-F39)*E5b!F39 -> 7.87525 | T39: =(1-G39)*E5b!G39 -> 12.9 | U39: =(1-H39)*E5b!H39 -> 27.25 | V39: =(1-I39)*E5b!I39 -> 44.5 | ... Z39: =(1-M39)*E5b!M39 -> 500 | AA39: 1 | AB39: =(E5b!C39-P39-(E5b!B39-O39))/(E5b!C39-E5b!B39) -> 0 | AC39: =(E5b!D39-Q39-(E5b!C39-P39))/(E5b!D39-E5b!C39) -> 0.5637931 | AD39: =(E5b!E39-R39-(E5b!D39-Q39))/(E5b!E39-E5b!D39) -> 0.4386875 | AE39: =(E5b!F39-S39-(E5b!E39-R39))/(E5b!F39-E5b!E39) -> 0.38547101 | AF39: =(E5b!G39-T39-(E5b!F39-S39))/(E5b!G39-E5b!F39) -> 0.44782967 | AG39: =(E5b!H39-U39-(E5b!G39-T39))/(E5b!H39-E5b!G39) -> 0.52166667 | AH39: =(E5b!I39-V39-(E5b!H39-U39))/(E5b!I39-E5b!H39) -> 0.655 | AI39: =(E5b!J39-W39-(E5b!I39-V39))/(E5b!J39-E5b!I39) -> 0.755 | ... AL39: =(E5b!M39-Z39-(E5b!L39-Y39))/(E5b!M39-E5b!L39) -> 0.925
A40: 2062 | B40: =B39+(B$48-B$28)/20 -> 0 | C40: =C39+(C$48-C$28)/20 -> 0 | D40: =D39+(D$48-D$28)/20 -> 0.15 | E40: =E39+(E$48-E$28)/20 -> 0.23 | F40: =F39+(F$48-F$28)/20 -> 0.28 | G40: =G39+(G$48-G$28)/20 -> 0.36 | H40: =H39+(H$48-H$28)/20 -> 0.46 | I40: =I39+(I$48-I$28)/20 -> 0.56 | ... M40: =M39+(M$48-M$28)/20 -> 0.9 | O40: =(1-B40)*E5b!B40 -> 3 | P40: =(1-C40)*E5b!C40 -> 4 | Q40: =(1-D40)*E5b!D40 -> 4.59 | R40: =(1-E40)*E5b!E40 -> 5.698 | S40: =(1-F40)*E5b!F40 -> 7.776 | T40: =(1-G40)*E5b!G40 -> 12.8 | U40: =(1-H40)*E5b!H40 -> 27 | V40: =(1-I40)*E5b!I40 -> 44 | ... Z40: =(1-M40)*E5b!M40 -> 500 | AA40: 1 | AB40: =(E5b!C40-P40-(E5b!B40-O40))/(E5b!C40-E5b!B40) -> 0 | AC40: =(E5b!D40-Q40-(E5b!C40-P40))/(E5b!D40-E5b!C40) -> 0.57857143 | AD40: =(E5b!E40-R40-(E5b!D40-Q40))/(E5b!E40-E5b!D40) -> 0.446 | AE40: =(E5b!F40-S40-(E5b!E40-R40))/(E5b!F40-E5b!E40) -> 0.38882353 | AF40: =(E5b!G40-T40-(E5b!F40-S40))/(E5b!G40-E5b!F40) -> 0.45391304 | AG40: =(E5b!H40-U40-(E5b!G40-T40))/(E5b!H40-E5b!G40) -> 0.52666667 | AH40: =(E5b!I40-V40-(E5b!H40-U40))/(E5b!I40-E5b!H40) -> 0.66 | AI40: =(E5b!J40-W40-(E5b!I40-V40))/(E5b!J40-E5b!I40) -> 0.76 | ... AL40: =(E5b!M40-Z40-(E5b!L40-Y40))/(E5b!M40-E5b!L40) -> 0.925
... A47: 2069 | B47: =B46+(B$48-B$28)/20 -> 0 | C47: =C46+(C$48-C$28)/20 -> 0 | D47: =D46+(D$48-D$28)/20 -> 0.15 | E47: =E46+(E$48-E$28)/20 -> 0.2475 | F47: =F46+(F$48-F$28)/20 -> 0.2975 | G47: =G46+(G$48-G$28)/20 -> 0.395 | H47: =H46+(H$48-H$28)/20 -> 0.495 | I47: =I46+(I$48-I$28)/20 -> 0.595 | ... M47: =M46+(M$48-M$28)/20 -> 0.9 | O47: =(1-B47)*E5b!B47 -> 3 | P47: =(1-C47)*E5b!C47 -> 4 | Q47: =(1-D47)*E5b!D47 -> 4.2925 | R47: =(1-E47)*E5b!E47 -> 5.305125 | S47: =(1-F47)*E5b!F47 -> 7.09525 | T47: =(1-G47)*E5b!G47 -> 12.1 | U47: =(1-H47)*E5b!H47 -> 25.25 | V47: =(1-I47)*E5b!I47 -> 40.5 | ... Z47: =(1-M47)*E5b!M47 -> 500 | AA47: 1 | AB47: =(E5b!C47-P47-(E5b!B47-O47))/(E5b!C47-E5b!B47) -> 0 | AC47: =(E5b!D47-Q47-(E5b!C47-P47))/(E5b!D47-E5b!C47) -> 0.72142857 | AD47: =(E5b!E47-R47-(E5b!D47-Q47))/(E5b!E47-E5b!D47) -> 0.4936875 | AE47: =(E5b!F47-S47-(E5b!E47-R47))/(E5b!F47-E5b!E47) -> 0.41307377 | AF47: =(E5b!G47-T47-(E5b!F47-S47))/(E5b!G47-E5b!F47) -> 0.4944697 | AG47: =(E5b!H47-U47-(E5b!G47-T47))/(E5b!H47-E5b!G47) -> 0.56166667 | AH47: =(E5b!I47-V47-(E5b!H47-U47))/(E5b!I47-E5b!H47) -> 0.695 | AI47: =(E5b!J47-W47-(E5b!I47-V47))/(E5b!J47-E5b!I47) -> 0.795 | ... AL47: =(E5b!M47-Z47-(E5b!L47-Y47))/(E5b!M47-E5b!L47) -> 0.925
A48: 2070 | B48: 0 | C48: 0 | D48: 0.15 | E48: 0.25 | F48: 0.3 | G48: 0.4 | H48: 0.5 | I48: 0.6 | J48: 0.7 | K48: 0.75 | L48: 0.8 | M48: 0.9 | O48: =(1-B48)*E5b!B48 -> 3 | P48: =(1-C48)*E5b!C48 -> 4 | Q48: =(1-D48)*E5b!D48 -> 4.25 | R48: =(1-E48)*E5b!E48 -> 5.25 | S48: =(1-F48)*E5b!F48 -> 7 | T48: =(1-G48)*E5b!G48 -> 12 | U48: =(1-H48)*E5b!H48 -> 25 | V48: =(1-I48)*E5b!I48 -> 40 | ... Z48: =(1-M48)*E5b!M48 -> 500 | AA48: 1 | AB48: =(E5b!C48-P48-(E5b!B48-O48))/(E5b!C48-E5b!B48) -> 0 | AC48: =(E5b!D48-Q48-(E5b!C48-P48))/(E5b!D48-E5b!C48) -> 0.75 | AD48: =(E5b!E48-R48-(E5b!D48-Q48))/(E5b!E48-E5b!D48) -> 0.5 | AE48: =(E5b!F48-S48-(E5b!E48-R48))/(E5b!F48-E5b!E48) -> 0.41666667 | AF48: =(E5b!G48-T48-(E5b!F48-S48))/(E5b!G48-E5b!F48) -> 0.5 | AG48: =(E5b!H48-U48-(E5b!G48-T48))/(E5b!H48-E5b!G48) -> 0.56666667 | AH48: =(E5b!I48-V48-(E5b!H48-U48))/(E5b!I48-E5b!H48) -> 0.7 | AI48: =(E5b!J48-W48-(E5b!I48-V48))/(E5b!J48-E5b!I48) -> 0.8 | ... AL48: =(E5b!M48-Z48-(E5b!L48-Y48))/(E5b!M48-E5b!L48) -> 0.925
A49: 2071 | B49: =B48+(B$58-B$48)/10 -> 0 | C49: =C48+(C$58-C$48)/10 -> 0 | D49: =D48+(D$58-D$48)/10 -> 0.15 | E49: =E48+(E$58-E$48)/10 -> 0.255 | F49: =F48+(F$58-F$48)/10 -> 0.31 | G49: =G48+(G$58-G$48)/10 -> 0.41 | H49: =H48+(H$58-H$48)/10 -> 0.51 | I49: =I48+(I$58-I$48)/10 -> 0.61 | ... M49: =M48+(M$58-M$48)/10 -> 0.9 | O49: =(1-B49)*E5b!B49 -> 3 | P49: =(1-C49)*E5b!C49 -> 4 | Q49: =(1-D49)*E5b!D49 -> 4.25 | R49: =(1-E49)*E5b!E49 -> 5.215 | S49: =(1-F49)*E5b!F49 -> 6.9 | T49: =(1-G49)*E5b!G49 -> 11.8 | U49: =(1-H49)*E5b!H49 -> 24.5 | V49: =(1-I49)*E5b!I49 -> 39 | ... Z49: =(1-M49)*E5b!M49 -> 500 | AA49: 1 | AB49: =(E5b!C49-P49-(E5b!B49-O49))/(E5b!C49-E5b!B49) -> 0 | AC49: =(E5b!D49-Q49-(E5b!C49-P49))/(E5b!D49-E5b!C49) -> 0.75 | AD49: =(E5b!E49-R49-(E5b!D49-Q49))/(E5b!E49-E5b!D49) -> 0.5175 | AE49: =(E5b!F49-S49-(E5b!E49-R49))/(E5b!F49-E5b!E49) -> 0.43833333 | AF49: =(E5b!G49-T49-(E5b!F49-S49))/(E5b!G49-E5b!F49) -> 0.51 | AG49: =(E5b!H49-U49-(E5b!G49-T49))/(E5b!H49-E5b!G49) -> 0.57666667 | AH49: =(E5b!I49-V49-(E5b!H49-U49))/(E5b!I49-E5b!H49) -> 0.71 | AI49: =(E5b!J49-W49-(E5b!I49-V49))/(E5b!J49-E5b!I49) -> 0.8 | ... AL49: =(E5b!M49-Z49-(E5b!L49-Y49))/(E5b!M49-E5b!L49) -> 0.92375
A50: 2072 | B50: =B49+(B$58-B$48)/10 -> 0 | C50: =C49+(C$58-C$48)/10 -> 0 | D50: =D49+(D$58-D$48)/10 -> 0.15 | E50: =E49+(E$58-E$48)/10 -> 0.26 | F50: =F49+(F$58-F$48)/10 -> 0.32 | G50: =G49+(G$58-G$48)/10 -> 0.42 | H50: =H49+(H$58-H$48)/10 -> 0.52 | I50: =I49+(I$58-I$48)/10 -> 0.62 | ... M50: =M49+(M$58-M$48)/10 -> 0.9 | O50: =(1-B50)*E5b!B50 -> 3 | P50: =(1-C50)*E5b!C50 -> 4 | Q50: =(1-D50)*E5b!D50 -> 4.25 | R50: =(1-E50)*E5b!E50 -> 5.18 | S50: =(1-F50)*E5b!F50 -> 6.8 | T50: =(1-G50)*E5b!G50 -> 11.6 | U50: =(1-H50)*E5b!H50 -> 24 | V50: =(1-I50)*E5b!I50 -> 38 | ... Z50: =(1-M50)*E5b!M50 -> 500 | AA50: 1 | AB50: =(E5b!C50-P50-(E5b!B50-O50))/(E5b!C50-E5b!B50) -> 0 | AC50: =(E5b!D50-Q50-(E5b!C50-P50))/(E5b!D50-E5b!C50) -> 0.75 | AD50: =(E5b!E50-R50-(E5b!D50-Q50))/(E5b!E50-E5b!D50) -> 0.535 | AE50: =(E5b!F50-S50-(E5b!E50-R50))/(E5b!F50-E5b!E50) -> 0.46 | AF50: =(E5b!G50-T50-(E5b!F50-S50))/(E5b!G50-E5b!F50) -> 0.52 | AG50: =(E5b!H50-U50-(E5b!G50-T50))/(E5b!H50-E5b!G50) -> 0.58666667 | AH50: =(E5b!I50-V50-(E5b!H50-U50))/(E5b!I50-E5b!H50) -> 0.72 | AI50: =(E5b!J50-W50-(E5b!I50-V50))/(E5b!J50-E5b!I50) -> 0.8 | ... AL50: =(E5b!M50-Z50-(E5b!L50-Y50))/(E5b!M50-E5b!L50) -> 0.9225
A51: 2073 | B51: =B50+(B$58-B$48)/10 -> 0 | C51: =C50+(C$58-C$48)/10 -> 0 | D51: =D50+(D$58-D$48)/10 -> 0.15 | E51: =E50+(E$58-E$48)/10 -> 0.265 | F51: =F50+(F$58-F$48)/10 -> 0.33 | G51: =G50+(G$58-G$48)/10 -> 0.43 | H51: =H50+(H$58-H$48)/10 -> 0.53 | I51: =I50+(I$58-I$48)/10 -> 0.63 | ... M51: =M50+(M$58-M$48)/10 -> 0.9 | O51: =(1-B51)*E5b!B51 -> 3 | P51: =(1-C51)*E5b!C51 -> 4 | Q51: =(1-D51)*E5b!D51 -> 4.25 | R51: =(1-E51)*E5b!E51 -> 5.145 | S51: =(1-F51)*E5b!F51 -> 6.7 | T51: =(1-G51)*E5b!G51 -> 11.4 | U51: =(1-H51)*E5b!H51 -> 23.5 | V51: =(1-I51)*E5b!I51 -> 37 | ... Z51: =(1-M51)*E5b!M51 -> 500 | AA51: 1 | AB51: =(E5b!C51-P51-(E5b!B51-O51))/(E5b!C51-E5b!B51) -> 0 | AC51: =(E5b!D51-Q51-(E5b!C51-P51))/(E5b!D51-E5b!C51) -> 0.75 | AD51: =(E5b!E51-R51-(E5b!D51-Q51))/(E5b!E51-E5b!D51) -> 0.5525 | AE51: =(E5b!F51-S51-(E5b!E51-R51))/(E5b!F51-E5b!E51) -> 0.48166667 | AF51: =(E5b!G51-T51-(E5b!F51-S51))/(E5b!G51-E5b!F51) -> 0.53 | AG51: =(E5b!H51-U51-(E5b!G51-T51))/(E5b!H51-E5b!G51) -> 0.59666667 | AH51: =(E5b!I51-V51-(E5b!H51-U51))/(E5b!I51-E5b!H51) -> 0.73 | AI51: =(E5b!J51-W51-(E5b!I51-V51))/(E5b!J51-E5b!I51) -> 0.8 | ... AL51: =(E5b!M51-Z51-(E5b!L51-Y51))/(E5b!M51-E5b!L51) -> 0.92125
A52: 2074 | B52: =B51+(B$58-B$48)/10 -> 0 | C52: =C51+(C$58-C$48)/10 -> 0 | D52: =D51+(D$58-D$48)/10 -> 0.15 | E52: =E51+(E$58-E$48)/10 -> 0.27 | F52: =F51+(F$58-F$48)/10 -> 0.34 | G52: =G51+(G$58-G$48)/10 -> 0.44 | H52: =H51+(H$58-H$48)/10 -> 0.54 | I52: =I51+(I$58-I$48)/10 -> 0.64 | ... M52: =M51+(M$58-M$48)/10 -> 0.9 | O52: =(1-B52)*E5b!B52 -> 3 | P52: =(1-C52)*E5b!C52 -> 4 | Q52: =(1-D52)*E5b!D52 -> 4.25 | R52: =(1-E52)*E5b!E52 -> 5.11 | S52: =(1-F52)*E5b!F52 -> 6.6 | T52: =(1-G52)*E5b!G52 -> 11.2 | U52: =(1-H52)*E5b!H52 -> 23 | V52: =(1-I52)*E5b!I52 -> 36 | ... Z52: =(1-M52)*E5b!M52 -> 500 | AA52: 1 | AB52: =(E5b!C52-P52-(E5b!B52-O52))/(E5b!C52-E5b!B52) -> 0 | AC52: =(E5b!D52-Q52-(E5b!C52-P52))/(E5b!D52-E5b!C52) -> 0.75 | AD52: =(E5b!E52-R52-(E5b!D52-Q52))/(E5b!E52-E5b!D52) -> 0.57 | AE52: =(E5b!F52-S52-(E5b!E52-R52))/(E5b!F52-E5b!E52) -> 0.50333333 | AF52: =(E5b!G52-T52-(E5b!F52-S52))/(E5b!G52-E5b!F52) -> 0.54 | AG52: =(E5b!H52-U52-(E5b!G52-T52))/(E5b!H52-E5b!G52) -> 0.60666667 | AH52: =(E5b!I52-V52-(E5b!H52-U52))/(E5b!I52-E5b!H52) -> 0.74 | AI52: =(E5b!J52-W52-(E5b!I52-V52))/(E5b!J52-E5b!I52) -> 0.8 | ... AL52: =(E5b!M52-Z52-(E5b!L52-Y52))/(E5b!M52-E5b!L52) -> 0.92
A53: 2075 | B53: =B52+(B$58-B$48)/10 -> 0 | C53: =C52+(C$58-C$48)/10 -> 0 | D53: =D52+(D$58-D$48)/10 -> 0.15 | E53: =E52+(E$58-E$48)/10 -> 0.275 | F53: =F52+(F$58-F$48)/10 -> 0.35 | G53: =G52+(G$58-G$48)/10 -> 0.45 | H53: =H52+(H$58-H$48)/10 -> 0.55 | I53: =I52+(I$58-I$48)/10 -> 0.65 | ... M53: =M52+(M$58-M$48)/10 -> 0.9 | O53: =(1-B53)*E5b!B53 -> 3 | P53: =(1-C53)*E5b!C53 -> 4 | Q53: =(1-D53)*E5b!D53 -> 4.25 | R53: =(1-E53)*E5b!E53 -> 5.075 | S53: =(1-F53)*E5b!F53 -> 6.5 | T53: =(1-G53)*E5b!G53 -> 11 | U53: =(1-H53)*E5b!H53 -> 22.5 | V53: =(1-I53)*E5b!I53 -> 35 | ... Z53: =(1-M53)*E5b!M53 -> 500 | AA53: 1 | AB53: =(E5b!C53-P53-(E5b!B53-O53))/(E5b!C53-E5b!B53) -> 0 | AC53: =(E5b!D53-Q53-(E5b!C53-P53))/(E5b!D53-E5b!C53) -> 0.75 | AD53: =(E5b!E53-R53-(E5b!D53-Q53))/(E5b!E53-E5b!D53) -> 0.5875 | AE53: =(E5b!F53-S53-(E5b!E53-R53))/(E5b!F53-E5b!E53) -> 0.525 | AF53: =(E5b!G53-T53-(E5b!F53-S53))/(E5b!G53-E5b!F53) -> 0.55 | AG53: =(E5b!H53-U53-(E5b!G53-T53))/(E5b!H53-E5b!G53) -> 0.61666667 | AH53: =(E5b!I53-V53-(E5b!H53-U53))/(E5b!I53-E5b!H53) -> 0.75 | AI53: =(E5b!J53-W53-(E5b!I53-V53))/(E5b!J53-E5b!I53) -> 0.8 | ... AL53: =(E5b!M53-Z53-(E5b!L53-Y53))/(E5b!M53-E5b!L53) -> 0.91875
A54: 2076 | B54: =B53+(B$58-B$48)/10 -> 0 | C54: =C53+(C$58-C$48)/10 -> 0 | D54: =D53+(D$58-D$48)/10 -> 0.15 | E54: =E53+(E$58-E$48)/10 -> 0.28 | F54: =F53+(F$58-F$48)/10 -> 0.36 | G54: =G53+(G$58-G$48)/10 -> 0.46 | H54: =H53+(H$58-H$48)/10 -> 0.56 | I54: =I53+(I$58-I$48)/10 -> 0.66 | ... M54: =M53+(M$58-M$48)/10 -> 0.9 | O54: =(1-B54)*E5b!B54 -> 3 | P54: =(1-C54)*E5b!C54 -> 4 | Q54: =(1-D54)*E5b!D54 -> 4.25 | R54: =(1-E54)*E5b!E54 -> 5.04 | S54: =(1-F54)*E5b!F54 -> 6.4 | T54: =(1-G54)*E5b!G54 -> 10.8 | U54: =(1-H54)*E5b!H54 -> 22 | V54: =(1-I54)*E5b!I54 -> 34 | ... Z54: =(1-M54)*E5b!M54 -> 500 | AA54: 1 | AB54: =(E5b!C54-P54-(E5b!B54-O54))/(E5b!C54-E5b!B54) -> 0 | AC54: =(E5b!D54-Q54-(E5b!C54-P54))/(E5b!D54-E5b!C54) -> 0.75 | AD54: =(E5b!E54-R54-(E5b!D54-Q54))/(E5b!E54-E5b!D54) -> 0.605 | AE54: =(E5b!F54-S54-(E5b!E54-R54))/(E5b!F54-E5b!E54) -> 0.54666667 | AF54: =(E5b!G54-T54-(E5b!F54-S54))/(E5b!G54-E5b!F54) -> 0.56 | AG54: =(E5b!H54-U54-(E5b!G54-T54))/(E5b!H54-E5b!G54) -> 0.62666667 | AH54: =(E5b!I54-V54-(E5b!H54-U54))/(E5b!I54-E5b!H54) -> 0.76 | AI54: =(E5b!J54-W54-(E5b!I54-V54))/(E5b!J54-E5b!I54) -> 0.8 | ... AL54: =(E5b!M54-Z54-(E5b!L54-Y54))/(E5b!M54-E5b!L54) -> 0.9175
A55: 2077 | B55: =B54+(B$58-B$48)/10 -> 0 | C55: =C54+(C$58-C$48)/10 -> 0 | D55: =D54+(D$58-D$48)/10 -> 0.15 | E55: =E54+(E$58-E$48)/10 -> 0.285 | F55: =F54+(F$58-F$48)/10 -> 0.37 | G55: =G54+(G$58-G$48)/10 -> 0.47 | H55: =H54+(H$58-H$48)/10 -> 0.57 | I55: =I54+(I$58-I$48)/10 -> 0.67 | ... M55: =M54+(M$58-M$48)/10 -> 0.9 | O55: =(1-B55)*E5b!B55 -> 3 | P55: =(1-C55)*E5b!C55 -> 4 | Q55: =(1-D55)*E5b!D55 -> 4.25 | R55: =(1-E55)*E5b!E55 -> 5.005 | S55: =(1-F55)*E5b!F55 -> 6.3 | T55: =(1-G55)*E5b!G55 -> 10.6 | U55: =(1-H55)*E5b!H55 -> 21.5 | V55: =(1-I55)*E5b!I55 -> 33 | ... Z55: =(1-M55)*E5b!M55 -> 500 | AA55: 2 | AB55: =(E5b!C55-P55-(E5b!B55-O55))/(E5b!C55-E5b!B55) -> 0 | AC55: =(E5b!D55-Q55-(E5b!C55-P55))/(E5b!D55-E5b!C55) -> 0.75 | AD55: =(E5b!E55-R55-(E5b!D55-Q55))/(E5b!E55-E5b!D55) -> 0.6225 | AE55: =(E5b!F55-S55-(E5b!E55-R55))/(E5b!F55-E5b!E55) -> 0.56833333 | AF55: =(E5b!G55-T55-(E5b!F55-S55))/(E5b!G55-E5b!F55) -> 0.57 | AG55: =(E5b!H55-U55-(E5b!G55-T55))/(E5b!H55-E5b!G55) -> 0.63666667 | AH55: =(E5b!I55-V55-(E5b!H55-U55))/(E5b!I55-E5b!H55) -> 0.77 | AI55: =(E5b!J55-W55-(E5b!I55-V55))/(E5b!J55-E5b!I55) -> 0.8 | ... AL55: =(E5b!M55-Z55-(E5b!L55-Y55))/(E5b!M55-E5b!L55) -> 0.91625
A56: 2078 | B56: =B55+(B$58-B$48)/10 -> 0 | C56: =C55+(C$58-C$48)/10 -> 0 | D56: =D55+(D$58-D$48)/10 -> 0.15 | E56: =E55+(E$58-E$48)/10 -> 0.29 | F56: =F55+(F$58-F$48)/10 -> 0.38 | G56: =G55+(G$58-G$48)/10 -> 0.48 | H56: =H55+(H$58-H$48)/10 -> 0.58 | I56: =I55+(I$58-I$48)/10 -> 0.68 | ... M56: =M55+(M$58-M$48)/10 -> 0.9 | O56: =(1-B56)*E5b!B56 -> 3 | P56: =(1-C56)*E5b!C56 -> 4 | Q56: =(1-D56)*E5b!D56 -> 4.25 | R56: =(1-E56)*E5b!E56 -> 4.97 | S56: =(1-F56)*E5b!F56 -> 6.2 | T56: =(1-G56)*E5b!G56 -> 10.4 | U56: =(1-H56)*E5b!H56 -> 21 | V56: =(1-I56)*E5b!I56 -> 32 | ... Z56: =(1-M56)*E5b!M56 -> 500 | AA56: 2 | AB56: =(E5b!C56-P56-(E5b!B56-O56))/(E5b!C56-E5b!B56) -> 0 | AC56: =(E5b!D56-Q56-(E5b!C56-P56))/(E5b!D56-E5b!C56) -> 0.75 | AD56: =(E5b!E56-R56-(E5b!D56-Q56))/(E5b!E56-E5b!D56) -> 0.64 | AE56: =(E5b!F56-S56-(E5b!E56-R56))/(E5b!F56-E5b!E56) -> 0.59 | AF56: =(E5b!G56-T56-(E5b!F56-S56))/(E5b!G56-E5b!F56) -> 0.58 | AG56: =(E5b!H56-U56-(E5b!G56-T56))/(E5b!H56-E5b!G56) -> 0.64666667 | AH56: =(E5b!I56-V56-(E5b!H56-U56))/(E5b!I56-E5b!H56) -> 0.78 | AI56: =(E5b!J56-W56-(E5b!I56-V56))/(E5b!J56-E5b!I56) -> 0.8 | ... AL56: =(E5b!M56-Z56-(E5b!L56-Y56))/(E5b!M56-E5b!L56) -> 0.915
A57: 2079 | B57: =B56+(B$58-B$48)/10 -> 0 | C57: =C56+(C$58-C$48)/10 -> 0 | D57: =D56+(D$58-D$48)/10 -> 0.15 | E57: =E56+(E$58-E$48)/10 -> 0.295 | F57: =F56+(F$58-F$48)/10 -> 0.39 | G57: =G56+(G$58-G$48)/10 -> 0.49 | H57: =H56+(H$58-H$48)/10 -> 0.59 | I57: =I56+(I$58-I$48)/10 -> 0.69 | ... M57: =M56+(M$58-M$48)/10 -> 0.9 | O57: =(1-B57)*E5b!B57 -> 3 | P57: =(1-C57)*E5b!C57 -> 4 | Q57: =(1-D57)*E5b!D57 -> 4.25 | R57: =(1-E57)*E5b!E57 -> 4.935 | S57: =(1-F57)*E5b!F57 -> 6.1 | T57: =(1-G57)*E5b!G57 -> 10.2 | U57: =(1-H57)*E5b!H57 -> 20.5 | V57: =(1-I57)*E5b!I57 -> 31 | ... Z57: =(1-M57)*E5b!M57 -> 500 | AA57: 2 | AB57: =(E5b!C57-P57-(E5b!B57-O57))/(E5b!C57-E5b!B57) -> 0 | AC57: =(E5b!D57-Q57-(E5b!C57-P57))/(E5b!D57-E5b!C57) -> 0.75 | AD57: =(E5b!E57-R57-(E5b!D57-Q57))/(E5b!E57-E5b!D57) -> 0.6575 | AE57: =(E5b!F57-S57-(E5b!E57-R57))/(E5b!F57-E5b!E57) -> 0.61166667 | AF57: =(E5b!G57-T57-(E5b!F57-S57))/(E5b!G57-E5b!F57) -> 0.59 | AG57: =(E5b!H57-U57-(E5b!G57-T57))/(E5b!H57-E5b!G57) -> 0.65666667 | AH57: =(E5b!I57-V57-(E5b!H57-U57))/(E5b!I57-E5b!H57) -> 0.79 | AI57: =(E5b!J57-W57-(E5b!I57-V57))/(E5b!J57-E5b!I57) -> 0.8 | ... AL57: =(E5b!M57-Z57-(E5b!L57-Y57))/(E5b!M57-E5b!L57) -> 0.91375
A58: 2080 | B58: 0 | C58: 0 | D58: 0.15 | E58: 0.3 | F58: 0.4 | G58: 0.5 | H58: 0.6 | I58: 0.7 | J58: 0.75 | K58: 0.8 | L58: 0.85 | M58: 0.9 | O58: =(1-B58)*E5b!B58 -> 3 | P58: =(1-C58)*E5b!C58 -> 4 | Q58: =(1-D58)*E5b!D58 -> 4.25 | R58: =(1-E58)*E5b!E58 -> 4.9 | S58: =(1-F58)*E5b!F58 -> 6 | T58: =(1-G58)*E5b!G58 -> 10 | U58: =(1-H58)*E5b!H58 -> 20 | V58: =(1-I58)*E5b!I58 -> 30 | ... Z58: =(1-M58)*E5b!M58 -> 500 | AA58: 2 | AB58: =(E5b!C58-P58-(E5b!B58-O58))/(E5b!C58-E5b!B58) -> 0 | AC58: =(E5b!D58-Q58-(E5b!C58-P58))/(E5b!D58-E5b!C58) -> 0.75 | AD58: =(E5b!E58-R58-(E5b!D58-Q58))/(E5b!E58-E5b!D58) -> 0.675 | AE58: =(E5b!F58-S58-(E5b!E58-R58))/(E5b!F58-E5b!E58) -> 0.63333333 | AF58: =(E5b!G58-T58-(E5b!F58-S58))/(E5b!G58-E5b!F58) -> 0.6 | AG58: =(E5b!H58-U58-(E5b!G58-T58))/(E5b!H58-E5b!G58) -> 0.66666667 | AH58: =(E5b!I58-V58-(E5b!H58-U58))/(E5b!I58-E5b!H58) -> 0.8 | AI58: =(E5b!J58-W58-(E5b!I58-V58))/(E5b!J58-E5b!I58) -> 0.8 | ... AL58: =(E5b!M58-Z58-(E5b!L58-Y58))/(E5b!M58-E5b!L58) -> 0.9125
A59: 2081 | B59: =B58+(B$78-B$58)/20 -> 0 | C59: =C58+(C$78-C$58)/20 -> 0 | D59: =D58+(D$78-D$58)/20 -> 0.15 | E59: =E58+(E$78-E$58)/20 -> 0.3 | F59: =F58+(F$78-F$58)/20 -> 0.4 | G59: =G58+(G$78-G$58)/20 -> 0.5 | H59: =H58+(H$78-H$58)/20 -> 0.6 | I59: =I58+(I$78-I$58)/20 -> 0.7 | ... M59: =M58+(M$78-M$58)/20 -> 0.9 | O59: =(1-B59)*E5b!B59 -> 3 | P59: =(1-C59)*E5b!C59 -> 4 | Q59: =(1-D59)*E5b!D59 -> 4.25 | R59: =(1-E59)*E5b!E59 -> 4.9 | S59: =(1-F59)*E5b!F59 -> 6 | T59: =(1-G59)*E5b!G59 -> 10 | U59: =(1-H59)*E5b!H59 -> 20 | V59: =(1-I59)*E5b!I59 -> 30 | ... Z59: =(1-M59)*E5b!M59 -> 500 | AA59: 2 | AB59: =(E5b!C59-P59-(E5b!B59-O59))/(E5b!C59-E5b!B59) -> 0 | AC59: =(E5b!D59-Q59-(E5b!C59-P59))/(E5b!D59-E5b!C59) -> 0.75 | AD59: =(E5b!E59-R59-(E5b!D59-Q59))/(E5b!E59-E5b!D59) -> 0.675 | AE59: =(E5b!F59-S59-(E5b!E59-R59))/(E5b!F59-E5b!E59) -> 0.63333333 | AF59: =(E5b!G59-T59-(E5b!F59-S59))/(E5b!G59-E5b!F59) -> 0.6 | AG59: =(E5b!H59-U59-(E5b!G59-T59))/(E5b!H59-E5b!G59) -> 0.66666667 | AH59: =(E5b!I59-V59-(E5b!H59-U59))/(E5b!I59-E5b!H59) -> 0.8 | AI59: =(E5b!J59-W59-(E5b!I59-V59))/(E5b!J59-E5b!I59) -> 0.8 | ... AL59: =(E5b!M59-Z59-(E5b!L59-Y59))/(E5b!M59-E5b!L59) -> 0.9125
A60: 2082 | B60: =B59+(B$78-B$58)/20 -> 0 | C60: =C59+(C$78-C$58)/20 -> 0 | D60: =D59+(D$78-D$58)/20 -> 0.15 | E60: =E59+(E$78-E$58)/20 -> 0.3 | F60: =F59+(F$78-F$58)/20 -> 0.4 | G60: =G59+(G$78-G$58)/20 -> 0.5 | H60: =H59+(H$78-H$58)/20 -> 0.6 | I60: =I59+(I$78-I$58)/20 -> 0.7 | ... M60: =M59+(M$78-M$58)/20 -> 0.9 | O60: =(1-B60)*E5b!B60 -> 3 | P60: =(1-C60)*E5b!C60 -> 4 | Q60: =(1-D60)*E5b!D60 -> 4.25 | R60: =(1-E60)*E5b!E60 -> 4.9 | S60: =(1-F60)*E5b!F60 -> 6 | T60: =(1-G60)*E5b!G60 -> 10 | U60: =(1-H60)*E5b!H60 -> 20 | V60: =(1-I60)*E5b!I60 -> 30 | ... Z60: =(1-M60)*E5b!M60 -> 500 | AA60: 2 | AB60: =(E5b!C60-P60-(E5b!B60-O60))/(E5b!C60-E5b!B60) -> 0 | AC60: =(E5b!D60-Q60-(E5b!C60-P60))/(E5b!D60-E5b!C60) -> 0.75 | AD60: =(E5b!E60-R60-(E5b!D60-Q60))/(E5b!E60-E5b!D60) -> 0.675 | AE60: =(E5b!F60-S60-(E5b!E60-R60))/(E5b!F60-E5b!E60) -> 0.63333333 | AF60: =(E5b!G60-T60-(E5b!F60-S60))/(E5b!G60-E5b!F60) -> 0.6 | AG60: =(E5b!H60-U60-(E5b!G60-T60))/(E5b!H60-E5b!G60) -> 0.66666667 | AH60: =(E5b!I60-V60-(E5b!H60-U60))/(E5b!I60-E5b!H60) -> 0.8 | AI60: =(E5b!J60-W60-(E5b!I60-V60))/(E5b!J60-E5b!I60) -> 0.8 | ... AL60: =(E5b!M60-Z60-(E5b!L60-Y60))/(E5b!M60-E5b!L60) -> 0.9125
A61: 2083 | B61: =B60+(B$78-B$58)/20 -> 0 | C61: =C60+(C$78-C$58)/20 -> 0 | D61: =D60+(D$78-D$58)/20 -> 0.15 | E61: =E60+(E$78-E$58)/20 -> 0.3 | F61: =F60+(F$78-F$58)/20 -> 0.4 | G61: =G60+(G$78-G$58)/20 -> 0.5 | H61: =H60+(H$78-H$58)/20 -> 0.6 | I61: =I60+(I$78-I$58)/20 -> 0.7 | ... M61: =M60+(M$78-M$58)/20 -> 0.9 | O61: =(1-B61)*E5b!B61 -> 3 | P61: =(1-C61)*E5b!C61 -> 4 | Q61: =(1-D61)*E5b!D61 -> 4.25 | R61: =(1-E61)*E5b!E61 -> 4.9 | S61: =(1-F61)*E5b!F61 -> 6 | T61: =(1-G61)*E5b!G61 -> 10 | U61: =(1-H61)*E5b!H61 -> 20 | V61: =(1-I61)*E5b!I61 -> 30 | ... Z61: =(1-M61)*E5b!M61 -> 500 | AA61: 2 | AB61: =(E5b!C61-P61-(E5b!B61-O61))/(E5b!C61-E5b!B61) -> 0 | AC61: =(E5b!D61-Q61-(E5b!C61-P61))/(E5b!D61-E5b!C61) -> 0.75 | AD61: =(E5b!E61-R61-(E5b!D61-Q61))/(E5b!E61-E5b!D61) -> 0.675 | AE61: =(E5b!F61-S61-(E5b!E61-R61))/(E5b!F61-E5b!E61) -> 0.63333333 | AF61: =(E5b!G61-T61-(E5b!F61-S61))/(E5b!G61-E5b!F61) -> 0.6 | AG61: =(E5b!H61-U61-(E5b!G61-T61))/(E5b!H61-E5b!G61) -> 0.66666667 | AH61: =(E5b!I61-V61-(E5b!H61-U61))/(E5b!I61-E5b!H61) -> 0.8 | AI61: =(E5b!J61-W61-(E5b!I61-V61))/(E5b!J61-E5b!I61) -> 0.8 | ... AL61: =(E5b!M61-Z61-(E5b!L61-Y61))/(E5b!M61-E5b!L61) -> 0.9125
A62: 2084 | B62: =B61+(B$78-B$58)/20 -> 0 | C62: =C61+(C$78-C$58)/20 -> 0 | D62: =D61+(D$78-D$58)/20 -> 0.15 | E62: =E61+(E$78-E$58)/20 -> 0.3 | F62: =F61+(F$78-F$58)/20 -> 0.4 | G62: =G61+(G$78-G$58)/20 -> 0.5 | H62: =H61+(H$78-H$58)/20 -> 0.6 | I62: =I61+(I$78-I$58)/20 -> 0.7 | ... M62: =M61+(M$78-M$58)/20 -> 0.9 | O62: =(1-B62)*E5b!B62 -> 3 | P62: =(1-C62)*E5b!C62 -> 4 | Q62: =(1-D62)*E5b!D62 -> 4.25 | R62: =(1-E62)*E5b!E62 -> 4.9 | S62: =(1-F62)*E5b!F62 -> 6 | T62: =(1-G62)*E5b!G62 -> 10 | U62: =(1-H62)*E5b!H62 -> 20 | V62: =(1-I62)*E5b!I62 -> 30 | ... Z62: =(1-M62)*E5b!M62 -> 500 | AA62: 2 | AB62: =(E5b!C62-P62-(E5b!B62-O62))/(E5b!C62-E5b!B62) -> 0 | AC62: =(E5b!D62-Q62-(E5b!C62-P62))/(E5b!D62-E5b!C62) -> 0.75 | AD62: =(E5b!E62-R62-(E5b!D62-Q62))/(E5b!E62-E5b!D62) -> 0.675 | AE62: =(E5b!F62-S62-(E5b!E62-R62))/(E5b!F62-E5b!E62) -> 0.63333333 | AF62: =(E5b!G62-T62-(E5b!F62-S62))/(E5b!G62-E5b!F62) -> 0.6 | AG62: =(E5b!H62-U62-(E5b!G62-T62))/(E5b!H62-E5b!G62) -> 0.66666667 | AH62: =(E5b!I62-V62-(E5b!H62-U62))/(E5b!I62-E5b!H62) -> 0.8 | AI62: =(E5b!J62-W62-(E5b!I62-V62))/(E5b!J62-E5b!I62) -> 0.8 | ... AL62: =(E5b!M62-Z62-(E5b!L62-Y62))/(E5b!M62-E5b!L62) -> 0.9125
A63: 2085 | B63: =B62+(B$78-B$58)/20 -> 0 | C63: =C62+(C$78-C$58)/20 -> 0 | D63: =D62+(D$78-D$58)/20 -> 0.15 | E63: =E62+(E$78-E$58)/20 -> 0.3 | F63: =F62+(F$78-F$58)/20 -> 0.4 | G63: =G62+(G$78-G$58)/20 -> 0.5 | H63: =H62+(H$78-H$58)/20 -> 0.6 | I63: =I62+(I$78-I$58)/20 -> 0.7 | ... M63: =M62+(M$78-M$58)/20 -> 0.9 | O63: =(1-B63)*E5b!B63 -> 3 | P63: =(1-C63)*E5b!C63 -> 4 | Q63: =(1-D63)*E5b!D63 -> 4.25 | R63: =(1-E63)*E5b!E63 -> 4.9 | S63: =(1-F63)*E5b!F63 -> 6 | T63: =(1-G63)*E5b!G63 -> 10 | U63: =(1-H63)*E5b!H63 -> 20 | V63: =(1-I63)*E5b!I63 -> 30 | ... Z63: =(1-M63)*E5b!M63 -> 500 | AA63: 2 | AB63: =(E5b!C63-P63-(E5b!B63-O63))/(E5b!C63-E5b!B63) -> 0 | AC63: =(E5b!D63-Q63-(E5b!C63-P63))/(E5b!D63-E5b!C63) -> 0.75 | AD63: =(E5b!E63-R63-(E5b!D63-Q63))/(E5b!E63-E5b!D63) -> 0.675 | AE63: =(E5b!F63-S63-(E5b!E63-R63))/(E5b!F63-E5b!E63) -> 0.63333333 | AF63: =(E5b!G63-T63-(E5b!F63-S63))/(E5b!G63-E5b!F63) -> 0.6 | AG63: =(E5b!H63-U63-(E5b!G63-T63))/(E5b!H63-E5b!G63) -> 0.66666667 | AH63: =(E5b!I63-V63-(E5b!H63-U63))/(E5b!I63-E5b!H63) -> 0.8 | AI63: =(E5b!J63-W63-(E5b!I63-V63))/(E5b!J63-E5b!I63) -> 0.8 | ... AL63: =(E5b!M63-Z63-(E5b!L63-Y63))/(E5b!M63-E5b!L63) -> 0.9125
A64: 2086 | B64: =B63+(B$78-B$58)/20 -> 0 | C64: =C63+(C$78-C$58)/20 -> 0 | D64: =D63+(D$78-D$58)/20 -> 0.15 | E64: =E63+(E$78-E$58)/20 -> 0.3 | F64: =F63+(F$78-F$58)/20 -> 0.4 | G64: =G63+(G$78-G$58)/20 -> 0.5 | H64: =H63+(H$78-H$58)/20 -> 0.6 | I64: =I63+(I$78-I$58)/20 -> 0.7 | ... M64: =M63+(M$78-M$58)/20 -> 0.9 | O64: =(1-B64)*E5b!B64 -> 3 | P64: =(1-C64)*E5b!C64 -> 4 | Q64: =(1-D64)*E5b!D64 -> 4.25 | R64: =(1-E64)*E5b!E64 -> 4.9 | S64: =(1-F64)*E5b!F64 -> 6 | T64: =(1-G64)*E5b!G64 -> 10 | U64: =(1-H64)*E5b!H64 -> 20 | V64: =(1-I64)*E5b!I64 -> 30 | ... Z64: =(1-M64)*E5b!M64 -> 500 | AA64: 2 | AB64: =(E5b!C64-P64-(E5b!B64-O64))/(E5b!C64-E5b!B64) -> 0 | AC64: =(E5b!D64-Q64-(E5b!C64-P64))/(E5b!D64-E5b!C64) -> 0.75 | AD64: =(E5b!E64-R64-(E5b!D64-Q64))/(E5b!E64-E5b!D64) -> 0.675 | AE64: =(E5b!F64-S64-(E5b!E64-R64))/(E5b!F64-E5b!E64) -> 0.63333333 | AF64: =(E5b!G64-T64-(E5b!F64-S64))/(E5b!G64-E5b!F64) -> 0.6 | AG64: =(E5b!H64-U64-(E5b!G64-T64))/(E5b!H64-E5b!G64) -> 0.66666667 | AH64: =(E5b!I64-V64-(E5b!H64-U64))/(E5b!I64-E5b!H64) -> 0.8 | AI64: =(E5b!J64-W64-(E5b!I64-V64))/(E5b!J64-E5b!I64) -> 0.8 | ... AL64: =(E5b!M64-Z64-(E5b!L64-Y64))/(E5b!M64-E5b!L64) -> 0.9125
A65: 2087 | B65: =B64+(B$78-B$58)/20 -> 0 | C65: =C64+(C$78-C$58)/20 -> 0 | D65: =D64+(D$78-D$58)/20 -> 0.15 | E65: =E64+(E$78-E$58)/20 -> 0.3 | F65: =F64+(F$78-F$58)/20 -> 0.4 | G65: =G64+(G$78-G$58)/20 -> 0.5 | H65: =H64+(H$78-H$58)/20 -> 0.6 | I65: =I64+(I$78-I$58)/20 -> 0.7 | ... M65: =M64+(M$78-M$58)/20 -> 0.9 | O65: =(1-B65)*E5b!B65 -> 3 | P65: =(1-C65)*E5b!C65 -> 4 | Q65: =(1-D65)*E5b!D65 -> 4.25 | R65: =(1-E65)*E5b!E65 -> 4.9 | S65: =(1-F65)*E5b!F65 -> 6 | T65: =(1-G65)*E5b!G65 -> 10 | U65: =(1-H65)*E5b!H65 -> 20 | V65: =(1-I65)*E5b!I65 -> 30 | ... Z65: =(1-M65)*E5b!M65 -> 500 | AA65: 2 | AB65: =(E5b!C65-P65-(E5b!B65-O65))/(E5b!C65-E5b!B65) -> 0 | AC65: =(E5b!D65-Q65-(E5b!C65-P65))/(E5b!D65-E5b!C65) -> 0.75 | AD65: =(E5b!E65-R65-(E5b!D65-Q65))/(E5b!E65-E5b!D65) -> 0.675 | AE65: =(E5b!F65-S65-(E5b!E65-R65))/(E5b!F65-E5b!E65) -> 0.63333333 | AF65: =(E5b!G65-T65-(E5b!F65-S65))/(E5b!G65-E5b!F65) -> 0.6 | AG65: =(E5b!H65-U65-(E5b!G65-T65))/(E5b!H65-E5b!G65) -> 0.66666667 | AH65: =(E5b!I65-V65-(E5b!H65-U65))/(E5b!I65-E5b!H65) -> 0.8 | AI65: =(E5b!J65-W65-(E5b!I65-V65))/(E5b!J65-E5b!I65) -> 0.8 | ... AL65: =(E5b!M65-Z65-(E5b!L65-Y65))/(E5b!M65-E5b!L65) -> 0.9125
A66: 2088 | B66: =B65+(B$78-B$58)/20 -> 0 | C66: =C65+(C$78-C$58)/20 -> 0 | D66: =D65+(D$78-D$58)/20 -> 0.15 | E66: =E65+(E$78-E$58)/20 -> 0.3 | F66: =F65+(F$78-F$58)/20 -> 0.4 | G66: =G65+(G$78-G$58)/20 -> 0.5 | H66: =H65+(H$78-H$58)/20 -> 0.6 | I66: =I65+(I$78-I$58)/20 -> 0.7 | ... M66: =M65+(M$78-M$58)/20 -> 0.9 | O66: =(1-B66)*E5b!B66 -> 3 | P66: =(1-C66)*E5b!C66 -> 4 | Q66: =(1-D66)*E5b!D66 -> 4.25 | R66: =(1-E66)*E5b!E66 -> 4.9 | S66: =(1-F66)*E5b!F66 -> 6 | T66: =(1-G66)*E5b!G66 -> 10 | U66: =(1-H66)*E5b!H66 -> 20 | V66: =(1-I66)*E5b!I66 -> 30 | ... Z66: =(1-M66)*E5b!M66 -> 500 | AA66: 2 | AB66: =(E5b!C66-P66-(E5b!B66-O66))/(E5b!C66-E5b!B66) -> 0 | AC66: =(E5b!D66-Q66-(E5b!C66-P66))/(E5b!D66-E5b!C66) -> 0.75 | AD66: =(E5b!E66-R66-(E5b!D66-Q66))/(E5b!E66-E5b!D66) -> 0.675 | AE66: =(E5b!F66-S66-(E5b!E66-R66))/(E5b!F66-E5b!E66) -> 0.63333333 | AF66: =(E5b!G66-T66-(E5b!F66-S66))/(E5b!G66-E5b!F66) -> 0.6 | AG66: =(E5b!H66-U66-(E5b!G66-T66))/(E5b!H66-E5b!G66) -> 0.66666667 | AH66: =(E5b!I66-V66-(E5b!H66-U66))/(E5b!I66-E5b!H66) -> 0.8 | AI66: =(E5b!J66-W66-(E5b!I66-V66))/(E5b!J66-E5b!I66) -> 0.8 | ... AL66: =(E5b!M66-Z66-(E5b!L66-Y66))/(E5b!M66-E5b!L66) -> 0.9125
A67: 2089 | B67: =B66+(B$78-B$58)/20 -> 0 | C67: =C66+(C$78-C$58)/20 -> 0 | D67: =D66+(D$78-D$58)/20 -> 0.15 | E67: =E66+(E$78-E$58)/20 -> 0.3 | F67: =F66+(F$78-F$58)/20 -> 0.4 | G67: =G66+(G$78-G$58)/20 -> 0.5 | H67: =H66+(H$78-H$58)/20 -> 0.6 | I67: =I66+(I$78-I$58)/20 -> 0.7 | ... M67: =M66+(M$78-M$58)/20 -> 0.9 | O67: =(1-B67)*E5b!B67 -> 3 | P67: =(1-C67)*E5b!C67 -> 4 | Q67: =(1-D67)*E5b!D67 -> 4.25 | R67: =(1-E67)*E5b!E67 -> 4.9 | S67: =(1-F67)*E5b!F67 -> 6 | T67: =(1-G67)*E5b!G67 -> 10 | U67: =(1-H67)*E5b!H67 -> 20 | V67: =(1-I67)*E5b!I67 -> 30 | ... Z67: =(1-M67)*E5b!M67 -> 500 | AA67: 2 | AB67: =(E5b!C67-P67-(E5b!B67-O67))/(E5b!C67-E5b!B67) -> 0 | AC67: =(E5b!D67-Q67-(E5b!C67-P67))/(E5b!D67-E5b!C67) -> 0.75 | AD67: =(E5b!E67-R67-(E5b!D67-Q67))/(E5b!E67-E5b!D67) -> 0.675 | AE67: =(E5b!F67-S67-(E5b!E67-R67))/(E5b!F67-E5b!E67) -> 0.63333333 | AF67: =(E5b!G67-T67-(E5b!F67-S67))/(E5b!G67-E5b!F67) -> 0.6 | AG67: =(E5b!H67-U67-(E5b!G67-T67))/(E5b!H67-E5b!G67) -> 0.66666667 | AH67: =(E5b!I67-V67-(E5b!H67-U67))/(E5b!I67-E5b!H67) -> 0.8 | AI67: =(E5b!J67-W67-(E5b!I67-V67))/(E5b!J67-E5b!I67) -> 0.8 | ... AL67: =(E5b!M67-Z67-(E5b!L67-Y67))/(E5b!M67-E5b!L67) -> 0.9125
A68: 2090 | B68: =B67+(B$78-B$58)/20 -> 0 | C68: =C67+(C$78-C$58)/20 -> 0 | D68: =D67+(D$78-D$58)/20 -> 0.15 | E68: =E67+(E$78-E$58)/20 -> 0.3 | F68: =F67+(F$78-F$58)/20 -> 0.4 | G68: =G67+(G$78-G$58)/20 -> 0.5 | H68: =H67+(H$78-H$58)/20 -> 0.6 | I68: =I67+(I$78-I$58)/20 -> 0.7 | ... M68: =M67+(M$78-M$58)/20 -> 0.9 | O68: =(1-B68)*E5b!B68 -> 3 | P68: =(1-C68)*E5b!C68 -> 4 | Q68: =(1-D68)*E5b!D68 -> 4.25 | R68: =(1-E68)*E5b!E68 -> 4.9 | S68: =(1-F68)*E5b!F68 -> 6 | T68: =(1-G68)*E5b!G68 -> 10 | U68: =(1-H68)*E5b!H68 -> 20 | V68: =(1-I68)*E5b!I68 -> 30 | ... Z68: =(1-M68)*E5b!M68 -> 500 | AA68: 2 | AB68: =(E5b!C68-P68-(E5b!B68-O68))/(E5b!C68-E5b!B68) -> 0 | AC68: =(E5b!D68-Q68-(E5b!C68-P68))/(E5b!D68-E5b!C68) -> 0.75 | AD68: =(E5b!E68-R68-(E5b!D68-Q68))/(E5b!E68-E5b!D68) -> 0.675 | AE68: =(E5b!F68-S68-(E5b!E68-R68))/(E5b!F68-E5b!E68) -> 0.63333333 | AF68: =(E5b!G68-T68-(E5b!F68-S68))/(E5b!G68-E5b!F68) -> 0.6 | AG68: =(E5b!H68-U68-(E5b!G68-T68))/(E5b!H68-E5b!G68) -> 0.66666667 | AH68: =(E5b!I68-V68-(E5b!H68-U68))/(E5b!I68-E5b!H68) -> 0.8 | AI68: =(E5b!J68-W68-(E5b!I68-V68))/(E5b!J68-E5b!I68) -> 0.8 | ... AL68: =(E5b!M68-Z68-(E5b!L68-Y68))/(E5b!M68-E5b!L68) -> 0.9125
A69: 2091 | B69: =B68+(B$78-B$58)/20 -> 0 | C69: =C68+(C$78-C$58)/20 -> 0 | D69: =D68+(D$78-D$58)/20 -> 0.15 | E69: =E68+(E$78-E$58)/20 -> 0.3 | F69: =F68+(F$78-F$58)/20 -> 0.4 | G69: =G68+(G$78-G$58)/20 -> 0.5 | H69: =H68+(H$78-H$58)/20 -> 0.6 | I69: =I68+(I$78-I$58)/20 -> 0.7 | ... M69: =M68+(M$78-M$58)/20 -> 0.9 | O69: =(1-B69)*E5b!B69 -> 3 | P69: =(1-C69)*E5b!C69 -> 4 | Q69: =(1-D69)*E5b!D69 -> 4.25 | R69: =(1-E69)*E5b!E69 -> 4.9 | S69: =(1-F69)*E5b!F69 -> 6 | T69: =(1-G69)*E5b!G69 -> 10 | U69: =(1-H69)*E5b!H69 -> 20 | V69: =(1-I69)*E5b!I69 -> 30 | ... Z69: =(1-M69)*E5b!M69 -> 500 | AA69: 2 | AB69: =(E5b!C69-P69-(E5b!B69-O69))/(E5b!C69-E5b!B69) -> 0 | AC69: =(E5b!D69-Q69-(E5b!C69-P69))/(E5b!D69-E5b!C69) -> 0.75 | AD69: =(E5b!E69-R69-(E5b!D69-Q69))/(E5b!E69-E5b!D69) -> 0.675 | AE69: =(E5b!F69-S69-(E5b!E69-R69))/(E5b!F69-E5b!E69) -> 0.63333333 | AF69: =(E5b!G69-T69-(E5b!F69-S69))/(E5b!G69-E5b!F69) -> 0.6 | AG69: =(E5b!H69-U69-(E5b!G69-T69))/(E5b!H69-E5b!G69) -> 0.66666667 | AH69: =(E5b!I69-V69-(E5b!H69-U69))/(E5b!I69-E5b!H69) -> 0.8 | AI69: =(E5b!J69-W69-(E5b!I69-V69))/(E5b!J69-E5b!I69) -> 0.8 | ... AL69: =(E5b!M69-Z69-(E5b!L69-Y69))/(E5b!M69-E5b!L69) -> 0.9125
A70: 2092 | B70: =B69+(B$78-B$58)/20 -> 0 | C70: =C69+(C$78-C$58)/20 -> 0 | D70: =D69+(D$78-D$58)/20 -> 0.15 | E70: =E69+(E$78-E$58)/20 -> 0.3 | F70: =F69+(F$78-F$58)/20 -> 0.4 | G70: =G69+(G$78-G$58)/20 -> 0.5 | H70: =H69+(H$78-H$58)/20 -> 0.6 | I70: =I69+(I$78-I$58)/20 -> 0.7 | ... M70: =M69+(M$78-M$58)/20 -> 0.9 | O70: =(1-B70)*E5b!B70 -> 3 | P70: =(1-C70)*E5b!C70 -> 4 | Q70: =(1-D70)*E5b!D70 -> 4.25 | R70: =(1-E70)*E5b!E70 -> 4.9 | S70: =(1-F70)*E5b!F70 -> 6 | T70: =(1-G70)*E5b!G70 -> 10 | U70: =(1-H70)*E5b!H70 -> 20 | V70: =(1-I70)*E5b!I70 -> 30 | ... Z70: =(1-M70)*E5b!M70 -> 500 | AA70: 2 | AB70: =(E5b!C70-P70-(E5b!B70-O70))/(E5b!C70-E5b!B70) -> 0 | AC70: =(E5b!D70-Q70-(E5b!C70-P70))/(E5b!D70-E5b!C70) -> 0.75 | AD70: =(E5b!E70-R70-(E5b!D70-Q70))/(E5b!E70-E5b!D70) -> 0.675 | AE70: =(E5b!F70-S70-(E5b!E70-R70))/(E5b!F70-E5b!E70) -> 0.63333333 | AF70: =(E5b!G70-T70-(E5b!F70-S70))/(E5b!G70-E5b!F70) -> 0.6 | AG70: =(E5b!H70-U70-(E5b!G70-T70))/(E5b!H70-E5b!G70) -> 0.66666667 | AH70: =(E5b!I70-V70-(E5b!H70-U70))/(E5b!I70-E5b!H70) -> 0.8 | AI70: =(E5b!J70-W70-(E5b!I70-V70))/(E5b!J70-E5b!I70) -> 0.8 | ... AL70: =(E5b!M70-Z70-(E5b!L70-Y70))/(E5b!M70-E5b!L70) -> 0.9125
... A77: 2099 | B77: =B76+(B$78-B$58)/20 -> 0 | C77: =C76+(C$78-C$58)/20 -> 0 | D77: =D76+(D$78-D$58)/20 -> 0.15 | E77: =E76+(E$78-E$58)/20 -> 0.3 | F77: =F76+(F$78-F$58)/20 -> 0.4 | G77: =G76+(G$78-G$58)/20 -> 0.5 | H77: =H76+(H$78-H$58)/20 -> 0.6 | I77: =I76+(I$78-I$58)/20 -> 0.7 | ... M77: =M76+(M$78-M$58)/20 -> 0.9 | O77: =(1-B77)*E5b!B77 -> 3 | P77: =(1-C77)*E5b!C77 -> 4 | Q77: =(1-D77)*E5b!D77 -> 4.25 | R77: =(1-E77)*E5b!E77 -> 4.9 | S77: =(1-F77)*E5b!F77 -> 6 | T77: =(1-G77)*E5b!G77 -> 10 | U77: =(1-H77)*E5b!H77 -> 20 | V77: =(1-I77)*E5b!I77 -> 30 | ... Z77: =(1-M77)*E5b!M77 -> 500 | AA77: 2 | AB77: =(E5b!C77-P77-(E5b!B77-O77))/(E5b!C77-E5b!B77) -> 0 | AC77: =(E5b!D77-Q77-(E5b!C77-P77))/(E5b!D77-E5b!C77) -> 0.75 | AD77: =(E5b!E77-R77-(E5b!D77-Q77))/(E5b!E77-E5b!D77) -> 0.675 | AE77: =(E5b!F77-S77-(E5b!E77-R77))/(E5b!F77-E5b!E77) -> 0.63333333 | AF77: =(E5b!G77-T77-(E5b!F77-S77))/(E5b!G77-E5b!F77) -> 0.6 | AG77: =(E5b!H77-U77-(E5b!G77-T77))/(E5b!H77-E5b!G77) -> 0.66666667 | AH77: =(E5b!I77-V77-(E5b!H77-U77))/(E5b!I77-E5b!H77) -> 0.8 | AI77: =(E5b!J77-W77-(E5b!I77-V77))/(E5b!J77-E5b!I77) -> 0.8 | ... AL77: =(E5b!M77-Z77-(E5b!L77-Y77))/(E5b!M77-E5b!L77) -> 0.9125
A78: 2100 | B78: 0 | C78: 0 | D78: 0.15 | E78: 0.3 | F78: 0.4 | G78: 0.5 | H78: 0.6 | I78: 0.7 | J78: 0.75 | K78: 0.8 | L78: 0.85 | M78: 0.9 | O78: =(1-B78)*E5b!B78 -> 3 | P78: =(1-C78)*E5b!C78 -> 4 | Q78: =(1-D78)*E5b!D78 -> 4.25 | R78: =(1-E78)*E5b!E78 -> 4.9 | S78: =(1-F78)*E5b!F78 -> 6 | T78: =(1-G78)*E5b!G78 -> 10 | U78: =(1-H78)*E5b!H78 -> 20 | V78: =(1-I78)*E5b!I78 -> 30 | ... Z78: =(1-M78)*E5b!M78 -> 500 | AA78: 2 | AB78: =(E5b!C78-P78-(E5b!B78-O78))/(E5b!C78-E5b!B78) -> 0 | AC78: =(E5b!D78-Q78-(E5b!C78-P78))/(E5b!D78-E5b!C78) -> 0.75 | AD78: =(E5b!E78-R78-(E5b!D78-Q78))/(E5b!E78-E5b!D78) -> 0.675 | AE78: =(E5b!F78-S78-(E5b!E78-R78))/(E5b!F78-E5b!E78) -> 0.63333333 | AF78: =(E5b!G78-T78-(E5b!F78-S78))/(E5b!G78-E5b!F78) -> 0.6 | AG78: =(E5b!H78-U78-(E5b!G78-T78))/(E5b!H78-E5b!G78) -> 0.66666667 | AH78: =(E5b!I78-V78-(E5b!H78-U78))/(E5b!I78-E5b!H78) -> 0.8 | AI78: =(E5b!J78-W78-(E5b!I78-V78))/(E5b!J78-E5b!I78) -> 0.8 | ... AL78: =(E5b!M78-Z78-(E5b!L78-Y78))/(E5b!M78-E5b!L78) -> 0.9125

Sheet E4t
A1: Wealth Tax Schedules (Effective Tax Rates): Series for Stata Import | O1: After-tax income | AB1: Marginal tax rates
AA2: Non-monotonic marginal tax rates
A3: year | B3: tw1 | C3: tw2 | D3: tw3 | E3: tw4 | F3: tw5 | G3: tw6 | H3: tw7 | I3: tw8 | J3: tw9 | K3: tw10 | L3: tw11 | M3: tw12
A4: 2026 | B4: =TE4f!$C7 -> 0 | C4: =TE4f!$C8 -> 0 | D4: =TE4f!$C9 -> 0 | E4: =TE4f!$C10 -> 0.002 | F4: =TE4f!$C11 -> 0.005 | G4: =TE4f!$C12 -> 0.01 | H4: =TE4f!$C13 -> 0.03 | I4: =TE4f!$C14 -> 0.05 | J4: =TE4f!$C15 -> 0.08 | K4: =TE4f!$C16 -> 0.1 | L4: =TE4f!$C17 -> 0.15 | M4: =TE4f!$C18 -> 0.2 | O4: =(1-B4)*E4b!B4 -> 5 | P4: =(1-C4)*E4b!C4 -> 8 | Q4: =(1-D4)*E4b!D4 -> 10 | R4: =(1-E4)*E4b!E4 -> 11.976 | S4: =(1-F4)*E4b!F4 -> 14.925 | T4: =(1-G4)*E4b!G4 -> 19.8 | U4: =(1-H4)*E4b!H4 -> 48.5 | V4: =(1-I4)*E4b!I4 -> 95 | ... Z4: =(1-M4)*E4b!M4 -> 4000 | AA4: 0 | AB4: =(E4b!C4-P4-(E4b!B4-O4))/(E4b!C4-E4b!B4) -> 0 | AC4: =(E4b!D4-Q4-(E4b!C4-P4))/(E4b!D4-E4b!C4) -> 0 | AD4: =(E4b!E4-R4-(E4b!D4-Q4))/(E4b!E4-E4b!D4) -> 0.012 | AE4: =(E4b!F4-S4-(E4b!E4-R4))/(E4b!F4-E4b!E4) -> 0.017 | AF4: =(E4b!G4-T4-(E4b!F4-S4))/(E4b!G4-E4b!F4) -> 0.025 | AG4: =(E4b!H4-U4-(E4b!G4-T4))/(E4b!H4-E4b!G4) -> 0.043333333 | AH4: =(E4b!I4-V4-(E4b!H4-U4))/(E4b!I4-E4b!H4) -> 0.07 | AI4: =(E4b!J4-W4-(E4b!I4-V4))/(E4b!J4-E4b!I4) -> 0.11 | ... AM4: =(E4b!N4-AA4-(E4b!M4-Z4))/(E4b!N4-E4b!M4) -> 0.2
A5: 2027 | B5: =B4+(B$13-B$4)/9 -> 0 | C5: =C4+(C$13-C$4)/9 -> 0 | D5: =D4+(D$13-D$4)/9 -> 0 | E5: =E4+(E$13-E$4)/9 -> 0.0028888889 | F5: =F4+(F$13-F$4)/9 -> 0.0066666667 | G5: =G4+(G$13-G$4)/9 -> 0.012222222 | H5: =H4+(H$13-H$4)/9 -> 0.031111111 | I5: =I4+(I$13-I$4)/9 -> 0.051111111 | ... M5: =M4+(M$13-M$4)/9 -> 0.2 | O5: =(1-B5)*E4b!B5 -> 5 | P5: =(1-C5)*E4b!C5 -> 8 | Q5: =(1-D5)*E4b!D5 -> 10 | R5: =(1-E5)*E4b!E5 -> 11.965333 | S5: =(1-F5)*E4b!F5 -> 14.9 | T5: =(1-G5)*E4b!G5 -> 19.755556 | U5: =(1-H5)*E4b!H5 -> 48.444444 | V5: =(1-I5)*E4b!I5 -> 94.888889 | ... Z5: =(1-M5)*E4b!M5 -> 4000 | AA5: 0 | AB5: =(E4b!C5-P5-(E4b!B5-O5))/(E4b!C5-E4b!B5) -> 0 | AC5: =(E4b!D5-Q5-(E4b!C5-P5))/(E4b!D5-E4b!C5) -> 0 | AD5: =(E4b!E5-R5-(E4b!D5-Q5))/(E4b!E5-E4b!D5) -> 0.017333333 | AE5: =(E4b!F5-S5-(E4b!E5-R5))/(E4b!F5-E4b!E5) -> 0.021777778 | AF5: =(E4b!G5-T5-(E4b!F5-S5))/(E4b!G5-E4b!F5) -> 0.028888889 | AG5: =(E4b!H5-U5-(E4b!G5-T5))/(E4b!H5-E4b!G5) -> 0.043703704 | AH5: =(E4b!I5-V5-(E4b!H5-U5))/(E4b!I5-E4b!H5) -> 0.071111111 | AI5: =(E4b!J5-W5-(E4b!I5-V5))/(E4b!J5-E4b!I5) -> 0.11111111 | ... AM5: =(E4b!N5-AA5-(E4b!M5-Z5))/(E4b!N5-E4b!M5) -> 0.2
A6: 2028 | B6: =B5+(B$13-B$4)/9 -> 0 | C6: =C5+(C$13-C$4)/9 -> 0 | D6: =D5+(D$13-D$4)/9 -> 0 | E6: =E5+(E$13-E$4)/9 -> 0.0037777778 | F6: =F5+(F$13-F$4)/9 -> 0.0083333333 | G6: =G5+(G$13-G$4)/9 -> 0.014444444 | H6: =H5+(H$13-H$4)/9 -> 0.032222222 | I6: =I5+(I$13-I$4)/9 -> 0.052222222 | ... M6: =M5+(M$13-M$4)/9 -> 0.2 | O6: =(1-B6)*E4b!B6 -> 5 | P6: =(1-C6)*E4b!C6 -> 8 | Q6: =(1-D6)*E4b!D6 -> 10 | R6: =(1-E6)*E4b!E6 -> 11.954667 | S6: =(1-F6)*E4b!F6 -> 14.875 | T6: =(1-G6)*E4b!G6 -> 19.711111 | U6: =(1-H6)*E4b!H6 -> 48.388889 | V6: =(1-I6)*E4b!I6 -> 94.777778 | ... Z6: =(1-M6)*E4b!M6 -> 4000 | AA6: 0 | AB6: =(E4b!C6-P6-(E4b!B6-O6))/(E4b!C6-E4b!B6) -> 0 | AC6: =(E4b!D6-Q6-(E4b!C6-P6))/(E4b!D6-E4b!C6) -> 0 | AD6: =(E4b!E6-R6-(E4b!D6-Q6))/(E4b!E6-E4b!D6) -> 0.022666667 | AE6: =(E4b!F6-S6-(E4b!E6-R6))/(E4b!F6-E4b!E6) -> 0.026555556 | AF6: =(E4b!G6-T6-(E4b!F6-S6))/(E4b!G6-E4b!F6) -> 0.032777778 | AG6: =(E4b!H6-U6-(E4b!G6-T6))/(E4b!H6-E4b!G6) -> 0.044074074 | AH6: =(E4b!I6-V6-(E4b!H6-U6))/(E4b!I6-E4b!H6) -> 0.072222222 | AI6: =(E4b!J6-W6-(E4b!I6-V6))/(E4b!J6-E4b!I6) -> 0.11222222 | ... AM6: =(E4b!N6-AA6-(E4b!M6-Z6))/(E4b!N6-E4b!M6) -> 0.2
A7: 2029 | B7: =B6+(B$13-B$4)/9 -> 0 | C7: =C6+(C$13-C$4)/9 -> 0 | D7: =D6+(D$13-D$4)/9 -> 0 | E7: =E6+(E$13-E$4)/9 -> 0.0046666667 | F7: =F6+(F$13-F$4)/9 -> 0.01 | G7: =G6+(G$13-G$4)/9 -> 0.016666667 | H7: =H6+(H$13-H$4)/9 -> 0.033333333 | I7: =I6+(I$13-I$4)/9 -> 0.053333333 | ... M7: =M6+(M$13-M$4)/9 -> 0.2 | O7: =(1-B7)*E4b!B7 -> 5 | P7: =(1-C7)*E4b!C7 -> 8 | Q7: =(1-D7)*E4b!D7 -> 10 | R7: =(1-E7)*E4b!E7 -> 11.944 | S7: =(1-F7)*E4b!F7 -> 14.85 | T7: =(1-G7)*E4b!G7 -> 19.666667 | U7: =(1-H7)*E4b!H7 -> 48.333333 | V7: =(1-I7)*E4b!I7 -> 94.666667 | ... Z7: =(1-M7)*E4b!M7 -> 4000 | AA7: 0 | AB7: =(E4b!C7-P7-(E4b!B7-O7))/(E4b!C7-E4b!B7) -> 0 | AC7: =(E4b!D7-Q7-(E4b!C7-P7))/(E4b!D7-E4b!C7) -> 0 | AD7: =(E4b!E7-R7-(E4b!D7-Q7))/(E4b!E7-E4b!D7) -> 0.028 | AE7: =(E4b!F7-S7-(E4b!E7-R7))/(E4b!F7-E4b!E7) -> 0.031333333 | AF7: =(E4b!G7-T7-(E4b!F7-S7))/(E4b!G7-E4b!F7) -> 0.036666667 | AG7: =(E4b!H7-U7-(E4b!G7-T7))/(E4b!H7-E4b!G7) -> 0.044444444 | AH7: =(E4b!I7-V7-(E4b!H7-U7))/(E4b!I7-E4b!H7) -> 0.073333333 | AI7: =(E4b!J7-W7-(E4b!I7-V7))/(E4b!J7-E4b!I7) -> 0.11333333 | ... AM7: =(E4b!N7-AA7-(E4b!M7-Z7))/(E4b!N7-E4b!M7) -> 0.2
A8: 2030 | B8: =B7+(B$13-B$4)/9 -> 0 | C8: =C7+(C$13-C$4)/9 -> 0 | D8: =D7+(D$13-D$4)/9 -> 0 | E8: =E7+(E$13-E$4)/9 -> 0.0055555556 | F8: =F7+(F$13-F$4)/9 -> 0.011666667 | G8: =G7+(G$13-G$4)/9 -> 0.018888889 | H8: =H7+(H$13-H$4)/9 -> 0.034444444 | I8: =I7+(I$13-I$4)/9 -> 0.054444444 | ... M8: =M7+(M$13-M$4)/9 -> 0.2 | O8: =(1-B8)*E4b!B8 -> 5 | P8: =(1-C8)*E4b!C8 -> 8 | Q8: =(1-D8)*E4b!D8 -> 10 | R8: =(1-E8)*E4b!E8 -> 11.933333 | S8: =(1-F8)*E4b!F8 -> 14.825 | T8: =(1-G8)*E4b!G8 -> 19.622222 | U8: =(1-H8)*E4b!H8 -> 48.277778 | V8: =(1-I8)*E4b!I8 -> 94.555556 | ... Z8: =(1-M8)*E4b!M8 -> 4000 | AA8: 0 | AB8: =(E4b!C8-P8-(E4b!B8-O8))/(E4b!C8-E4b!B8) -> 0 | AC8: =(E4b!D8-Q8-(E4b!C8-P8))/(E4b!D8-E4b!C8) -> 0 | AD8: =(E4b!E8-R8-(E4b!D8-Q8))/(E4b!E8-E4b!D8) -> 0.033333333 | AE8: =(E4b!F8-S8-(E4b!E8-R8))/(E4b!F8-E4b!E8) -> 0.036111111 | AF8: =(E4b!G8-T8-(E4b!F8-S8))/(E4b!G8-E4b!F8) -> 0.040555556 | AG8: =(E4b!H8-U8-(E4b!G8-T8))/(E4b!H8-E4b!G8) -> 0.044814815 | AH8: =(E4b!I8-V8-(E4b!H8-U8))/(E4b!I8-E4b!H8) -> 0.074444444 | AI8: =(E4b!J8-W8-(E4b!I8-V8))/(E4b!J8-E4b!I8) -> 0.11444444 | ... AM8: =(E4b!N8-AA8-(E4b!M8-Z8))/(E4b!N8-E4b!M8) -> 0.2
A9: 2031 | B9: =B8+(B$13-B$4)/9 -> 0 | C9: =C8+(C$13-C$4)/9 -> 0 | D9: =D8+(D$13-D$4)/9 -> 0 | E9: =E8+(E$13-E$4)/9 -> 0.0064444444 | F9: =F8+(F$13-F$4)/9 -> 0.013333333 | G9: =G8+(G$13-G$4)/9 -> 0.021111111 | H9: =H8+(H$13-H$4)/9 -> 0.035555556 | I9: =I8+(I$13-I$4)/9 -> 0.055555556 | ... M9: =M8+(M$13-M$4)/9 -> 0.2 | O9: =(1-B9)*E4b!B9 -> 5 | P9: =(1-C9)*E4b!C9 -> 8 | Q9: =(1-D9)*E4b!D9 -> 10 | R9: =(1-E9)*E4b!E9 -> 11.922667 | S9: =(1-F9)*E4b!F9 -> 14.8 | T9: =(1-G9)*E4b!G9 -> 19.577778 | U9: =(1-H9)*E4b!H9 -> 48.222222 | V9: =(1-I9)*E4b!I9 -> 94.444444 | ... Z9: =(1-M9)*E4b!M9 -> 4000 | AA9: 0 | AB9: =(E4b!C9-P9-(E4b!B9-O9))/(E4b!C9-E4b!B9) -> 0 | AC9: =(E4b!D9-Q9-(E4b!C9-P9))/(E4b!D9-E4b!C9) -> 0 | AD9: =(E4b!E9-R9-(E4b!D9-Q9))/(E4b!E9-E4b!D9) -> 0.038666667 | AE9: =(E4b!F9-S9-(E4b!E9-R9))/(E4b!F9-E4b!E9) -> 0.040888889 | AF9: =(E4b!G9-T9-(E4b!F9-S9))/(E4b!G9-E4b!F9) -> 0.044444444 | AG9: =(E4b!H9-U9-(E4b!G9-T9))/(E4b!H9-E4b!G9) -> 0.045185185 | AH9: =(E4b!I9-V9-(E4b!H9-U9))/(E4b!I9-E4b!H9) -> 0.075555556 | AI9: =(E4b!J9-W9-(E4b!I9-V9))/(E4b!J9-E4b!I9) -> 0.11555556 | ... AM9: =(E4b!N9-AA9-(E4b!M9-Z9))/(E4b!N9-E4b!M9) -> 0.2
A10: 2032 | B10: =B9+(B$13-B$4)/9 -> 0 | C10: =C9+(C$13-C$4)/9 -> 0 | D10: =D9+(D$13-D$4)/9 -> 0 | E10: =E9+(E$13-E$4)/9 -> 0.0073333333 | F10: =F9+(F$13-F$4)/9 -> 0.015 | G10: =G9+(G$13-G$4)/9 -> 0.023333333 | H10: =H9+(H$13-H$4)/9 -> 0.036666667 | I10: =I9+(I$13-I$4)/9 -> 0.056666667 | ... M10: =M9+(M$13-M$4)/9 -> 0.2 | O10: =(1-B10)*E4b!B10 -> 5 | P10: =(1-C10)*E4b!C10 -> 8 | Q10: =(1-D10)*E4b!D10 -> 10 | R10: =(1-E10)*E4b!E10 -> 11.912 | S10: =(1-F10)*E4b!F10 -> 14.775 | T10: =(1-G10)*E4b!G10 -> 19.533333 | U10: =(1-H10)*E4b!H10 -> 48.166667 | V10: =(1-I10)*E4b!I10 -> 94.333333 | ... Z10: =(1-M10)*E4b!M10 -> 4000 | AA10: 0 | AB10: =(E4b!C10-P10-(E4b!B10-O10))/(E4b!C10-E4b!B10) -> 0 | AC10: =(E4b!D10-Q10-(E4b!C10-P10))/(E4b!D10-E4b!C10) -> 0 | AD10: =(E4b!E10-R10-(E4b!D10-Q10))/(E4b!E10-E4b!D10) -> 0.044 | AE10: =(E4b!F10-S10-(E4b!E10-R10))/(E4b!F10-E4b!E10) -> 0.045666667 | AF10: =(E4b!G10-T10-(E4b!F10-S10))/(E4b!G10-E4b!F10) -> 0.048333333 | AG10: =(E4b!H10-U10-(E4b!G10-T10))/(E4b!H10-E4b!G10) -> 0.045555556 | AH10: =(E4b!I10-V10-(E4b!H10-U10))/(E4b!I10-E4b!H10) -> 0.076666667 | AI10: =(E4b!J10-W10-(E4b!I10-V10))/(E4b!J10-E4b!I10) -> 0.11666667 | ... AM10: =(E4b!N10-AA10-(E4b!M10-Z10))/(E4b!N10-E4b!M10) -> 0.2
A11: 2033 | B11: =B10+(B$13-B$4)/9 -> 0 | C11: =C10+(C$13-C$4)/9 -> 0 | D11: =D10+(D$13-D$4)/9 -> 0 | E11: =E10+(E$13-E$4)/9 -> 0.0082222222 | F11: =F10+(F$13-F$4)/9 -> 0.016666667 | G11: =G10+(G$13-G$4)/9 -> 0.025555556 | H11: =H10+(H$13-H$4)/9 -> 0.037777778 | I11: =I10+(I$13-I$4)/9 -> 0.057777778 | ... M11: =M10+(M$13-M$4)/9 -> 0.2 | O11: =(1-B11)*E4b!B11 -> 5 | P11: =(1-C11)*E4b!C11 -> 8 | Q11: =(1-D11)*E4b!D11 -> 10 | R11: =(1-E11)*E4b!E11 -> 11.901333 | S11: =(1-F11)*E4b!F11 -> 14.75 | T11: =(1-G11)*E4b!G11 -> 19.488889 | U11: =(1-H11)*E4b!H11 -> 48.111111 | V11: =(1-I11)*E4b!I11 -> 94.222222 | ... Z11: =(1-M11)*E4b!M11 -> 4000 | AA11: 1 | AB11: =(E4b!C11-P11-(E4b!B11-O11))/(E4b!C11-E4b!B11) -> 0 | AC11: =(E4b!D11-Q11-(E4b!C11-P11))/(E4b!D11-E4b!C11) -> 0 | AD11: =(E4b!E11-R11-(E4b!D11-Q11))/(E4b!E11-E4b!D11) -> 0.049333333 | AE11: =(E4b!F11-S11-(E4b!E11-R11))/(E4b!F11-E4b!E11) -> 0.050444444 | AF11: =(E4b!G11-T11-(E4b!F11-S11))/(E4b!G11-E4b!F11) -> 0.052222222 | AG11: =(E4b!H11-U11-(E4b!G11-T11))/(E4b!H11-E4b!G11) -> 0.045925926 | AH11: =(E4b!I11-V11-(E4b!H11-U11))/(E4b!I11-E4b!H11) -> 0.077777778 | AI11: =(E4b!J11-W11-(E4b!I11-V11))/(E4b!J11-E4b!I11) -> 0.11777778 | ... AM11: =(E4b!N11-AA11-(E4b!M11-Z11))/(E4b!N11-E4b!M11) -> 0.2002
A12: 2034 | B12: =B11+(B$13-B$4)/9 -> 0 | C12: =C11+(C$13-C$4)/9 -> 0 | D12: =D11+(D$13-D$4)/9 -> 0 | E12: =E11+(E$13-E$4)/9 -> 0.0091111111 | F12: =F11+(F$13-F$4)/9 -> 0.018333333 | G12: =G11+(G$13-G$4)/9 -> 0.027777778 | H12: =H11+(H$13-H$4)/9 -> 0.038888889 | I12: =I11+(I$13-I$4)/9 -> 0.058888889 | ... M12: =M11+(M$13-M$4)/9 -> 0.2 | O12: =(1-B12)*E4b!B12 -> 5 | P12: =(1-C12)*E4b!C12 -> 8 | Q12: =(1-D12)*E4b!D12 -> 10 | R12: =(1-E12)*E4b!E12 -> 11.890667 | S12: =(1-F12)*E4b!F12 -> 14.725 | T12: =(1-G12)*E4b!G12 -> 19.444444 | U12: =(1-H12)*E4b!H12 -> 48.055556 | V12: =(1-I12)*E4b!I12 -> 94.111111 | ... Z12: =(1-M12)*E4b!M12 -> 4000 | AA12: 1 | AB12: =(E4b!C12-P12-(E4b!B12-O12))/(E4b!C12-E4b!B12) -> 0 | AC12: =(E4b!D12-Q12-(E4b!C12-P12))/(E4b!D12-E4b!C12) -> 0 | AD12: =(E4b!E12-R12-(E4b!D12-Q12))/(E4b!E12-E4b!D12) -> 0.054666667 | AE12: =(E4b!F12-S12-(E4b!E12-R12))/(E4b!F12-E4b!E12) -> 0.055222222 | AF12: =(E4b!G12-T12-(E4b!F12-S12))/(E4b!G12-E4b!F12) -> 0.056111111 | AG12: =(E4b!H12-U12-(E4b!G12-T12))/(E4b!H12-E4b!G12) -> 0.046296296 | AH12: =(E4b!I12-V12-(E4b!H12-U12))/(E4b!I12-E4b!H12) -> 0.078888889 | AI12: =(E4b!J12-W12-(E4b!I12-V12))/(E4b!J12-E4b!I12) -> 0.11888889 | ... AM12: =(E4b!N12-AA12-(E4b!M12-Z12))/(E4b!N12-E4b!M12) -> 0.2002
A13: 2035 | B13: 0 | C13: 0 | D13: 0 | E13: 0.01 | F13: 0.02 | G13: 0.03 | H13: 0.04 | I13: 0.06 | J13: 0.09 | K13: 0.1 | L13: 0.15 | M13: 0.2 | O13: =(1-B13)*E4b!B13 -> 5 | P13: =(1-C13)*E4b!C13 -> 8 | Q13: =(1-D13)*E4b!D13 -> 10 | R13: =(1-E13)*E4b!E13 -> 11.88 | S13: =(1-F13)*E4b!F13 -> 14.7 | T13: =(1-G13)*E4b!G13 -> 19.4 | U13: =(1-H13)*E4b!H13 -> 48 | V13: =(1-I13)*E4b!I13 -> 94 | ... Z13: =(1-M13)*E4b!M13 -> 4000 | AA13: 1 | AB13: =(E4b!C13-P13-(E4b!B13-O13))/(E4b!C13-E4b!B13) -> 0 | AC13: =(E4b!D13-Q13-(E4b!C13-P13))/(E4b!D13-E4b!C13) -> 0 | AD13: =(E4b!E13-R13-(E4b!D13-Q13))/(E4b!E13-E4b!D13) -> 0.06 | AE13: =(E4b!F13-S13-(E4b!E13-R13))/(E4b!F13-E4b!E13) -> 0.06 | AF13: =(E4b!G13-T13-(E4b!F13-S13))/(E4b!G13-E4b!F13) -> 0.06 | AG13: =(E4b!H13-U13-(E4b!G13-T13))/(E4b!H13-E4b!G13) -> 0.046666667 | AH13: =(E4b!I13-V13-(E4b!H13-U13))/(E4b!I13-E4b!H13) -> 0.08 | AI13: =(E4b!J13-W13-(E4b!I13-V13))/(E4b!J13-E4b!I13) -> 0.12 | ... AM13: =(E4b!N13-AA13-(E4b!M13-Z13))/(E4b!N13-E4b!M13) -> 0.2002
A14: 2036 | B14: =B13+(B$28-B$13)/15 -> 0 | C14: =C13+(C$28-C$13)/15 -> 0 | D14: =D13+(D$28-D$13)/15 -> 0 | E14: =E13+(E$28-E$13)/15 -> 0.010666667 | F14: =F13+(F$28-F$13)/15 -> 0.020666667 | G14: =G13+(G$28-G$13)/15 -> 0.031333333 | H14: =H13+(H$28-H$13)/15 -> 0.041333333 | I14: =I13+(I$28-I$13)/15 -> 0.061333333 | ... M14: =M13+(M$28-M$13)/15 -> 0.2 | O14: =(1-B14)*E4b!B14 -> 4.9333333 | P14: =(1-C14)*E4b!C14 -> 7.8 | Q14: =(1-D14)*E4b!D14 -> 9.8666667 | R14: =(1-E14)*E4b!E14 -> 11.740089 | S14: =(1-F14)*E4b!F14 -> 14.69 | T14: =(1-G14)*E4b!G14 -> 19.373333 | U14: =(1-H14)*E4b!H14 -> 47.933333 | V14: =(1-I14)*E4b!I14 -> 93.866667 | ... Z14: =(1-M14)*E4b!M14 -> 4000 | AA14: 2 | AB14: =(E4b!C14-P14-(E4b!B14-O14))/(E4b!C14-E4b!B14) -> 0 | AC14: =(E4b!D14-Q14-(E4b!C14-P14))/(E4b!D14-E4b!C14) -> 0 | AD14: =(E4b!E14-R14-(E4b!D14-Q14))/(E4b!E14-E4b!D14) -> 0.063288889 | AE14: =(E4b!F14-S14-(E4b!E14-R14))/(E4b!F14-E4b!E14) -> 0.058539007 | AF14: =(E4b!G14-T14-(E4b!F14-S14))/(E4b!G14-E4b!F14) -> 0.063333333 | AG14: =(E4b!H14-U14-(E4b!G14-T14))/(E4b!H14-E4b!G14) -> 0.048 | AH14: =(E4b!I14-V14-(E4b!H14-U14))/(E4b!I14-E4b!H14) -> 0.081333333 | AI14: =(E4b!J14-W14-(E4b!I14-V14))/(E4b!J14-E4b!I14) -> 0.12 | ... AM14: =(E4b!N14-AA14-(E4b!M14-Z14))/(E4b!N14-E4b!M14) -> 0.2004
A15: 2037 | B15: =B14+(B$28-B$13)/15 -> 0 | C15: =C14+(C$28-C$13)/15 -> 0 | D15: =D14+(D$28-D$13)/15 -> 0 | E15: =E14+(E$28-E$13)/15 -> 0.011333333 | F15: =F14+(F$28-F$13)/15 -> 0.021333333 | G15: =G14+(G$28-G$13)/15 -> 0.032666667 | H15: =H14+(H$28-H$13)/15 -> 0.042666667 | I15: =I14+(I$28-I$13)/15 -> 0.062666667 | ... M15: =M14+(M$28-M$13)/15 -> 0.2 | O15: =(1-B15)*E4b!B15 -> 4.8666667 | P15: =(1-C15)*E4b!C15 -> 7.6 | Q15: =(1-D15)*E4b!D15 -> 9.7333333 | R15: =(1-E15)*E4b!E15 -> 11.600356 | S15: =(1-F15)*E4b!F15 -> 14.68 | T15: =(1-G15)*E4b!G15 -> 19.346667 | U15: =(1-H15)*E4b!H15 -> 47.866667 | V15: =(1-I15)*E4b!I15 -> 93.733333 | ... Z15: =(1-M15)*E4b!M15 -> 4000 | AA15: 2 | AB15: =(E4b!C15-P15-(E4b!B15-O15))/(E4b!C15-E4b!B15) -> 0 | AC15: =(E4b!D15-Q15-(E4b!C15-P15))/(E4b!D15-E4b!C15) -> 0 | AD15: =(E4b!E15-R15-(E4b!D15-Q15))/(E4b!E15-E4b!D15) -> 0.066488889 | AE15: =(E4b!F15-S15-(E4b!E15-R15))/(E4b!F15-E4b!E15) -> 0.057251701 | AF15: =(E4b!G15-T15-(E4b!F15-S15))/(E4b!G15-E4b!F15) -> 0.066666667 | AG15: =(E4b!H15-U15-(E4b!G15-T15))/(E4b!H15-E4b!G15) -> 0.049333333 | AH15: =(E4b!I15-V15-(E4b!H15-U15))/(E4b!I15-E4b!H15) -> 0.082666667 | AI15: =(E4b!J15-W15-(E4b!I15-V15))/(E4b!J15-E4b!I15) -> 0.12 | ... AM15: =(E4b!N15-AA15-(E4b!M15-Z15))/(E4b!N15-E4b!M15) -> 0.2004
A16: 2038 | B16: =B15+(B$28-B$13)/15 -> 0 | C16: =C15+(C$28-C$13)/15 -> 0 | D16: =D15+(D$28-D$13)/15 -> 0 | E16: =E15+(E$28-E$13)/15 -> 0.012 | F16: =F15+(F$28-F$13)/15 -> 0.022 | G16: =G15+(G$28-G$13)/15 -> 0.034 | H16: =H15+(H$28-H$13)/15 -> 0.044 | I16: =I15+(I$28-I$13)/15 -> 0.064 | ... M16: =M15+(M$28-M$13)/15 -> 0.2 | O16: =(1-B16)*E4b!B16 -> 4.8 | P16: =(1-C16)*E4b!C16 -> 7.4 | Q16: =(1-D16)*E4b!D16 -> 9.6 | R16: =(1-E16)*E4b!E16 -> 11.4608 | S16: =(1-F16)*E4b!F16 -> 14.67 | T16: =(1-G16)*E4b!G16 -> 19.32 | U16: =(1-H16)*E4b!H16 -> 47.8 | V16: =(1-I16)*E4b!I16 -> 93.6 | ... Z16: =(1-M16)*E4b!M16 -> 4000 | AA16: 2 | AB16: =(E4b!C16-P16-(E4b!B16-O16))/(E4b!C16-E4b!B16) -> 0 | AC16: =(E4b!D16-Q16-(E4b!C16-P16))/(E4b!D16-E4b!C16) -> 0 | AD16: =(E4b!E16-R16-(E4b!D16-Q16))/(E4b!E16-E4b!D16) -> 0.0696 | AE16: =(E4b!F16-S16-(E4b!E16-R16))/(E4b!F16-E4b!E16) -> 0.056117647 | AF16: =(E4b!G16-T16-(E4b!F16-S16))/(E4b!G16-E4b!F16) -> 0.07 | AG16: =(E4b!H16-U16-(E4b!G16-T16))/(E4b!H16-E4b!G16) -> 0.050666667 | AH16: =(E4b!I16-V16-(E4b!H16-U16))/(E4b!I16-E4b!H16) -> 0.084 | AI16: =(E4b!J16-W16-(E4b!I16-V16))/(E4b!J16-E4b!I16) -> 0.12 | ... AM16: =(E4b!N16-AA16-(E4b!M16-Z16))/(E4b!N16-E4b!M16) -> 0.2004
A17: 2039 | B17: =B16+(B$28-B$13)/15 -> 0 | C17: =C16+(C$28-C$13)/15 -> 0 | D17: =D16+(D$28-D$13)/15 -> 0 | E17: =E16+(E$28-E$13)/15 -> 0.012666667 | F17: =F16+(F$28-F$13)/15 -> 0.022666667 | G17: =G16+(G$28-G$13)/15 -> 0.035333333 | H17: =H16+(H$28-H$13)/15 -> 0.045333333 | I17: =I16+(I$28-I$13)/15 -> 0.065333333 | ... M17: =M16+(M$28-M$13)/15 -> 0.2 | O17: =(1-B17)*E4b!B17 -> 4.7333333 | P17: =(1-C17)*E4b!C17 -> 7.2 | Q17: =(1-D17)*E4b!D17 -> 9.4666667 | R17: =(1-E17)*E4b!E17 -> 11.321422 | S17: =(1-F17)*E4b!F17 -> 14.66 | T17: =(1-G17)*E4b!G17 -> 19.293333 | U17: =(1-H17)*E4b!H17 -> 47.733333 | V17: =(1-I17)*E4b!I17 -> 93.466667 | ... Z17: =(1-M17)*E4b!M17 -> 4000 | AA17: 2 | AB17: =(E4b!C17-P17-(E4b!B17-O17))/(E4b!C17-E4b!B17) -> 0 | AC17: =(E4b!D17-Q17-(E4b!C17-P17))/(E4b!D17-E4b!C17) -> 0 | AD17: =(E4b!E17-R17-(E4b!D17-Q17))/(E4b!E17-E4b!D17) -> 0.072622222 | AE17: =(E4b!F17-S17-(E4b!E17-R17))/(E4b!F17-E4b!E17) -> 0.055119497 | AF17: =(E4b!G17-T17-(E4b!F17-S17))/(E4b!G17-E4b!F17) -> 0.073333333 | AG17: =(E4b!H17-U17-(E4b!G17-T17))/(E4b!H17-E4b!G17) -> 0.052 | AH17: =(E4b!I17-V17-(E4b!H17-U17))/(E4b!I17-E4b!H17) -> 0.085333333 | AI17: =(E4b!J17-W17-(E4b!I17-V17))/(E4b!J17-E4b!I17) -> 0.12 | ... AM17: =(E4b!N17-AA17-(E4b!M17-Z17))/(E4b!N17-E4b!M17) -> 0.2004
A18: 2040 | B18: =B17+(B$28-B$13)/15 -> 0 | C18: =C17+(C$28-C$13)/15 -> 0 | D18: =D17+(D$28-D$13)/15 -> 0 | E18: =E17+(E$28-E$13)/15 -> 0.013333333 | F18: =F17+(F$28-F$13)/15 -> 0.023333333 | G18: =G17+(G$28-G$13)/15 -> 0.036666667 | H18: =H17+(H$28-H$13)/15 -> 0.046666667 | I18: =I17+(I$28-I$13)/15 -> 0.066666667 | ... M18: =M17+(M$28-M$13)/15 -> 0.2 | O18: =(1-B18)*E4b!B18 -> 4.6666667 | P18: =(1-C18)*E4b!C18 -> 7 | Q18: =(1-D18)*E4b!D18 -> 9.3333333 | R18: =(1-E18)*E4b!E18 -> 11.182222 | S18: =(1-F18)*E4b!F18 -> 14.65 | T18: =(1-G18)*E4b!G18 -> 19.266667 | U18: =(1-H18)*E4b!H18 -> 47.666667 | V18: =(1-I18)*E4b!I18 -> 93.333333 | ... Z18: =(1-M18)*E4b!M18 -> 4000 | AA18: 2 | AB18: =(E4b!C18-P18-(E4b!B18-O18))/(E4b!C18-E4b!B18) -> 0 | AC18: =(E4b!D18-Q18-(E4b!C18-P18))/(E4b!D18-E4b!C18) -> 0 | AD18: =(E4b!E18-R18-(E4b!D18-Q18))/(E4b!E18-E4b!D18) -> 0.075555556 | AE18: =(E4b!F18-S18-(E4b!E18-R18))/(E4b!F18-E4b!E18) -> 0.054242424 | AF18: =(E4b!G18-T18-(E4b!F18-S18))/(E4b!G18-E4b!F18) -> 0.076666667 | AG18: =(E4b!H18-U18-(E4b!G18-T18))/(E4b!H18-E4b!G18) -> 0.053333333 | AH18: =(E4b!I18-V18-(E4b!H18-U18))/(E4b!I18-E4b!H18) -> 0.086666667 | AI18: =(E4b!J18-W18-(E4b!I18-V18))/(E4b!J18-E4b!I18) -> 0.12 | ... AM18: =(E4b!N18-AA18-(E4b!M18-Z18))/(E4b!N18-E4b!M18) -> 0.2004
A19: 2041 | B19: =B18+(B$28-B$13)/15 -> 0 | C19: =C18+(C$28-C$13)/15 -> 0 | D19: =D18+(D$28-D$13)/15 -> 0 | E19: =E18+(E$28-E$13)/15 -> 0.014 | F19: =F18+(F$28-F$13)/15 -> 0.024 | G19: =G18+(G$28-G$13)/15 -> 0.038 | H19: =H18+(H$28-H$13)/15 -> 0.048 | I19: =I18+(I$28-I$13)/15 -> 0.068 | ... M19: =M18+(M$28-M$13)/15 -> 0.2 | O19: =(1-B19)*E4b!B19 -> 4.6 | P19: =(1-C19)*E4b!C19 -> 6.8 | Q19: =(1-D19)*E4b!D19 -> 9.2 | R19: =(1-E19)*E4b!E19 -> 11.0432 | S19: =(1-F19)*E4b!F19 -> 14.64 | T19: =(1-G19)*E4b!G19 -> 19.24 | U19: =(1-H19)*E4b!H19 -> 47.6 | V19: =(1-I19)*E4b!I19 -> 93.2 | ... Z19: =(1-M19)*E4b!M19 -> 4000 | AA19: 2 | AB19: =(E4b!C19-P19-(E4b!B19-O19))/(E4b!C19-E4b!B19) -> 0 | AC19: =(E4b!D19-Q19-(E4b!C19-P19))/(E4b!D19-E4b!C19) -> 0 | AD19: =(E4b!E19-R19-(E4b!D19-Q19))/(E4b!E19-E4b!D19) -> 0.0784 | AE19: =(E4b!F19-S19-(E4b!E19-R19))/(E4b!F19-E4b!E19) -> 0.053473684 | AF19: =(E4b!G19-T19-(E4b!F19-S19))/(E4b!G19-E4b!F19) -> 0.08 | AG19: =(E4b!H19-U19-(E4b!G19-T19))/(E4b!H19-E4b!G19) -> 0.054666667 | AH19: =(E4b!I19-V19-(E4b!H19-U19))/(E4b!I19-E4b!H19) -> 0.088 | AI19: =(E4b!J19-W19-(E4b!I19-V19))/(E4b!J19-E4b!I19) -> 0.12 | ... AM19: =(E4b!N19-AA19-(E4b!M19-Z19))/(E4b!N19-E4b!M19) -> 0.2004
A20: 2042 | B20: =B19+(B$28-B$13)/15 -> 0 | C20: =C19+(C$28-C$13)/15 -> 0 | D20: =D19+(D$28-D$13)/15 -> 0 | E20: =E19+(E$28-E$13)/15 -> 0.014666667 | F20: =F19+(F$28-F$13)/15 -> 0.024666667 | G20: =G19+(G$28-G$13)/15 -> 0.039333333 | H20: =H19+(H$28-H$13)/15 -> 0.049333333 | I20: =I19+(I$28-I$13)/15 -> 0.069333333 | ... M20: =M19+(M$28-M$13)/15 -> 0.2 | O20: =(1-B20)*E4b!B20 -> 4.5333333 | P20: =(1-C20)*E4b!C20 -> 6.6 | Q20: =(1-D20)*E4b!D20 -> 9.0666667 | R20: =(1-E20)*E4b!E20 -> 10.904356 | S20: =(1-F20)*E4b!F20 -> 14.63 | T20: =(1-G20)*E4b!G20 -> 19.213333 | U20: =(1-H20)*E4b!H20 -> 47.533333 | V20: =(1-I20)*E4b!I20 -> 93.066667 | ... Z20: =(1-M20)*E4b!M20 -> 4000 | AA20: 2 | AB20: =(E4b!C20-P20-(E4b!B20-O20))/(E4b!C20-E4b!B20) -> 0 | AC20: =(E4b!D20-Q20-(E4b!C20-P20))/(E4b!D20-E4b!C20) -> 0 | AD20: =(E4b!E20-R20-(E4b!D20-Q20))/(E4b!E20-E4b!D20) -> 0.081155556 | AE20: =(E4b!F20-S20-(E4b!E20-R20))/(E4b!F20-E4b!E20) -> 0.05280226 | AF20: =(E4b!G20-T20-(E4b!F20-S20))/(E4b!G20-E4b!F20) -> 0.083333333 | AG20: =(E4b!H20-U20-(E4b!G20-T20))/(E4b!H20-E4b!G20) -> 0.056 | AH20: =(E4b!I20-V20-(E4b!H20-U20))/(E4b!I20-E4b!H20) -> 0.089333333 | AI20: =(E4b!J20-W20-(E4b!I20-V20))/(E4b!J20-E4b!I20) -> 0.12 | ... AM20: =(E4b!N20-AA20-(E4b!M20-Z20))/(E4b!N20-E4b!M20) -> 0.2004
A21: 2043 | B21: =B20+(B$28-B$13)/15 -> 0 | C21: =C20+(C$28-C$13)/15 -> 0 | D21: =D20+(D$28-D$13)/15 -> 0 | E21: =E20+(E$28-E$13)/15 -> 0.015333333 | F21: =F20+(F$28-F$13)/15 -> 0.025333333 | G21: =G20+(G$28-G$13)/15 -> 0.040666667 | H21: =H20+(H$28-H$13)/15 -> 0.050666667 | I21: =I20+(I$28-I$13)/15 -> 0.070666667 | ... M21: =M20+(M$28-M$13)/15 -> 0.2 | O21: =(1-B21)*E4b!B21 -> 4.4666667 | P21: =(1-C21)*E4b!C21 -> 6.4 | Q21: =(1-D21)*E4b!D21 -> 8.9333333 | R21: =(1-E21)*E4b!E21 -> 10.765689 | S21: =(1-F21)*E4b!F21 -> 14.62 | T21: =(1-G21)*E4b!G21 -> 19.186667 | U21: =(1-H21)*E4b!H21 -> 47.466667 | V21: =(1-I21)*E4b!I21 -> 92.933333 | ... Z21: =(1-M21)*E4b!M21 -> 4000 | AA21: 2 | AB21: =(E4b!C21-P21-(E4b!B21-O21))/(E4b!C21-E4b!B21) -> 0 | AC21: =(E4b!D21-Q21-(E4b!C21-P21))/(E4b!D21-E4b!C21) -> 0 | AD21: =(E4b!E21-R21-(E4b!D21-Q21))/(E4b!E21-E4b!D21) -> 0.083822222 | AE21: =(E4b!F21-S21-(E4b!E21-R21))/(E4b!F21-E4b!E21) -> 0.052218579 | AF21: =(E4b!G21-T21-(E4b!F21-S21))/(E4b!G21-E4b!F21) -> 0.086666667 | AG21: =(E4b!H21-U21-(E4b!G21-T21))/(E4b!H21-E4b!G21) -> 0.057333333 | AH21: =(E4b!I21-V21-(E4b!H21-U21))/(E4b!I21-E4b!H21) -> 0.090666667 | AI21: =(E4b!J21-W21-(E4b!I21-V21))/(E4b!J21-E4b!I21) -> 0.12 | ... AM21: =(E4b!N21-AA21-(E4b!M21-Z21))/(E4b!N21-E4b!M21) -> 0.2004
A22: 2044 | B22: =B21+(B$28-B$13)/15 -> 0 | C22: =C21+(C$28-C$13)/15 -> 0 | D22: =D21+(D$28-D$13)/15 -> 0 | E22: =E21+(E$28-E$13)/15 -> 0.016 | F22: =F21+(F$28-F$13)/15 -> 0.026 | G22: =G21+(G$28-G$13)/15 -> 0.042 | H22: =H21+(H$28-H$13)/15 -> 0.052 | I22: =I21+(I$28-I$13)/15 -> 0.072 | ... M22: =M21+(M$28-M$13)/15 -> 0.2 | O22: =(1-B22)*E4b!B22 -> 4.4 | P22: =(1-C22)*E4b!C22 -> 6.2 | Q22: =(1-D22)*E4b!D22 -> 8.8 | R22: =(1-E22)*E4b!E22 -> 10.6272 | S22: =(1-F22)*E4b!F22 -> 14.61 | T22: =(1-G22)*E4b!G22 -> 19.16 | U22: =(1-H22)*E4b!H22 -> 47.4 | V22: =(1-I22)*E4b!I22 -> 92.8 | ... Z22: =(1-M22)*E4b!M22 -> 4000 | AA22: 2 | AB22: =(E4b!C22-P22-(E4b!B22-O22))/(E4b!C22-E4b!B22) -> 0 | AC22: =(E4b!D22-Q22-(E4b!C22-P22))/(E4b!D22-E4b!C22) -> 0 | AD22: =(E4b!E22-R22-(E4b!D22-Q22))/(E4b!E22-E4b!D22) -> 0.0864 | AE22: =(E4b!F22-S22-(E4b!E22-R22))/(E4b!F22-E4b!E22) -> 0.051714286 | AF22: =(E4b!G22-T22-(E4b!F22-S22))/(E4b!G22-E4b!F22) -> 0.09 | AG22: =(E4b!H22-U22-(E4b!G22-T22))/(E4b!H22-E4b!G22) -> 0.058666667 | AH22: =(E4b!I22-V22-(E4b!H22-U22))/(E4b!I22-E4b!H22) -> 0.092 | AI22: =(E4b!J22-W22-(E4b!I22-V22))/(E4b!J22-E4b!I22) -> 0.12 | ... AM22: =(E4b!N22-AA22-(E4b!M22-Z22))/(E4b!N22-E4b!M22) -> 0.2004
A23: 2045 | B23: =B22+(B$28-B$13)/15 -> 0 | C23: =C22+(C$28-C$13)/15 -> 0 | D23: =D22+(D$28-D$13)/15 -> 0 | E23: =E22+(E$28-E$13)/15 -> 0.016666667 | F23: =F22+(F$28-F$13)/15 -> 0.026666667 | G23: =G22+(G$28-G$13)/15 -> 0.043333333 | H23: =H22+(H$28-H$13)/15 -> 0.053333333 | I23: =I22+(I$28-I$13)/15 -> 0.073333333 | ... M23: =M22+(M$28-M$13)/15 -> 0.2 | O23: =(1-B23)*E4b!B23 -> 4.3333333 | P23: =(1-C23)*E4b!C23 -> 6 | Q23: =(1-D23)*E4b!D23 -> 8.6666667 | R23: =(1-E23)*E4b!E23 -> 10.488889 | S23: =(1-F23)*E4b!F23 -> 14.6 | T23: =(1-G23)*E4b!G23 -> 19.133333 | U23: =(1-H23)*E4b!H23 -> 47.333333 | V23: =(1-I23)*E4b!I23 -> 92.666667 | ... Z23: =(1-M23)*E4b!M23 -> 4000 | AA23: 2 | AB23: =(E4b!C23-P23-(E4b!B23-O23))/(E4b!C23-E4b!B23) -> 0 | AC23: =(E4b!D23-Q23-(E4b!C23-P23))/(E4b!D23-E4b!C23) -> 0 | AD23: =(E4b!E23-R23-(E4b!D23-Q23))/(E4b!E23-E4b!D23) -> 0.088888889 | AE23: =(E4b!F23-S23-(E4b!E23-R23))/(E4b!F23-E4b!E23) -> 0.051282051 | AF23: =(E4b!G23-T23-(E4b!F23-S23))/(E4b!G23-E4b!F23) -> 0.093333333 | AG23: =(E4b!H23-U23-(E4b!G23-T23))/(E4b!H23-E4b!G23) -> 0.06 | AH23: =(E4b!I23-V23-(E4b!H23-U23))/(E4b!I23-E4b!H23) -> 0.093333333 | AI23: =(E4b!J23-W23-(E4b!I23-V23))/(E4b!J23-E4b!I23) -> 0.12 | ... AM23: =(E4b!N23-AA23-(E4b!M23-Z23))/(E4b!N23-E4b!M23) -> 0.2004
A24: 2046 | B24: =B23+(B$28-B$13)/15 -> 0 | C24: =C23+(C$28-C$13)/15 -> 0 | D24: =D23+(D$28-D$13)/15 -> 0 | E24: =E23+(E$28-E$13)/15 -> 0.017333333 | F24: =F23+(F$28-F$13)/15 -> 0.027333333 | G24: =G23+(G$28-G$13)/15 -> 0.044666667 | H24: =H23+(H$28-H$13)/15 -> 0.054666667 | I24: =I23+(I$28-I$13)/15 -> 0.074666667 | ... M24: =M23+(M$28-M$13)/15 -> 0.2 | O24: =(1-B24)*E4b!B24 -> 4.2666667 | P24: =(1-C24)*E4b!C24 -> 5.8 | Q24: =(1-D24)*E4b!D24 -> 8.5333333 | R24: =(1-E24)*E4b!E24 -> 10.350756 | S24: =(1-F24)*E4b!F24 -> 14.59 | T24: =(1-G24)*E4b!G24 -> 19.106667 | U24: =(1-H24)*E4b!H24 -> 47.266667 | V24: =(1-I24)*E4b!I24 -> 92.533333 | ... Z24: =(1-M24)*E4b!M24 -> 4000 | AA24: 2 | AB24: =(E4b!C24-P24-(E4b!B24-O24))/(E4b!C24-E4b!B24) -> 0 | AC24: =(E4b!D24-Q24-(E4b!C24-P24))/(E4b!D24-E4b!C24) -> 0 | AD24: =(E4b!E24-R24-(E4b!D24-Q24))/(E4b!E24-E4b!D24) -> 0.091288889 | AE24: =(E4b!F24-S24-(E4b!E24-R24))/(E4b!F24-E4b!E24) -> 0.050915423 | AF24: =(E4b!G24-T24-(E4b!F24-S24))/(E4b!G24-E4b!F24) -> 0.096666667 | AG24: =(E4b!H24-U24-(E4b!G24-T24))/(E4b!H24-E4b!G24) -> 0.061333333 | AH24: =(E4b!I24-V24-(E4b!H24-U24))/(E4b!I24-E4b!H24) -> 0.094666667 | AI24: =(E4b!J24-W24-(E4b!I24-V24))/(E4b!J24-E4b!I24) -> 0.12 | ... AM24: =(E4b!N24-AA24-(E4b!M24-Z24))/(E4b!N24-E4b!M24) -> 0.2004
A25: 2047 | B25: =B24+(B$28-B$13)/15 -> 0 | C25: =C24+(C$28-C$13)/15 -> 0 | D25: =D24+(D$28-D$13)/15 -> 0 | E25: =E24+(E$28-E$13)/15 -> 0.018 | F25: =F24+(F$28-F$13)/15 -> 0.028 | G25: =G24+(G$28-G$13)/15 -> 0.046 | H25: =H24+(H$28-H$13)/15 -> 0.056 | I25: =I24+(I$28-I$13)/15 -> 0.076 | ... M25: =M24+(M$28-M$13)/15 -> 0.2 | O25: =(1-B25)*E4b!B25 -> 4.2 | P25: =(1-C25)*E4b!C25 -> 5.6 | Q25: =(1-D25)*E4b!D25 -> 8.4 | R25: =(1-E25)*E4b!E25 -> 10.2128 | S25: =(1-F25)*E4b!F25 -> 14.58 | T25: =(1-G25)*E4b!G25 -> 19.08 | U25: =(1-H25)*E4b!H25 -> 47.2 | V25: =(1-I25)*E4b!I25 -> 92.4 | ... Z25: =(1-M25)*E4b!M25 -> 4000 | AA25: 2 | AB25: =(E4b!C25-P25-(E4b!B25-O25))/(E4b!C25-E4b!B25) -> 0 | AC25: =(E4b!D25-Q25-(E4b!C25-P25))/(E4b!D25-E4b!C25) -> 0 | AD25: =(E4b!E25-R25-(E4b!D25-Q25))/(E4b!E25-E4b!D25) -> 0.0936 | AE25: =(E4b!F25-S25-(E4b!E25-R25))/(E4b!F25-E4b!E25) -> 0.050608696 | AF25: =(E4b!G25-T25-(E4b!F25-S25))/(E4b!G25-E4b!F25) -> 0.1 | AG25: =(E4b!H25-U25-(E4b!G25-T25))/(E4b!H25-E4b!G25) -> 0.062666667 | AH25: =(E4b!I25-V25-(E4b!H25-U25))/(E4b!I25-E4b!H25) -> 0.096 | AI25: =(E4b!J25-W25-(E4b!I25-V25))/(E4b!J25-E4b!I25) -> 0.12 | ... AM25: =(E4b!N25-AA25-(E4b!M25-Z25))/(E4b!N25-E4b!M25) -> 0.2004
... A27: 2049 | B27: =B26+(B$28-B$13)/15 -> 0 | C27: =C26+(C$28-C$13)/15 -> 0 | D27: =D26+(D$28-D$13)/15 -> 0 | E27: =E26+(E$28-E$13)/15 -> 0.019333333 | F27: =F26+(F$28-F$13)/15 -> 0.029333333 | G27: =G26+(G$28-G$13)/15 -> 0.048666667 | H27: =H26+(H$28-H$13)/15 -> 0.058666667 | I27: =I26+(I$28-I$13)/15 -> 0.078666667 | ... M27: =M26+(M$28-M$13)/15 -> 0.2 | O27: =(1-B27)*E4b!B27 -> 4.0666667 | P27: =(1-C27)*E4b!C27 -> 5.2 | Q27: =(1-D27)*E4b!D27 -> 8.1333333 | R27: =(1-E27)*E4b!E27 -> 9.9374222 | S27: =(1-F27)*E4b!F27 -> 14.56 | T27: =(1-G27)*E4b!G27 -> 19.026667 | U27: =(1-H27)*E4b!H27 -> 47.066667 | V27: =(1-I27)*E4b!I27 -> 92.133333 | ... Z27: =(1-M27)*E4b!M27 -> 4000 | AA27: 2 | AB27: =(E4b!C27-P27-(E4b!B27-O27))/(E4b!C27-E4b!B27) -> 0 | AC27: =(E4b!D27-Q27-(E4b!C27-P27))/(E4b!D27-E4b!C27) -> 0 | AD27: =(E4b!E27-R27-(E4b!D27-Q27))/(E4b!E27-E4b!D27) -> 0.097955556 | AE27: =(E4b!F27-S27-(E4b!E27-R27))/(E4b!F27-E4b!E27) -> 0.050155251 | AF27: =(E4b!G27-T27-(E4b!F27-S27))/(E4b!G27-E4b!F27) -> 0.10666667 | AG27: =(E4b!H27-U27-(E4b!G27-T27))/(E4b!H27-E4b!G27) -> 0.065333333 | AH27: =(E4b!I27-V27-(E4b!H27-U27))/(E4b!I27-E4b!H27) -> 0.098666667 | AI27: =(E4b!J27-W27-(E4b!I27-V27))/(E4b!J27-E4b!I27) -> 0.12 | ... AM27: =(E4b!N27-AA27-(E4b!M27-Z27))/(E4b!N27-E4b!M27) -> 0.2004
A28: 2050 | B28: 0 | C28: 0 | D28: 0 | E28: 0.02 | F28: 0.03 | G28: 0.05 | H28: 0.06 | I28: 0.08 | J28: 0.1 | K28: 0.12 | L28: 0.15 | M28: 0.2 | O28: =(1-B28)*E4b!B28 -> 4 | P28: =(1-C28)*E4b!C28 -> 5 | Q28: =(1-D28)*E4b!D28 -> 8 | R28: =(1-E28)*E4b!E28 -> 9.8 | S28: =(1-F28)*E4b!F28 -> 14.55 | T28: =(1-G28)*E4b!G28 -> 19 | U28: =(1-H28)*E4b!H28 -> 47 | V28: =(1-I28)*E4b!I28 -> 92 | ... Z28: =(1-M28)*E4b!M28 -> 4000 | AA28: 2 | AB28: =(E4b!C28-P28-(E4b!B28-O28))/(E4b!C28-E4b!B28) -> 0 | AC28: =(E4b!D28-Q28-(E4b!C28-P28))/(E4b!D28-E4b!C28) -> 0 | AD28: =(E4b!E28-R28-(E4b!D28-Q28))/(E4b!E28-E4b!D28) -> 0.1 | AE28: =(E4b!F28-S28-(E4b!E28-R28))/(E4b!F28-E4b!E28) -> 0.05 | AF28: =(E4b!G28-T28-(E4b!F28-S28))/(E4b!G28-E4b!F28) -> 0.11 | AG28: =(E4b!H28-U28-(E4b!G28-T28))/(E4b!H28-E4b!G28) -> 0.066666667 | AH28: =(E4b!I28-V28-(E4b!H28-U28))/(E4b!I28-E4b!H28) -> 0.1 | AI28: =(E4b!J28-W28-(E4b!I28-V28))/(E4b!J28-E4b!I28) -> 0.12 | ... AM28: =(E4b!N28-AA28-(E4b!M28-Z28))/(E4b!N28-E4b!M28) -> 0.2004
A29: 2051 | B29: =B28+(B$48-B$28)/20 -> 0 | C29: =C28+(C$48-C$28)/20 -> 0 | D29: =D28+(D$48-D$28)/20 -> 0 | E29: =E28+(E$48-E$28)/20 -> 0.0215 | F29: =F28+(F$48-F$28)/20 -> 0.031 | G29: =G28+(G$48-G$28)/20 -> 0.0525 | H29: =H28+(H$48-H$28)/20 -> 0.062 | I29: =I28+(I$48-I$28)/20 -> 0.0835 | ... M29: =M28+(M$48-M$28)/20 -> 0.2 | O29: =(1-B29)*E4b!B29 -> 3.95 | P29: =(1-C29)*E4b!C29 -> 4.95 | Q29: =(1-D29)*E4b!D29 -> 7.95 | R29: =(1-E29)*E4b!E29 -> 9.736075 | S29: =(1-F29)*E4b!F29 -> 14.38965 | T29: =(1-G29)*E4b!G29 -> 18.95 | U29: =(1-H29)*E4b!H29 -> 46.9 | V29: =(1-I29)*E4b!I29 -> 91.65 | ... Z29: =(1-M29)*E4b!M29 -> 4000 | AA29: 2 | AB29: =(E4b!C29-P29-(E4b!B29-O29))/(E4b!C29-E4b!B29) -> 0 | AC29: =(E4b!D29-Q29-(E4b!C29-P29))/(E4b!D29-E4b!C29) -> 0 | AD29: =(E4b!E29-R29-(E4b!D29-Q29))/(E4b!E29-E4b!D29) -> 0.1069625 | AE29: =(E4b!F29-S29-(E4b!E29-R29))/(E4b!F29-E4b!E29) -> 0.050290816 | AF29: =(E4b!G29-T29-(E4b!F29-S29))/(E4b!G29-E4b!F29) -> 0.11449515 | AG29: =(E4b!H29-U29-(E4b!G29-T29))/(E4b!H29-E4b!G29) -> 0.068333333 | AH29: =(E4b!I29-V29-(E4b!H29-U29))/(E4b!I29-E4b!H29) -> 0.105 | AI29: =(E4b!J29-W29-(E4b!I29-V29))/(E4b!J29-E4b!I29) -> 0.1215 | ... AM29: =(E4b!N29-AA29-(E4b!M29-Z29))/(E4b!N29-E4b!M29) -> 0.2004
A30: 2052 | B30: =B29+(B$48-B$28)/20 -> 0 | C30: =C29+(C$48-C$28)/20 -> 0 | D30: =D29+(D$48-D$28)/20 -> 0 | E30: =E29+(E$48-E$28)/20 -> 0.023 | F30: =F29+(F$48-F$28)/20 -> 0.032 | G30: =G29+(G$48-G$28)/20 -> 0.055 | H30: =H29+(H$48-H$28)/20 -> 0.064 | I30: =I29+(I$48-I$28)/20 -> 0.087 | ... M30: =M29+(M$48-M$28)/20 -> 0.2 | O30: =(1-B30)*E4b!B30 -> 3.9 | P30: =(1-C30)*E4b!C30 -> 4.9 | Q30: =(1-D30)*E4b!D30 -> 7.9 | R30: =(1-E30)*E4b!E30 -> 9.6723 | S30: =(1-F30)*E4b!F30 -> 14.2296 | T30: =(1-G30)*E4b!G30 -> 18.9 | U30: =(1-H30)*E4b!H30 -> 46.8 | V30: =(1-I30)*E4b!I30 -> 91.3 | ... Z30: =(1-M30)*E4b!M30 -> 4000 | AA30: 2 | AB30: =(E4b!C30-P30-(E4b!B30-O30))/(E4b!C30-E4b!B30) -> 0 | AC30: =(E4b!D30-Q30-(E4b!C30-P30))/(E4b!D30-E4b!C30) -> 0 | AD30: =(E4b!E30-R30-(E4b!D30-Q30))/(E4b!E30-E4b!D30) -> 0.11385 | AE30: =(E4b!F30-S30-(E4b!E30-R30))/(E4b!F30-E4b!E30) -> 0.0505625 | AF30: =(E4b!G30-T30-(E4b!F30-S30))/(E4b!G30-E4b!F30) -> 0.11879245 | AG30: =(E4b!H30-U30-(E4b!G30-T30))/(E4b!H30-E4b!G30) -> 0.07 | AH30: =(E4b!I30-V30-(E4b!H30-U30))/(E4b!I30-E4b!H30) -> 0.11 | AI30: =(E4b!J30-W30-(E4b!I30-V30))/(E4b!J30-E4b!I30) -> 0.123 | ... AM30: =(E4b!N30-AA30-(E4b!M30-Z30))/(E4b!N30-E4b!M30) -> 0.2004
A31: 2053 | B31: =B30+(B$48-B$28)/20 -> 0 | C31: =C30+(C$48-C$28)/20 -> 0 | D31: =D30+(D$48-D$28)/20 -> 0 | E31: =E30+(E$48-E$28)/20 -> 0.0245 | F31: =F30+(F$48-F$28)/20 -> 0.033 | G31: =G30+(G$48-G$28)/20 -> 0.0575 | H31: =H30+(H$48-H$28)/20 -> 0.066 | I31: =I30+(I$48-I$28)/20 -> 0.0905 | ... M31: =M30+(M$48-M$28)/20 -> 0.2 | O31: =(1-B31)*E4b!B31 -> 3.85 | P31: =(1-C31)*E4b!C31 -> 4.85 | Q31: =(1-D31)*E4b!D31 -> 7.85 | R31: =(1-E31)*E4b!E31 -> 9.608675 | S31: =(1-F31)*E4b!F31 -> 14.06985 | T31: =(1-G31)*E4b!G31 -> 18.85 | U31: =(1-H31)*E4b!H31 -> 46.7 | V31: =(1-I31)*E4b!I31 -> 90.95 | ... Z31: =(1-M31)*E4b!M31 -> 4000 | AA31: 2 | AB31: =(E4b!C31-P31-(E4b!B31-O31))/(E4b!C31-E4b!B31) -> 0 | AC31: =(E4b!D31-Q31-(E4b!C31-P31))/(E4b!D31-E4b!C31) -> 0 | AD31: =(E4b!E31-R31-(E4b!D31-Q31))/(E4b!E31-E4b!D31) -> 0.1206625 | AE31: =(E4b!F31-S31-(E4b!E31-R31))/(E4b!F31-E4b!E31) -> 0.05081383 | AF31: =(E4b!G31-T31-(E4b!F31-S31))/(E4b!G31-E4b!F31) -> 0.12290826 | AG31: =(E4b!H31-U31-(E4b!G31-T31))/(E4b!H31-E4b!G31) -> 0.071666667 | AH31: =(E4b!I31-V31-(E4b!H31-U31))/(E4b!I31-E4b!H31) -> 0.115 | AI31: =(E4b!J31-W31-(E4b!I31-V31))/(E4b!J31-E4b!I31) -> 0.1245 | ... AM31: =(E4b!N31-AA31-(E4b!M31-Z31))/(E4b!N31-E4b!M31) -> 0.2004
A32: 2054 | B32: =B31+(B$48-B$28)/20 -> 0 | C32: =C31+(C$48-C$28)/20 -> 0 | D32: =D31+(D$48-D$28)/20 -> 0 | E32: =E31+(E$48-E$28)/20 -> 0.026 | F32: =F31+(F$48-F$28)/20 -> 0.034 | G32: =G31+(G$48-G$28)/20 -> 0.06 | H32: =H31+(H$48-H$28)/20 -> 0.068 | I32: =I31+(I$48-I$28)/20 -> 0.094 | ... M32: =M31+(M$48-M$28)/20 -> 0.2 | O32: =(1-B32)*E4b!B32 -> 3.8 | P32: =(1-C32)*E4b!C32 -> 4.8 | Q32: =(1-D32)*E4b!D32 -> 7.8 | R32: =(1-E32)*E4b!E32 -> 9.5452 | S32: =(1-F32)*E4b!F32 -> 13.9104 | T32: =(1-G32)*E4b!G32 -> 18.8 | U32: =(1-H32)*E4b!H32 -> 46.6 | V32: =(1-I32)*E4b!I32 -> 90.6 | ... Z32: =(1-M32)*E4b!M32 -> 4000 | AA32: 2 | AB32: =(E4b!C32-P32-(E4b!B32-O32))/(E4b!C32-E4b!B32) -> 0 | AC32: =(E4b!D32-Q32-(E4b!C32-P32))/(E4b!D32-E4b!C32) -> 0 | AD32: =(E4b!E32-R32-(E4b!D32-Q32))/(E4b!E32-E4b!D32) -> 0.1274 | AE32: =(E4b!F32-S32-(E4b!E32-R32))/(E4b!F32-E4b!E32) -> 0.051043478 | AF32: =(E4b!G32-T32-(E4b!F32-S32))/(E4b!G32-E4b!F32) -> 0.12685714 | AG32: =(E4b!H32-U32-(E4b!G32-T32))/(E4b!H32-E4b!G32) -> 0.073333333 | AH32: =(E4b!I32-V32-(E4b!H32-U32))/(E4b!I32-E4b!H32) -> 0.12 | AI32: =(E4b!J32-W32-(E4b!I32-V32))/(E4b!J32-E4b!I32) -> 0.126 | ... AM32: =(E4b!N32-AA32-(E4b!M32-Z32))/(E4b!N32-E4b!M32) -> 0.2004
A33: 2055 | B33: =B32+(B$48-B$28)/20 -> 0 | C33: =C32+(C$48-C$28)/20 -> 0 | D33: =D32+(D$48-D$28)/20 -> 0 | E33: =E32+(E$48-E$28)/20 -> 0.0275 | F33: =F32+(F$48-F$28)/20 -> 0.035 | G33: =G32+(G$48-G$28)/20 -> 0.0625 | H33: =H32+(H$48-H$28)/20 -> 0.07 | I33: =I32+(I$48-I$28)/20 -> 0.0975 | ... M33: =M32+(M$48-M$28)/20 -> 0.2 | O33: =(1-B33)*E4b!B33 -> 3.75 | P33: =(1-C33)*E4b!C33 -> 4.75 | Q33: =(1-D33)*E4b!D33 -> 7.75 | R33: =(1-E33)*E4b!E33 -> 9.481875 | S33: =(1-F33)*E4b!F33 -> 13.75125 | T33: =(1-G33)*E4b!G33 -> 18.75 | U33: =(1-H33)*E4b!H33 -> 46.5 | V33: =(1-I33)*E4b!I33 -> 90.25 | ... Z33: =(1-M33)*E4b!M33 -> 4000 | AA33: 2 | AB33: =(E4b!C33-P33-(E4b!B33-O33))/(E4b!C33-E4b!B33) -> 0 | AC33: =(E4b!D33-Q33-(E4b!C33-P33))/(E4b!D33-E4b!C33) -> 0 | AD33: =(E4b!E33-R33-(E4b!D33-Q33))/(E4b!E33-E4b!D33) -> 0.1340625 | AE33: =(E4b!F33-S33-(E4b!E33-R33))/(E4b!F33-E4b!E33) -> 0.05125 | AF33: =(E4b!G33-T33-(E4b!F33-S33))/(E4b!G33-E4b!F33) -> 0.13065217 | AG33: =(E4b!H33-U33-(E4b!G33-T33))/(E4b!H33-E4b!G33) -> 0.075 | AH33: =(E4b!I33-V33-(E4b!H33-U33))/(E4b!I33-E4b!H33) -> 0.125 | AI33: =(E4b!J33-W33-(E4b!I33-V33))/(E4b!J33-E4b!I33) -> 0.1275 | ... AM33: =(E4b!N33-AA33-(E4b!M33-Z33))/(E4b!N33-E4b!M33) -> 0.2004
A34: 2056 | B34: =B33+(B$48-B$28)/20 -> 0 | C34: =C33+(C$48-C$28)/20 -> 0 | D34: =D33+(D$48-D$28)/20 -> 0 | E34: =E33+(E$48-E$28)/20 -> 0.029 | F34: =F33+(F$48-F$28)/20 -> 0.036 | G34: =G33+(G$48-G$28)/20 -> 0.065 | H34: =H33+(H$48-H$28)/20 -> 0.072 | I34: =I33+(I$48-I$28)/20 -> 0.101 | ... M34: =M33+(M$48-M$28)/20 -> 0.2 | O34: =(1-B34)*E4b!B34 -> 3.7 | P34: =(1-C34)*E4b!C34 -> 4.7 | Q34: =(1-D34)*E4b!D34 -> 7.7 | R34: =(1-E34)*E4b!E34 -> 9.4187 | S34: =(1-F34)*E4b!F34 -> 13.5924 | T34: =(1-G34)*E4b!G34 -> 18.7 | U34: =(1-H34)*E4b!H34 -> 46.4 | V34: =(1-I34)*E4b!I34 -> 89.9 | ... Z34: =(1-M34)*E4b!M34 -> 4000 | AA34: 2 | AB34: =(E4b!C34-P34-(E4b!B34-O34))/(E4b!C34-E4b!B34) -> 0 | AC34: =(E4b!D34-Q34-(E4b!C34-P34))/(E4b!D34-E4b!C34) -> 0 | AD34: =(E4b!E34-R34-(E4b!D34-Q34))/(E4b!E34-E4b!D34) -> 0.14065 | AE34: =(E4b!F34-S34-(E4b!E34-R34))/(E4b!F34-E4b!E34) -> 0.051431818 | AF34: =(E4b!G34-T34-(E4b!F34-S34))/(E4b!G34-E4b!F34) -> 0.13430508 | AG34: =(E4b!H34-U34-(E4b!G34-T34))/(E4b!H34-E4b!G34) -> 0.076666667 | AH34: =(E4b!I34-V34-(E4b!H34-U34))/(E4b!I34-E4b!H34) -> 0.13 | AI34: =(E4b!J34-W34-(E4b!I34-V34))/(E4b!J34-E4b!I34) -> 0.129 | ... AM34: =(E4b!N34-AA34-(E4b!M34-Z34))/(E4b!N34-E4b!M34) -> 0.2004
A35: 2057 | B35: =B34+(B$48-B$28)/20 -> 0 | C35: =C34+(C$48-C$28)/20 -> 0 | D35: =D34+(D$48-D$28)/20 -> 0 | E35: =E34+(E$48-E$28)/20 -> 0.0305 | F35: =F34+(F$48-F$28)/20 -> 0.037 | G35: =G34+(G$48-G$28)/20 -> 0.0675 | H35: =H34+(H$48-H$28)/20 -> 0.074 | I35: =I34+(I$48-I$28)/20 -> 0.1045 | ... M35: =M34+(M$48-M$28)/20 -> 0.2 | O35: =(1-B35)*E4b!B35 -> 3.65 | P35: =(1-C35)*E4b!C35 -> 4.65 | Q35: =(1-D35)*E4b!D35 -> 7.65 | R35: =(1-E35)*E4b!E35 -> 9.355675 | S35: =(1-F35)*E4b!F35 -> 13.43385 | T35: =(1-G35)*E4b!G35 -> 18.65 | U35: =(1-H35)*E4b!H35 -> 46.3 | V35: =(1-I35)*E4b!I35 -> 89.55 | ... Z35: =(1-M35)*E4b!M35 -> 4000 | AA35: 3 | AB35: =(E4b!C35-P35-(E4b!B35-O35))/(E4b!C35-E4b!B35) -> 0 | AC35: =(E4b!D35-Q35-(E4b!C35-P35))/(E4b!D35-E4b!C35) -> 0 | AD35: =(E4b!E35-R35-(E4b!D35-Q35))/(E4b!E35-E4b!D35) -> 0.1471625 | AE35: =(E4b!F35-S35-(E4b!E35-R35))/(E4b!F35-E4b!E35) -> 0.051587209 | AF35: =(E4b!G35-T35-(E4b!F35-S35))/(E4b!G35-E4b!F35) -> 0.13782645 | AG35: =(E4b!H35-U35-(E4b!G35-T35))/(E4b!H35-E4b!G35) -> 0.078333333 | AH35: =(E4b!I35-V35-(E4b!H35-U35))/(E4b!I35-E4b!H35) -> 0.135 | AI35: =(E4b!J35-W35-(E4b!I35-V35))/(E4b!J35-E4b!I35) -> 0.1305 | ... AM35: =(E4b!N35-AA35-(E4b!M35-Z35))/(E4b!N35-E4b!M35) -> 0.2006
A36: 2058 | B36: =B35+(B$48-B$28)/20 -> 0 | C36: =C35+(C$48-C$28)/20 -> 0 | D36: =D35+(D$48-D$28)/20 -> 0 | E36: =E35+(E$48-E$28)/20 -> 0.032 | F36: =F35+(F$48-F$28)/20 -> 0.038 | G36: =G35+(G$48-G$28)/20 -> 0.07 | H36: =H35+(H$48-H$28)/20 -> 0.076 | I36: =I35+(I$48-I$28)/20 -> 0.108 | ... M36: =M35+(M$48-M$28)/20 -> 0.2 | O36: =(1-B36)*E4b!B36 -> 3.6 | P36: =(1-C36)*E4b!C36 -> 4.6 | Q36: =(1-D36)*E4b!D36 -> 7.6 | R36: =(1-E36)*E4b!E36 -> 9.2928 | S36: =(1-F36)*E4b!F36 -> 13.2756 | T36: =(1-G36)*E4b!G36 -> 18.6 | U36: =(1-H36)*E4b!H36 -> 46.2 | V36: =(1-I36)*E4b!I36 -> 89.2 | ... Z36: =(1-M36)*E4b!M36 -> 4000 | AA36: 3 | AB36: =(E4b!C36-P36-(E4b!B36-O36))/(E4b!C36-E4b!B36) -> 0 | AC36: =(E4b!D36-Q36-(E4b!C36-P36))/(E4b!D36-E4b!C36) -> 0 | AD36: =(E4b!E36-R36-(E4b!D36-Q36))/(E4b!E36-E4b!D36) -> 0.1536 | AE36: =(E4b!F36-S36-(E4b!E36-R36))/(E4b!F36-E4b!E36) -> 0.051714286 | AF36: =(E4b!G36-T36-(E4b!F36-S36))/(E4b!G36-E4b!F36) -> 0.14122581 | AG36: =(E4b!H36-U36-(E4b!G36-T36))/(E4b!H36-E4b!G36) -> 0.08 | AH36: =(E4b!I36-V36-(E4b!H36-U36))/(E4b!I36-E4b!H36) -> 0.14 | AI36: =(E4b!J36-W36-(E4b!I36-V36))/(E4b!J36-E4b!I36) -> 0.132 | ... AM36: =(E4b!N36-AA36-(E4b!M36-Z36))/(E4b!N36-E4b!M36) -> 0.2006
A37: 2059 | B37: =B36+(B$48-B$28)/20 -> 0 | C37: =C36+(C$48-C$28)/20 -> 0 | D37: =D36+(D$48-D$28)/20 -> 0 | E37: =E36+(E$48-E$28)/20 -> 0.0335 | F37: =F36+(F$48-F$28)/20 -> 0.039 | G37: =G36+(G$48-G$28)/20 -> 0.0725 | H37: =H36+(H$48-H$28)/20 -> 0.078 | I37: =I36+(I$48-I$28)/20 -> 0.1115 | ... M37: =M36+(M$48-M$28)/20 -> 0.2 | O37: =(1-B37)*E4b!B37 -> 3.55 | P37: =(1-C37)*E4b!C37 -> 4.55 | Q37: =(1-D37)*E4b!D37 -> 7.55 | R37: =(1-E37)*E4b!E37 -> 9.230075 | S37: =(1-F37)*E4b!F37 -> 13.11765 | T37: =(1-G37)*E4b!G37 -> 18.55 | U37: =(1-H37)*E4b!H37 -> 46.1 | V37: =(1-I37)*E4b!I37 -> 88.85 | ... Z37: =(1-M37)*E4b!M37 -> 4000 | AA37: 3 | AB37: =(E4b!C37-P37-(E4b!B37-O37))/(E4b!C37-E4b!B37) -> 0 | AC37: =(E4b!D37-Q37-(E4b!C37-P37))/(E4b!D37-E4b!C37) -> 0 | AD37: =(E4b!E37-R37-(E4b!D37-Q37))/(E4b!E37-E4b!D37) -> 0.1599625 | AE37: =(E4b!F37-S37-(E4b!E37-R37))/(E4b!F37-E4b!E37) -> 0.051810976 | AF37: =(E4b!G37-T37-(E4b!F37-S37))/(E4b!G37-E4b!F37) -> 0.14451181 | AG37: =(E4b!H37-U37-(E4b!G37-T37))/(E4b!H37-E4b!G37) -> 0.081666667 | AH37: =(E4b!I37-V37-(E4b!H37-U37))/(E4b!I37-E4b!H37) -> 0.145 | AI37: =(E4b!J37-W37-(E4b!I37-V37))/(E4b!J37-E4b!I37) -> 0.1335 | ... AM37: =(E4b!N37-AA37-(E4b!M37-Z37))/(E4b!N37-E4b!M37) -> 0.2006
A38: 2060 | B38: =B37+(B$48-B$28)/20 -> 0 | C38: =C37+(C$48-C$28)/20 -> 0 | D38: =D37+(D$48-D$28)/20 -> 0 | E38: =E37+(E$48-E$28)/20 -> 0.035 | F38: =F37+(F$48-F$28)/20 -> 0.04 | G38: =G37+(G$48-G$28)/20 -> 0.075 | H38: =H37+(H$48-H$28)/20 -> 0.08 | I38: =I37+(I$48-I$28)/20 -> 0.115 | ... M38: =M37+(M$48-M$28)/20 -> 0.2 | O38: =(1-B38)*E4b!B38 -> 3.5 | P38: =(1-C38)*E4b!C38 -> 4.5 | Q38: =(1-D38)*E4b!D38 -> 7.5 | R38: =(1-E38)*E4b!E38 -> 9.1675 | S38: =(1-F38)*E4b!F38 -> 12.96 | T38: =(1-G38)*E4b!G38 -> 18.5 | U38: =(1-H38)*E4b!H38 -> 46 | V38: =(1-I38)*E4b!I38 -> 88.5 | ... Z38: =(1-M38)*E4b!M38 -> 4000 | AA38: 3 | AB38: =(E4b!C38-P38-(E4b!B38-O38))/(E4b!C38-E4b!B38) -> 0 | AC38: =(E4b!D38-Q38-(E4b!C38-P38))/(E4b!D38-E4b!C38) -> 0 | AD38: =(E4b!E38-R38-(E4b!D38-Q38))/(E4b!E38-E4b!D38) -> 0.16625 | AE38: =(E4b!F38-S38-(E4b!E38-R38))/(E4b!F38-E4b!E38) -> 0.051875 | AF38: =(E4b!G38-T38-(E4b!F38-S38))/(E4b!G38-E4b!F38) -> 0.14769231 | AG38: =(E4b!H38-U38-(E4b!G38-T38))/(E4b!H38-E4b!G38) -> 0.083333333 | AH38: =(E4b!I38-V38-(E4b!H38-U38))/(E4b!I38-E4b!H38) -> 0.15 | AI38: =(E4b!J38-W38-(E4b!I38-V38))/(E4b!J38-E4b!I38) -> 0.135 | ... AM38: =(E4b!N38-AA38-(E4b!M38-Z38))/(E4b!N38-E4b!M38) -> 0.2006
A39: 2061 | B39: =B38+(B$48-B$28)/20 -> 0 | C39: =C38+(C$48-C$28)/20 -> 0 | D39: =D38+(D$48-D$28)/20 -> 0 | E39: =E38+(E$48-E$28)/20 -> 0.0365 | F39: =F38+(F$48-F$28)/20 -> 0.041 | G39: =G38+(G$48-G$28)/20 -> 0.0775 | H39: =H38+(H$48-H$28)/20 -> 0.082 | I39: =I38+(I$48-I$28)/20 -> 0.1185 | ... M39: =M38+(M$48-M$28)/20 -> 0.2 | O39: =(1-B39)*E4b!B39 -> 3.45 | P39: =(1-C39)*E4b!C39 -> 4.45 | Q39: =(1-D39)*E4b!D39 -> 7.45 | R39: =(1-E39)*E4b!E39 -> 9.105075 | S39: =(1-F39)*E4b!F39 -> 12.80265 | T39: =(1-G39)*E4b!G39 -> 18.45 | U39: =(1-H39)*E4b!H39 -> 45.9 | V39: =(1-I39)*E4b!I39 -> 88.15 | ... Z39: =(1-M39)*E4b!M39 -> 4000 | AA39: 3 | AB39: =(E4b!C39-P39-(E4b!B39-O39))/(E4b!C39-E4b!B39) -> 0 | AC39: =(E4b!D39-Q39-(E4b!C39-P39))/(E4b!D39-E4b!C39) -> 0 | AD39: =(E4b!E39-R39-(E4b!D39-Q39))/(E4b!E39-E4b!D39) -> 0.1724625 | AE39: =(E4b!F39-S39-(E4b!E39-R39))/(E4b!F39-E4b!E39) -> 0.051903846 | AF39: =(E4b!G39-T39-(E4b!F39-S39))/(E4b!G39-E4b!F39) -> 0.15077444 | AG39: =(E4b!H39-U39-(E4b!G39-T39))/(E4b!H39-E4b!G39) -> 0.085 | AH39: =(E4b!I39-V39-(E4b!H39-U39))/(E4b!I39-E4b!H39) -> 0.155 | AI39: =(E4b!J39-W39-(E4b!I39-V39))/(E4b!J39-E4b!I39) -> 0.1365 | ... AM39: =(E4b!N39-AA39-(E4b!M39-Z39))/(E4b!N39-E4b!M39) -> 0.2006
A40: 2062 | B40: =B39+(B$48-B$28)/20 -> 0 | C40: =C39+(C$48-C$28)/20 -> 0 | D40: =D39+(D$48-D$28)/20 -> 0 | E40: =E39+(E$48-E$28)/20 -> 0.038 | F40: =F39+(F$48-F$28)/20 -> 0.042 | G40: =G39+(G$48-G$28)/20 -> 0.08 | H40: =H39+(H$48-H$28)/20 -> 0.084 | I40: =I39+(I$48-I$28)/20 -> 0.122 | ... M40: =M39+(M$48-M$28)/20 -> 0.2 | O40: =(1-B40)*E4b!B40 -> 3.4 | P40: =(1-C40)*E4b!C40 -> 4.4 | Q40: =(1-D40)*E4b!D40 -> 7.4 | R40: =(1-E40)*E4b!E40 -> 9.0428 | S40: =(1-F40)*E4b!F40 -> 12.6456 | T40: =(1-G40)*E4b!G40 -> 18.4 | U40: =(1-H40)*E4b!H40 -> 45.8 | V40: =(1-I40)*E4b!I40 -> 87.8 | ... Z40: =(1-M40)*E4b!M40 -> 4000 | AA40: 3 | AB40: =(E4b!C40-P40-(E4b!B40-O40))/(E4b!C40-E4b!B40) -> 0 | AC40: =(E4b!D40-Q40-(E4b!C40-P40))/(E4b!D40-E4b!C40) -> 0 | AD40: =(E4b!E40-R40-(E4b!D40-Q40))/(E4b!E40-E4b!D40) -> 0.1786 | AE40: =(E4b!F40-S40-(E4b!E40-R40))/(E4b!F40-E4b!E40) -> 0.051894737 | AF40: =(E4b!G40-T40-(E4b!F40-S40))/(E4b!G40-E4b!F40) -> 0.15376471 | AG40: =(E4b!H40-U40-(E4b!G40-T40))/(E4b!H40-E4b!G40) -> 0.086666667 | AH40: =(E4b!I40-V40-(E4b!H40-U40))/(E4b!I40-E4b!H40) -> 0.16 | AI40: =(E4b!J40-W40-(E4b!I40-V40))/(E4b!J40-E4b!I40) -> 0.138 | ... AM40: =(E4b!N40-AA40-(E4b!M40-Z40))/(E4b!N40-E4b!M40) -> 0.2006
... A47: 2069 | B47: =B46+(B$48-B$28)/20 -> 0 | C47: =C46+(C$48-C$28)/20 -> 0 | D47: =D46+(D$48-D$28)/20 -> 0 | E47: =E46+(E$48-E$28)/20 -> 0.0485 | F47: =F46+(F$48-F$28)/20 -> 0.049 | G47: =G46+(G$48-G$28)/20 -> 0.0975 | H47: =H46+(H$48-H$28)/20 -> 0.098 | I47: =I46+(I$48-I$28)/20 -> 0.1465 | ... M47: =M46+(M$48-M$28)/20 -> 0.2 | O47: =(1-B47)*E4b!B47 -> 3.05 | P47: =(1-C47)*E4b!C47 -> 4.05 | Q47: =(1-D47)*E4b!D47 -> 7.05 | R47: =(1-E47)*E4b!E47 -> 8.611075 | S47: =(1-F47)*E4b!F47 -> 11.55465 | T47: =(1-G47)*E4b!G47 -> 18.05 | U47: =(1-H47)*E4b!H47 -> 45.1 | V47: =(1-I47)*E4b!I47 -> 85.35 | ... Z47: =(1-M47)*E4b!M47 -> 4000 | AA47: 3 | AB47: =(E4b!C47-P47-(E4b!B47-O47))/(E4b!C47-E4b!B47) -> 0 | AC47: =(E4b!D47-Q47-(E4b!C47-P47))/(E4b!D47-E4b!C47) -> 0 | AD47: =(E4b!E47-R47-(E4b!D47-Q47))/(E4b!E47-E4b!D47) -> 0.2194625 | AE47: =(E4b!F47-S47-(E4b!E47-R47))/(E4b!F47-E4b!E47) -> 0.050459677 | AF47: =(E4b!G47-T47-(E4b!F47-S47))/(E4b!G47-E4b!F47) -> 0.17256688 | AG47: =(E4b!H47-U47-(E4b!G47-T47))/(E4b!H47-E4b!G47) -> 0.098333333 | AH47: =(E4b!I47-V47-(E4b!H47-U47))/(E4b!I47-E4b!H47) -> 0.195 | AI47: =(E4b!J47-W47-(E4b!I47-V47))/(E4b!J47-E4b!I47) -> 0.1485 | ... AM47: =(E4b!N47-AA47-(E4b!M47-Z47))/(E4b!N47-E4b!M47) -> 0.2006
A48: 2070 | B48: 0 | C48: 0 | D48: 0 | E48: 0.05 | F48: 0.05 | G48: 0.1 | H48: 0.1 | I48: 0.15 | J48: 0.15 | K48: 0.2 | L48: 0.2 | M48: 0.2 | O48: =(1-B48)*E4b!B48 -> 3 | P48: =(1-C48)*E4b!C48 -> 4 | Q48: =(1-D48)*E4b!D48 -> 7 | R48: =(1-E48)*E4b!E48 -> 8.55 | S48: =(1-F48)*E4b!F48 -> 11.4 | T48: =(1-G48)*E4b!G48 -> 18 | U48: =(1-H48)*E4b!H48 -> 45 | V48: =(1-I48)*E4b!I48 -> 85 | ... Z48: =(1-M48)*E4b!M48 -> 4000 | AA48: 3 | AB48: =(E4b!C48-P48-(E4b!B48-O48))/(E4b!C48-E4b!B48) -> 0 | AC48: =(E4b!D48-Q48-(E4b!C48-P48))/(E4b!D48-E4b!C48) -> 0 | AD48: =(E4b!E48-R48-(E4b!D48-Q48))/(E4b!E48-E4b!D48) -> 0.225 | AE48: =(E4b!F48-S48-(E4b!E48-R48))/(E4b!F48-E4b!E48) -> 0.05 | AF48: =(E4b!G48-T48-(E4b!F48-S48))/(E4b!G48-E4b!F48) -> 0.175 | AG48: =(E4b!H48-U48-(E4b!G48-T48))/(E4b!H48-E4b!G48) -> 0.1 | AH48: =(E4b!I48-V48-(E4b!H48-U48))/(E4b!I48-E4b!H48) -> 0.2 | AI48: =(E4b!J48-W48-(E4b!I48-V48))/(E4b!J48-E4b!I48) -> 0.15 | ... AM48: =(E4b!N48-AA48-(E4b!M48-Z48))/(E4b!N48-E4b!M48) -> 0.2006
A49: 2071 | B49: =B48+(B$58-B$48)/10 -> 0 | C49: =C48+(C$58-C$48)/10 -> 0 | D49: =D48+(D$58-D$48)/10 -> 0 | E49: =E48+(E$58-E$48)/10 -> 0.05 | F49: =F48+(F$58-F$48)/10 -> 0.05 | G49: =G48+(G$58-G$48)/10 -> 0.1 | H49: =H48+(H$58-H$48)/10 -> 0.1 | I49: =I48+(I$58-I$48)/10 -> 0.15 | ... M49: =M48+(M$58-M$48)/10 -> 0.2 | O49: =(1-B49)*E4b!B49 -> 3 | P49: =(1-C49)*E4b!C49 -> 4 | Q49: =(1-D49)*E4b!D49 -> 7 | R49: =(1-E49)*E4b!E49 -> 8.55 | S49: =(1-F49)*E4b!F49 -> 11.21 | T49: =(1-G49)*E4b!G49 -> 18 | U49: =(1-H49)*E4b!H49 -> 45 | V49: =(1-I49)*E4b!I49 -> 85 | ... Z49: =(1-M49)*E4b!M49 -> 4000 | AA49: 3 | AB49: =(E4b!C49-P49-(E4b!B49-O49))/(E4b!C49-E4b!B49) -> 0 | AC49: =(E4b!D49-Q49-(E4b!C49-P49))/(E4b!D49-E4b!C49) -> 0 | AD49: =(E4b!E49-R49-(E4b!D49-Q49))/(E4b!E49-E4b!D49) -> 0.225 | AE49: =(E4b!F49-S49-(E4b!E49-R49))/(E4b!F49-E4b!E49) -> 0.05 | AF49: =(E4b!G49-T49-(E4b!F49-S49))/(E4b!G49-E4b!F49) -> 0.17195122 | AG49: =(E4b!H49-U49-(E4b!G49-T49))/(E4b!H49-E4b!G49) -> 0.1 | AH49: =(E4b!I49-V49-(E4b!H49-U49))/(E4b!I49-E4b!H49) -> 0.2 | AI49: =(E4b!J49-W49-(E4b!I49-V49))/(E4b!J49-E4b!I49) -> 0.15 | ... AM49: =(E4b!N49-AA49-(E4b!M49-Z49))/(E4b!N49-E4b!M49) -> 0.2006
A50: 2072 | B50: =B49+(B$58-B$48)/10 -> 0 | C50: =C49+(C$58-C$48)/10 -> 0 | D50: =D49+(D$58-D$48)/10 -> 0 | E50: =E49+(E$58-E$48)/10 -> 0.05 | F50: =F49+(F$58-F$48)/10 -> 0.05 | G50: =G49+(G$58-G$48)/10 -> 0.1 | H50: =H49+(H$58-H$48)/10 -> 0.1 | I50: =I49+(I$58-I$48)/10 -> 0.15 | ... M50: =M49+(M$58-M$48)/10 -> 0.2 | O50: =(1-B50)*E4b!B50 -> 3 | P50: =(1-C50)*E4b!C50 -> 4 | Q50: =(1-D50)*E4b!D50 -> 7 | R50: =(1-E50)*E4b!E50 -> 8.55 | S50: =(1-F50)*E4b!F50 -> 11.02 | T50: =(1-G50)*E4b!G50 -> 18 | U50: =(1-H50)*E4b!H50 -> 45 | V50: =(1-I50)*E4b!I50 -> 85 | ... Z50: =(1-M50)*E4b!M50 -> 4000 | AA50: 3 | AB50: =(E4b!C50-P50-(E4b!B50-O50))/(E4b!C50-E4b!B50) -> 0 | AC50: =(E4b!D50-Q50-(E4b!C50-P50))/(E4b!D50-E4b!C50) -> 0 | AD50: =(E4b!E50-R50-(E4b!D50-Q50))/(E4b!E50-E4b!D50) -> 0.225 | AE50: =(E4b!F50-S50-(E4b!E50-R50))/(E4b!F50-E4b!E50) -> 0.05 | AF50: =(E4b!G50-T50-(E4b!F50-S50))/(E4b!G50-E4b!F50) -> 0.16904762 | AG50: =(E4b!H50-U50-(E4b!G50-T50))/(E4b!H50-E4b!G50) -> 0.1 | AH50: =(E4b!I50-V50-(E4b!H50-U50))/(E4b!I50-E4b!H50) -> 0.2 | AI50: =(E4b!J50-W50-(E4b!I50-V50))/(E4b!J50-E4b!I50) -> 0.15 | ... AM50: =(E4b!N50-AA50-(E4b!M50-Z50))/(E4b!N50-E4b!M50) -> 0.2006
A51: 2073 | B51: =B50+(B$58-B$48)/10 -> 0 | C51: =C50+(C$58-C$48)/10 -> 0 | D51: =D50+(D$58-D$48)/10 -> 0 | E51: =E50+(E$58-E$48)/10 -> 0.05 | F51: =F50+(F$58-F$48)/10 -> 0.05 | G51: =G50+(G$58-G$48)/10 -> 0.1 | H51: =H50+(H$58-H$48)/10 -> 0.1 | I51: =I50+(I$58-I$48)/10 -> 0.15 | ... M51: =M50+(M$58-M$48)/10 -> 0.2 | O51: =(1-B51)*E4b!B51 -> 3 | P51: =(1-C51)*E4b!C51 -> 4 | Q51: =(1-D51)*E4b!D51 -> 7 | R51: =(1-E51)*E4b!E51 -> 8.55 | S51: =(1-F51)*E4b!F51 -> 10.83 | T51: =(1-G51)*E4b!G51 -> 18 | U51: =(1-H51)*E4b!H51 -> 45 | V51: =(1-I51)*E4b!I51 -> 85 | ... Z51: =(1-M51)*E4b!M51 -> 4000 | AA51: 3 | AB51: =(E4b!C51-P51-(E4b!B51-O51))/(E4b!C51-E4b!B51) -> 0 | AC51: =(E4b!D51-Q51-(E4b!C51-P51))/(E4b!D51-E4b!C51) -> 0 | AD51: =(E4b!E51-R51-(E4b!D51-Q51))/(E4b!E51-E4b!D51) -> 0.225 | AE51: =(E4b!F51-S51-(E4b!E51-R51))/(E4b!F51-E4b!E51) -> 0.05 | AF51: =(E4b!G51-T51-(E4b!F51-S51))/(E4b!G51-E4b!F51) -> 0.16627907 | AG51: =(E4b!H51-U51-(E4b!G51-T51))/(E4b!H51-E4b!G51) -> 0.1 | AH51: =(E4b!I51-V51-(E4b!H51-U51))/(E4b!I51-E4b!H51) -> 0.2 | AI51: =(E4b!J51-W51-(E4b!I51-V51))/(E4b!J51-E4b!I51) -> 0.15 | ... AM51: =(E4b!N51-AA51-(E4b!M51-Z51))/(E4b!N51-E4b!M51) -> 0.2006
A52: 2074 | B52: =B51+(B$58-B$48)/10 -> 0 | C52: =C51+(C$58-C$48)/10 -> 0 | D52: =D51+(D$58-D$48)/10 -> 0 | E52: =E51+(E$58-E$48)/10 -> 0.05 | F52: =F51+(F$58-F$48)/10 -> 0.05 | G52: =G51+(G$58-G$48)/10 -> 0.1 | H52: =H51+(H$58-H$48)/10 -> 0.1 | I52: =I51+(I$58-I$48)/10 -> 0.15 | ... M52: =M51+(M$58-M$48)/10 -> 0.2 | O52: =(1-B52)*E4b!B52 -> 3 | P52: =(1-C52)*E4b!C52 -> 4 | Q52: =(1-D52)*E4b!D52 -> 7 | R52: =(1-E52)*E4b!E52 -> 8.55 | S52: =(1-F52)*E4b!F52 -> 10.64 | T52: =(1-G52)*E4b!G52 -> 18 | U52: =(1-H52)*E4b!H52 -> 45 | V52: =(1-I52)*E4b!I52 -> 85 | ... Z52: =(1-M52)*E4b!M52 -> 4000 | AA52: 3 | AB52: =(E4b!C52-P52-(E4b!B52-O52))/(E4b!C52-E4b!B52) -> 0 | AC52: =(E4b!D52-Q52-(E4b!C52-P52))/(E4b!D52-E4b!C52) -> 0 | AD52: =(E4b!E52-R52-(E4b!D52-Q52))/(E4b!E52-E4b!D52) -> 0.225 | AE52: =(E4b!F52-S52-(E4b!E52-R52))/(E4b!F52-E4b!E52) -> 0.05 | AF52: =(E4b!G52-T52-(E4b!F52-S52))/(E4b!G52-E4b!F52) -> 0.16363636 | AG52: =(E4b!H52-U52-(E4b!G52-T52))/(E4b!H52-E4b!G52) -> 0.1 | AH52: =(E4b!I52-V52-(E4b!H52-U52))/(E4b!I52-E4b!H52) -> 0.2 | AI52: =(E4b!J52-W52-(E4b!I52-V52))/(E4b!J52-E4b!I52) -> 0.15 | ... AM52: =(E4b!N52-AA52-(E4b!M52-Z52))/(E4b!N52-E4b!M52) -> 0.2006
A53: 2075 | B53: =B52+(B$58-B$48)/10 -> 0 | C53: =C52+(C$58-C$48)/10 -> 0 | D53: =D52+(D$58-D$48)/10 -> 0 | E53: =E52+(E$58-E$48)/10 -> 0.05 | F53: =F52+(F$58-F$48)/10 -> 0.05 | G53: =G52+(G$58-G$48)/10 -> 0.1 | H53: =H52+(H$58-H$48)/10 -> 0.1 | I53: =I52+(I$58-I$48)/10 -> 0.15 | ... M53: =M52+(M$58-M$48)/10 -> 0.2 | O53: =(1-B53)*E4b!B53 -> 3 | P53: =(1-C53)*E4b!C53 -> 4 | Q53: =(1-D53)*E4b!D53 -> 7 | R53: =(1-E53)*E4b!E53 -> 8.55 | S53: =(1-F53)*E4b!F53 -> 10.45 | T53: =(1-G53)*E4b!G53 -> 18 | U53: =(1-H53)*E4b!H53 -> 45 | V53: =(1-I53)*E4b!I53 -> 85 | ... Z53: =(1-M53)*E4b!M53 -> 4000 | AA53: 3 | AB53: =(E4b!C53-P53-(E4b!B53-O53))/(E4b!C53-E4b!B53) -> 0 | AC53: =(E4b!D53-Q53-(E4b!C53-P53))/(E4b!D53-E4b!C53) -> 0 | AD53: =(E4b!E53-R53-(E4b!D53-Q53))/(E4b!E53-E4b!D53) -> 0.225 | AE53: =(E4b!F53-S53-(E4b!E53-R53))/(E4b!F53-E4b!E53) -> 0.05 | AF53: =(E4b!G53-T53-(E4b!F53-S53))/(E4b!G53-E4b!F53) -> 0.16111111 | AG53: =(E4b!H53-U53-(E4b!G53-T53))/(E4b!H53-E4b!G53) -> 0.1 | AH53: =(E4b!I53-V53-(E4b!H53-U53))/(E4b!I53-E4b!H53) -> 0.2 | AI53: =(E4b!J53-W53-(E4b!I53-V53))/(E4b!J53-E4b!I53) -> 0.15 | ... AM53: =(E4b!N53-AA53-(E4b!M53-Z53))/(E4b!N53-E4b!M53) -> 0.2006
A54: 2076 | B54: =B53+(B$58-B$48)/10 -> 0 | C54: =C53+(C$58-C$48)/10 -> 0 | D54: =D53+(D$58-D$48)/10 -> 0 | E54: =E53+(E$58-E$48)/10 -> 0.05 | F54: =F53+(F$58-F$48)/10 -> 0.05 | G54: =G53+(G$58-G$48)/10 -> 0.1 | H54: =H53+(H$58-H$48)/10 -> 0.1 | I54: =I53+(I$58-I$48)/10 -> 0.15 | ... M54: =M53+(M$58-M$48)/10 -> 0.2 | O54: =(1-B54)*E4b!B54 -> 3 | P54: =(1-C54)*E4b!C54 -> 4 | Q54: =(1-D54)*E4b!D54 -> 7 | R54: =(1-E54)*E4b!E54 -> 8.55 | S54: =(1-F54)*E4b!F54 -> 10.26 | T54: =(1-G54)*E4b!G54 -> 18 | U54: =(1-H54)*E4b!H54 -> 45 | V54: =(1-I54)*E4b!I54 -> 85 | ... Z54: =(1-M54)*E4b!M54 -> 4000 | AA54: 3 | AB54: =(E4b!C54-P54-(E4b!B54-O54))/(E4b!C54-E4b!B54) -> 0 | AC54: =(E4b!D54-Q54-(E4b!C54-P54))/(E4b!D54-E4b!C54) -> 0 | AD54: =(E4b!E54-R54-(E4b!D54-Q54))/(E4b!E54-E4b!D54) -> 0.225 | AE54: =(E4b!F54-S54-(E4b!E54-R54))/(E4b!F54-E4b!E54) -> 0.05 | AF54: =(E4b!G54-T54-(E4b!F54-S54))/(E4b!G54-E4b!F54) -> 0.15869565 | AG54: =(E4b!H54-U54-(E4b!G54-T54))/(E4b!H54-E4b!G54) -> 0.1 | AH54: =(E4b!I54-V54-(E4b!H54-U54))/(E4b!I54-E4b!H54) -> 0.2 | AI54: =(E4b!J54-W54-(E4b!I54-V54))/(E4b!J54-E4b!I54) -> 0.15 | ... AM54: =(E4b!N54-AA54-(E4b!M54-Z54))/(E4b!N54-E4b!M54) -> 0.2006
A55: 2077 | B55: =B54+(B$58-B$48)/10 -> 0 | C55: =C54+(C$58-C$48)/10 -> 0 | D55: =D54+(D$58-D$48)/10 -> 0 | E55: =E54+(E$58-E$48)/10 -> 0.05 | F55: =F54+(F$58-F$48)/10 -> 0.05 | G55: =G54+(G$58-G$48)/10 -> 0.1 | H55: =H54+(H$58-H$48)/10 -> 0.1 | I55: =I54+(I$58-I$48)/10 -> 0.15 | ... M55: =M54+(M$58-M$48)/10 -> 0.2 | O55: =(1-B55)*E4b!B55 -> 3 | P55: =(1-C55)*E4b!C55 -> 4 | Q55: =(1-D55)*E4b!D55 -> 7 | R55: =(1-E55)*E4b!E55 -> 8.55 | S55: =(1-F55)*E4b!F55 -> 10.07 | T55: =(1-G55)*E4b!G55 -> 18 | U55: =(1-H55)*E4b!H55 -> 45 | V55: =(1-I55)*E4b!I55 -> 85 | ... Z55: =(1-M55)*E4b!M55 -> 4000 | AA55: 3 | AB55: =(E4b!C55-P55-(E4b!B55-O55))/(E4b!C55-E4b!B55) -> 0 | AC55: =(E4b!D55-Q55-(E4b!C55-P55))/(E4b!D55-E4b!C55) -> 0 | AD55: =(E4b!E55-R55-(E4b!D55-Q55))/(E4b!E55-E4b!D55) -> 0.225 | AE55: =(E4b!F55-S55-(E4b!E55-R55))/(E4b!F55-E4b!E55) -> 0.05 | AF55: =(E4b!G55-T55-(E4b!F55-S55))/(E4b!G55-E4b!F55) -> 0.15638298 | AG55: =(E4b!H55-U55-(E4b!G55-T55))/(E4b!H55-E4b!G55) -> 0.1 | AH55: =(E4b!I55-V55-(E4b!H55-U55))/(E4b!I55-E4b!H55) -> 0.2 | AI55: =(E4b!J55-W55-(E4b!I55-V55))/(E4b!J55-E4b!I55) -> 0.15 | ... AM55: =(E4b!N55-AA55-(E4b!M55-Z55))/(E4b!N55-E4b!M55) -> 0.2006
A56: 2078 | B56: =B55+(B$58-B$48)/10 -> 0 | C56: =C55+(C$58-C$48)/10 -> 0 | D56: =D55+(D$58-D$48)/10 -> 0 | E56: =E55+(E$58-E$48)/10 -> 0.05 | F56: =F55+(F$58-F$48)/10 -> 0.05 | G56: =G55+(G$58-G$48)/10 -> 0.1 | H56: =H55+(H$58-H$48)/10 -> 0.1 | I56: =I55+(I$58-I$48)/10 -> 0.15 | ... M56: =M55+(M$58-M$48)/10 -> 0.2 | O56: =(1-B56)*E4b!B56 -> 3 | P56: =(1-C56)*E4b!C56 -> 4 | Q56: =(1-D56)*E4b!D56 -> 7 | R56: =(1-E56)*E4b!E56 -> 8.55 | S56: =(1-F56)*E4b!F56 -> 9.88 | T56: =(1-G56)*E4b!G56 -> 18 | U56: =(1-H56)*E4b!H56 -> 45 | V56: =(1-I56)*E4b!I56 -> 85 | ... Z56: =(1-M56)*E4b!M56 -> 4000 | AA56: 3 | AB56: =(E4b!C56-P56-(E4b!B56-O56))/(E4b!C56-E4b!B56) -> 0 | AC56: =(E4b!D56-Q56-(E4b!C56-P56))/(E4b!D56-E4b!C56) -> 0 | AD56: =(E4b!E56-R56-(E4b!D56-Q56))/(E4b!E56-E4b!D56) -> 0.225 | AE56: =(E4b!F56-S56-(E4b!E56-R56))/(E4b!F56-E4b!E56) -> 0.05 | AF56: =(E4b!G56-T56-(E4b!F56-S56))/(E4b!G56-E4b!F56) -> 0.15416667 | AG56: =(E4b!H56-U56-(E4b!G56-T56))/(E4b!H56-E4b!G56) -> 0.1 | AH56: =(E4b!I56-V56-(E4b!H56-U56))/(E4b!I56-E4b!H56) -> 0.2 | AI56: =(E4b!J56-W56-(E4b!I56-V56))/(E4b!J56-E4b!I56) -> 0.15 | ... AM56: =(E4b!N56-AA56-(E4b!M56-Z56))/(E4b!N56-E4b!M56) -> 0.2006
A57: 2079 | B57: =B56+(B$58-B$48)/10 -> 0 | C57: =C56+(C$58-C$48)/10 -> 0 | D57: =D56+(D$58-D$48)/10 -> 0 | E57: =E56+(E$58-E$48)/10 -> 0.05 | F57: =F56+(F$58-F$48)/10 -> 0.05 | G57: =G56+(G$58-G$48)/10 -> 0.1 | H57: =H56+(H$58-H$48)/10 -> 0.1 | I57: =I56+(I$58-I$48)/10 -> 0.15 | ... M57: =M56+(M$58-M$48)/10 -> 0.2 | O57: =(1-B57)*E4b!B57 -> 3 | P57: =(1-C57)*E4b!C57 -> 4 | Q57: =(1-D57)*E4b!D57 -> 7 | R57: =(1-E57)*E4b!E57 -> 8.55 | S57: =(1-F57)*E4b!F57 -> 9.69 | T57: =(1-G57)*E4b!G57 -> 18 | U57: =(1-H57)*E4b!H57 -> 45 | V57: =(1-I57)*E4b!I57 -> 85 | ... Z57: =(1-M57)*E4b!M57 -> 4000 | AA57: 3 | AB57: =(E4b!C57-P57-(E4b!B57-O57))/(E4b!C57-E4b!B57) -> 0 | AC57: =(E4b!D57-Q57-(E4b!C57-P57))/(E4b!D57-E4b!C57) -> 0 | AD57: =(E4b!E57-R57-(E4b!D57-Q57))/(E4b!E57-E4b!D57) -> 0.225 | AE57: =(E4b!F57-S57-(E4b!E57-R57))/(E4b!F57-E4b!E57) -> 0.05 | AF57: =(E4b!G57-T57-(E4b!F57-S57))/(E4b!G57-E4b!F57) -> 0.15204082 | AG57: =(E4b!H57-U57-(E4b!G57-T57))/(E4b!H57-E4b!G57) -> 0.1 | AH57: =(E4b!I57-V57-(E4b!H57-U57))/(E4b!I57-E4b!H57) -> 0.2 | AI57: =(E4b!J57-W57-(E4b!I57-V57))/(E4b!J57-E4b!I57) -> 0.15 | ... AM57: =(E4b!N57-AA57-(E4b!M57-Z57))/(E4b!N57-E4b!M57) -> 0.2006
A58: 2080 | B58: 0 | C58: 0 | D58: 0 | E58: 0.05 | F58: 0.05 | G58: 0.1 | H58: 0.1 | I58: 0.15 | J58: 0.15 | K58: 0.2 | L58: 0.2 | M58: 0.2 | O58: =(1-B58)*E4b!B58 -> 3 | P58: =(1-C58)*E4b!C58 -> 4 | Q58: =(1-D58)*E4b!D58 -> 7 | R58: =(1-E58)*E4b!E58 -> 8.55 | S58: =(1-F58)*E4b!F58 -> 9.5 | T58: =(1-G58)*E4b!G58 -> 18 | U58: =(1-H58)*E4b!H58 -> 45 | V58: =(1-I58)*E4b!I58 -> 85 | ... Z58: =(1-M58)*E4b!M58 -> 4000 | AA58: 3 | AB58: =(E4b!C58-P58-(E4b!B58-O58))/(E4b!C58-E4b!B58) -> 0 | AC58: =(E4b!D58-Q58-(E4b!C58-P58))/(E4b!D58-E4b!C58) -> 0 | AD58: =(E4b!E58-R58-(E4b!D58-Q58))/(E4b!E58-E4b!D58) -> 0.225 | AE58: =(E4b!F58-S58-(E4b!E58-R58))/(E4b!F58-E4b!E58) -> 0.05 | AF58: =(E4b!G58-T58-(E4b!F58-S58))/(E4b!G58-E4b!F58) -> 0.15 | AG58: =(E4b!H58-U58-(E4b!G58-T58))/(E4b!H58-E4b!G58) -> 0.1 | AH58: =(E4b!I58-V58-(E4b!H58-U58))/(E4b!I58-E4b!H58) -> 0.2 | AI58: =(E4b!J58-W58-(E4b!I58-V58))/(E4b!J58-E4b!I58) -> 0.15 | ... AM58: =(E4b!N58-AA58-(E4b!M58-Z58))/(E4b!N58-E4b!M58) -> 0.2006
A59: 2081 | B59: =B58+(B$78-B$58)/20 -> 0 | C59: =C58+(C$78-C$58)/20 -> 0 | D59: =D58+(D$78-D$58)/20 -> 0 | E59: =E58+(E$78-E$58)/20 -> 0.05 | F59: =F58+(F$78-F$58)/20 -> 0.05 | G59: =G58+(G$78-G$58)/20 -> 0.1 | H59: =H58+(H$78-H$58)/20 -> 0.1 | I59: =I58+(I$78-I$58)/20 -> 0.15 | ... M59: =M58+(M$78-M$58)/20 -> 0.2 | O59: =(1-B59)*E4b!B59 -> 3 | P59: =(1-C59)*E4b!C59 -> 4 | Q59: =(1-D59)*E4b!D59 -> 6.95 | R59: =(1-E59)*E4b!E59 -> 8.5025 | S59: =(1-F59)*E4b!F59 -> 9.5 | T59: =(1-G59)*E4b!G59 -> 18 | U59: =(1-H59)*E4b!H59 -> 45 | V59: =(1-I59)*E4b!I59 -> 85 | ... Z59: =(1-M59)*E4b!M59 -> 4000 | AA59: 3 | AB59: =(E4b!C59-P59-(E4b!B59-O59))/(E4b!C59-E4b!B59) -> 0 | AC59: =(E4b!D59-Q59-(E4b!C59-P59))/(E4b!D59-E4b!C59) -> 0 | AD59: =(E4b!E59-R59-(E4b!D59-Q59))/(E4b!E59-E4b!D59) -> 0.22375 | AE59: =(E4b!F59-S59-(E4b!E59-R59))/(E4b!F59-E4b!E59) -> 0.05 | AF59: =(E4b!G59-T59-(E4b!F59-S59))/(E4b!G59-E4b!F59) -> 0.15 | AG59: =(E4b!H59-U59-(E4b!G59-T59))/(E4b!H59-E4b!G59) -> 0.1 | AH59: =(E4b!I59-V59-(E4b!H59-U59))/(E4b!I59-E4b!H59) -> 0.2 | AI59: =(E4b!J59-W59-(E4b!I59-V59))/(E4b!J59-E4b!I59) -> 0.15 | ... AM59: =(E4b!N59-AA59-(E4b!M59-Z59))/(E4b!N59-E4b!M59) -> 0.2006
A60: 2082 | B60: =B59+(B$78-B$58)/20 -> 0 | C60: =C59+(C$78-C$58)/20 -> 0 | D60: =D59+(D$78-D$58)/20 -> 0 | E60: =E59+(E$78-E$58)/20 -> 0.05 | F60: =F59+(F$78-F$58)/20 -> 0.05 | G60: =G59+(G$78-G$58)/20 -> 0.1 | H60: =H59+(H$78-H$58)/20 -> 0.1 | I60: =I59+(I$78-I$58)/20 -> 0.15 | ... M60: =M59+(M$78-M$58)/20 -> 0.2 | O60: =(1-B60)*E4b!B60 -> 3 | P60: =(1-C60)*E4b!C60 -> 4 | Q60: =(1-D60)*E4b!D60 -> 6.9 | R60: =(1-E60)*E4b!E60 -> 8.455 | S60: =(1-F60)*E4b!F60 -> 9.5 | T60: =(1-G60)*E4b!G60 -> 18 | U60: =(1-H60)*E4b!H60 -> 45 | V60: =(1-I60)*E4b!I60 -> 85 | ... Z60: =(1-M60)*E4b!M60 -> 4000 | AA60: 3 | AB60: =(E4b!C60-P60-(E4b!B60-O60))/(E4b!C60-E4b!B60) -> 0 | AC60: =(E4b!D60-Q60-(E4b!C60-P60))/(E4b!D60-E4b!C60) -> 0 | AD60: =(E4b!E60-R60-(E4b!D60-Q60))/(E4b!E60-E4b!D60) -> 0.2225 | AE60: =(E4b!F60-S60-(E4b!E60-R60))/(E4b!F60-E4b!E60) -> 0.05 | AF60: =(E4b!G60-T60-(E4b!F60-S60))/(E4b!G60-E4b!F60) -> 0.15 | AG60: =(E4b!H60-U60-(E4b!G60-T60))/(E4b!H60-E4b!G60) -> 0.1 | AH60: =(E4b!I60-V60-(E4b!H60-U60))/(E4b!I60-E4b!H60) -> 0.2 | AI60: =(E4b!J60-W60-(E4b!I60-V60))/(E4b!J60-E4b!I60) -> 0.15 | ... AM60: =(E4b!N60-AA60-(E4b!M60-Z60))/(E4b!N60-E4b!M60) -> 0.2006
A61: 2083 | B61: =B60+(B$78-B$58)/20 -> 0 | C61: =C60+(C$78-C$58)/20 -> 0 | D61: =D60+(D$78-D$58)/20 -> 0 | E61: =E60+(E$78-E$58)/20 -> 0.05 | F61: =F60+(F$78-F$58)/20 -> 0.05 | G61: =G60+(G$78-G$58)/20 -> 0.1 | H61: =H60+(H$78-H$58)/20 -> 0.1 | I61: =I60+(I$78-I$58)/20 -> 0.15 | ... M61: =M60+(M$78-M$58)/20 -> 0.2 | O61: =(1-B61)*E4b!B61 -> 3 | P61: =(1-C61)*E4b!C61 -> 4 | Q61: =(1-D61)*E4b!D61 -> 6.85 | R61: =(1-E61)*E4b!E61 -> 8.4075 | S61: =(1-F61)*E4b!F61 -> 9.5 | T61: =(1-G61)*E4b!G61 -> 18 | U61: =(1-H61)*E4b!H61 -> 45 | V61: =(1-I61)*E4b!I61 -> 85 | ... Z61: =(1-M61)*E4b!M61 -> 4000 | AA61: 3 | AB61: =(E4b!C61-P61-(E4b!B61-O61))/(E4b!C61-E4b!B61) -> 0 | AC61: =(E4b!D61-Q61-(E4b!C61-P61))/(E4b!D61-E4b!C61) -> 0 | AD61: =(E4b!E61-R61-(E4b!D61-Q61))/(E4b!E61-E4b!D61) -> 0.22125 | AE61: =(E4b!F61-S61-(E4b!E61-R61))/(E4b!F61-E4b!E61) -> 0.05 | AF61: =(E4b!G61-T61-(E4b!F61-S61))/(E4b!G61-E4b!F61) -> 0.15 | AG61: =(E4b!H61-U61-(E4b!G61-T61))/(E4b!H61-E4b!G61) -> 0.1 | AH61: =(E4b!I61-V61-(E4b!H61-U61))/(E4b!I61-E4b!H61) -> 0.2 | AI61: =(E4b!J61-W61-(E4b!I61-V61))/(E4b!J61-E4b!I61) -> 0.15 | ... AM61: =(E4b!N61-AA61-(E4b!M61-Z61))/(E4b!N61-E4b!M61) -> 0.2006
A62: 2084 | B62: =B61+(B$78-B$58)/20 -> 0 | C62: =C61+(C$78-C$58)/20 -> 0 | D62: =D61+(D$78-D$58)/20 -> 0 | E62: =E61+(E$78-E$58)/20 -> 0.05 | F62: =F61+(F$78-F$58)/20 -> 0.05 | G62: =G61+(G$78-G$58)/20 -> 0.1 | H62: =H61+(H$78-H$58)/20 -> 0.1 | I62: =I61+(I$78-I$58)/20 -> 0.15 | ... M62: =M61+(M$78-M$58)/20 -> 0.2 | O62: =(1-B62)*E4b!B62 -> 3 | P62: =(1-C62)*E4b!C62 -> 4 | Q62: =(1-D62)*E4b!D62 -> 6.8 | R62: =(1-E62)*E4b!E62 -> 8.36 | S62: =(1-F62)*E4b!F62 -> 9.5 | T62: =(1-G62)*E4b!G62 -> 18 | U62: =(1-H62)*E4b!H62 -> 45 | V62: =(1-I62)*E4b!I62 -> 85 | ... Z62: =(1-M62)*E4b!M62 -> 4000 | AA62: 3 | AB62: =(E4b!C62-P62-(E4b!B62-O62))/(E4b!C62-E4b!B62) -> 0 | AC62: =(E4b!D62-Q62-(E4b!C62-P62))/(E4b!D62-E4b!C62) -> 0 | AD62: =(E4b!E62-R62-(E4b!D62-Q62))/(E4b!E62-E4b!D62) -> 0.22 | AE62: =(E4b!F62-S62-(E4b!E62-R62))/(E4b!F62-E4b!E62) -> 0.05 | AF62: =(E4b!G62-T62-(E4b!F62-S62))/(E4b!G62-E4b!F62) -> 0.15 | AG62: =(E4b!H62-U62-(E4b!G62-T62))/(E4b!H62-E4b!G62) -> 0.1 | AH62: =(E4b!I62-V62-(E4b!H62-U62))/(E4b!I62-E4b!H62) -> 0.2 | AI62: =(E4b!J62-W62-(E4b!I62-V62))/(E4b!J62-E4b!I62) -> 0.15 | ... AM62: =(E4b!N62-AA62-(E4b!M62-Z62))/(E4b!N62-E4b!M62) -> 0.2006
A63: 2085 | B63: =B62+(B$78-B$58)/20 -> 0 | C63: =C62+(C$78-C$58)/20 -> 0 | D63: =D62+(D$78-D$58)/20 -> 0 | E63: =E62+(E$78-E$58)/20 -> 0.05 | F63: =F62+(F$78-F$58)/20 -> 0.05 | G63: =G62+(G$78-G$58)/20 -> 0.1 | H63: =H62+(H$78-H$58)/20 -> 0.1 | I63: =I62+(I$78-I$58)/20 -> 0.15 | ... M63: =M62+(M$78-M$58)/20 -> 0.2 | O63: =(1-B63)*E4b!B63 -> 3 | P63: =(1-C63)*E4b!C63 -> 4 | Q63: =(1-D63)*E4b!D63 -> 6.75 | R63: =(1-E63)*E4b!E63 -> 8.3125 | S63: =(1-F63)*E4b!F63 -> 9.5 | T63: =(1-G63)*E4b!G63 -> 18 | U63: =(1-H63)*E4b!H63 -> 45 | V63: =(1-I63)*E4b!I63 -> 85 | ... Z63: =(1-M63)*E4b!M63 -> 4000 | AA63: 3 | AB63: =(E4b!C63-P63-(E4b!B63-O63))/(E4b!C63-E4b!B63) -> 0 | AC63: =(E4b!D63-Q63-(E4b!C63-P63))/(E4b!D63-E4b!C63) -> 0 | AD63: =(E4b!E63-R63-(E4b!D63-Q63))/(E4b!E63-E4b!D63) -> 0.21875 | AE63: =(E4b!F63-S63-(E4b!E63-R63))/(E4b!F63-E4b!E63) -> 0.05 | AF63: =(E4b!G63-T63-(E4b!F63-S63))/(E4b!G63-E4b!F63) -> 0.15 | AG63: =(E4b!H63-U63-(E4b!G63-T63))/(E4b!H63-E4b!G63) -> 0.1 | AH63: =(E4b!I63-V63-(E4b!H63-U63))/(E4b!I63-E4b!H63) -> 0.2 | AI63: =(E4b!J63-W63-(E4b!I63-V63))/(E4b!J63-E4b!I63) -> 0.15 | ... AM63: =(E4b!N63-AA63-(E4b!M63-Z63))/(E4b!N63-E4b!M63) -> 0.2006
A64: 2086 | B64: =B63+(B$78-B$58)/20 -> 0 | C64: =C63+(C$78-C$58)/20 -> 0 | D64: =D63+(D$78-D$58)/20 -> 0 | E64: =E63+(E$78-E$58)/20 -> 0.05 | F64: =F63+(F$78-F$58)/20 -> 0.05 | G64: =G63+(G$78-G$58)/20 -> 0.1 | H64: =H63+(H$78-H$58)/20 -> 0.1 | I64: =I63+(I$78-I$58)/20 -> 0.15 | ... M64: =M63+(M$78-M$58)/20 -> 0.2 | O64: =(1-B64)*E4b!B64 -> 3 | P64: =(1-C64)*E4b!C64 -> 4 | Q64: =(1-D64)*E4b!D64 -> 6.7 | R64: =(1-E64)*E4b!E64 -> 8.265 | S64: =(1-F64)*E4b!F64 -> 9.5 | T64: =(1-G64)*E4b!G64 -> 18 | U64: =(1-H64)*E4b!H64 -> 45 | V64: =(1-I64)*E4b!I64 -> 85 | ... Z64: =(1-M64)*E4b!M64 -> 4000 | AA64: 3 | AB64: =(E4b!C64-P64-(E4b!B64-O64))/(E4b!C64-E4b!B64) -> 0 | AC64: =(E4b!D64-Q64-(E4b!C64-P64))/(E4b!D64-E4b!C64) -> 0 | AD64: =(E4b!E64-R64-(E4b!D64-Q64))/(E4b!E64-E4b!D64) -> 0.2175 | AE64: =(E4b!F64-S64-(E4b!E64-R64))/(E4b!F64-E4b!E64) -> 0.05 | AF64: =(E4b!G64-T64-(E4b!F64-S64))/(E4b!G64-E4b!F64) -> 0.15 | AG64: =(E4b!H64-U64-(E4b!G64-T64))/(E4b!H64-E4b!G64) -> 0.1 | AH64: =(E4b!I64-V64-(E4b!H64-U64))/(E4b!I64-E4b!H64) -> 0.2 | AI64: =(E4b!J64-W64-(E4b!I64-V64))/(E4b!J64-E4b!I64) -> 0.15 | ... AM64: =(E4b!N64-AA64-(E4b!M64-Z64))/(E4b!N64-E4b!M64) -> 0.2006
A65: 2087 | B65: =B64+(B$78-B$58)/20 -> 0 | C65: =C64+(C$78-C$58)/20 -> 0 | D65: =D64+(D$78-D$58)/20 -> 0 | E65: =E64+(E$78-E$58)/20 -> 0.05 | F65: =F64+(F$78-F$58)/20 -> 0.05 | G65: =G64+(G$78-G$58)/20 -> 0.1 | H65: =H64+(H$78-H$58)/20 -> 0.1 | I65: =I64+(I$78-I$58)/20 -> 0.15 | ... M65: =M64+(M$78-M$58)/20 -> 0.2 | O65: =(1-B65)*E4b!B65 -> 3 | P65: =(1-C65)*E4b!C65 -> 4 | Q65: =(1-D65)*E4b!D65 -> 6.65 | R65: =(1-E65)*E4b!E65 -> 8.2175 | S65: =(1-F65)*E4b!F65 -> 9.5 | T65: =(1-G65)*E4b!G65 -> 18 | U65: =(1-H65)*E4b!H65 -> 45 | V65: =(1-I65)*E4b!I65 -> 85 | ... Z65: =(1-M65)*E4b!M65 -> 4000 | AA65: 3 | AB65: =(E4b!C65-P65-(E4b!B65-O65))/(E4b!C65-E4b!B65) -> 0 | AC65: =(E4b!D65-Q65-(E4b!C65-P65))/(E4b!D65-E4b!C65) -> 0 | AD65: =(E4b!E65-R65-(E4b!D65-Q65))/(E4b!E65-E4b!D65) -> 0.21625 | AE65: =(E4b!F65-S65-(E4b!E65-R65))/(E4b!F65-E4b!E65) -> 0.05 | AF65: =(E4b!G65-T65-(E4b!F65-S65))/(E4b!G65-E4b!F65) -> 0.15 | AG65: =(E4b!H65-U65-(E4b!G65-T65))/(E4b!H65-E4b!G65) -> 0.1 | AH65: =(E4b!I65-V65-(E4b!H65-U65))/(E4b!I65-E4b!H65) -> 0.2 | AI65: =(E4b!J65-W65-(E4b!I65-V65))/(E4b!J65-E4b!I65) -> 0.15 | ... AM65: =(E4b!N65-AA65-(E4b!M65-Z65))/(E4b!N65-E4b!M65) -> 0.2006
A66: 2088 | B66: =B65+(B$78-B$58)/20 -> 0 | C66: =C65+(C$78-C$58)/20 -> 0 | D66: =D65+(D$78-D$58)/20 -> 0 | E66: =E65+(E$78-E$58)/20 -> 0.05 | F66: =F65+(F$78-F$58)/20 -> 0.05 | G66: =G65+(G$78-G$58)/20 -> 0.1 | H66: =H65+(H$78-H$58)/20 -> 0.1 | I66: =I65+(I$78-I$58)/20 -> 0.15 | ... M66: =M65+(M$78-M$58)/20 -> 0.2 | O66: =(1-B66)*E4b!B66 -> 3 | P66: =(1-C66)*E4b!C66 -> 4 | Q66: =(1-D66)*E4b!D66 -> 6.6 | R66: =(1-E66)*E4b!E66 -> 8.17 | S66: =(1-F66)*E4b!F66 -> 9.5 | T66: =(1-G66)*E4b!G66 -> 18 | U66: =(1-H66)*E4b!H66 -> 45 | V66: =(1-I66)*E4b!I66 -> 85 | ... Z66: =(1-M66)*E4b!M66 -> 4000 | AA66: 3 | AB66: =(E4b!C66-P66-(E4b!B66-O66))/(E4b!C66-E4b!B66) -> 0 | AC66: =(E4b!D66-Q66-(E4b!C66-P66))/(E4b!D66-E4b!C66) -> 0 | AD66: =(E4b!E66-R66-(E4b!D66-Q66))/(E4b!E66-E4b!D66) -> 0.215 | AE66: =(E4b!F66-S66-(E4b!E66-R66))/(E4b!F66-E4b!E66) -> 0.05 | AF66: =(E4b!G66-T66-(E4b!F66-S66))/(E4b!G66-E4b!F66) -> 0.15 | AG66: =(E4b!H66-U66-(E4b!G66-T66))/(E4b!H66-E4b!G66) -> 0.1 | AH66: =(E4b!I66-V66-(E4b!H66-U66))/(E4b!I66-E4b!H66) -> 0.2 | AI66: =(E4b!J66-W66-(E4b!I66-V66))/(E4b!J66-E4b!I66) -> 0.15 | ... AM66: =(E4b!N66-AA66-(E4b!M66-Z66))/(E4b!N66-E4b!M66) -> 0.2006
A67: 2089 | B67: =B66+(B$78-B$58)/20 -> 0 | C67: =C66+(C$78-C$58)/20 -> 0 | D67: =D66+(D$78-D$58)/20 -> 0 | E67: =E66+(E$78-E$58)/20 -> 0.05 | F67: =F66+(F$78-F$58)/20 -> 0.05 | G67: =G66+(G$78-G$58)/20 -> 0.1 | H67: =H66+(H$78-H$58)/20 -> 0.1 | I67: =I66+(I$78-I$58)/20 -> 0.15 | ... M67: =M66+(M$78-M$58)/20 -> 0.2 | O67: =(1-B67)*E4b!B67 -> 3 | P67: =(1-C67)*E4b!C67 -> 4 | Q67: =(1-D67)*E4b!D67 -> 6.55 | R67: =(1-E67)*E4b!E67 -> 8.1225 | S67: =(1-F67)*E4b!F67 -> 9.5 | T67: =(1-G67)*E4b!G67 -> 18 | U67: =(1-H67)*E4b!H67 -> 45 | V67: =(1-I67)*E4b!I67 -> 85 | ... Z67: =(1-M67)*E4b!M67 -> 4000 | AA67: 3 | AB67: =(E4b!C67-P67-(E4b!B67-O67))/(E4b!C67-E4b!B67) -> 0 | AC67: =(E4b!D67-Q67-(E4b!C67-P67))/(E4b!D67-E4b!C67) -> 0 | AD67: =(E4b!E67-R67-(E4b!D67-Q67))/(E4b!E67-E4b!D67) -> 0.21375 | AE67: =(E4b!F67-S67-(E4b!E67-R67))/(E4b!F67-E4b!E67) -> 0.05 | AF67: =(E4b!G67-T67-(E4b!F67-S67))/(E4b!G67-E4b!F67) -> 0.15 | AG67: =(E4b!H67-U67-(E4b!G67-T67))/(E4b!H67-E4b!G67) -> 0.1 | AH67: =(E4b!I67-V67-(E4b!H67-U67))/(E4b!I67-E4b!H67) -> 0.2 | AI67: =(E4b!J67-W67-(E4b!I67-V67))/(E4b!J67-E4b!I67) -> 0.15 | ... AM67: =(E4b!N67-AA67-(E4b!M67-Z67))/(E4b!N67-E4b!M67) -> 0.2006
A68: 2090 | B68: =B67+(B$78-B$58)/20 -> 0 | C68: =C67+(C$78-C$58)/20 -> 0 | D68: =D67+(D$78-D$58)/20 -> 0 | E68: =E67+(E$78-E$58)/20 -> 0.05 | F68: =F67+(F$78-F$58)/20 -> 0.05 | G68: =G67+(G$78-G$58)/20 -> 0.1 | H68: =H67+(H$78-H$58)/20 -> 0.1 | I68: =I67+(I$78-I$58)/20 -> 0.15 | ... M68: =M67+(M$78-M$58)/20 -> 0.2 | O68: =(1-B68)*E4b!B68 -> 3 | P68: =(1-C68)*E4b!C68 -> 4 | Q68: =(1-D68)*E4b!D68 -> 6.5 | R68: =(1-E68)*E4b!E68 -> 8.075 | S68: =(1-F68)*E4b!F68 -> 9.5 | T68: =(1-G68)*E4b!G68 -> 18 | U68: =(1-H68)*E4b!H68 -> 45 | V68: =(1-I68)*E4b!I68 -> 85 | ... Z68: =(1-M68)*E4b!M68 -> 4000 | AA68: 3 | AB68: =(E4b!C68-P68-(E4b!B68-O68))/(E4b!C68-E4b!B68) -> 0 | AC68: =(E4b!D68-Q68-(E4b!C68-P68))/(E4b!D68-E4b!C68) -> 0 | AD68: =(E4b!E68-R68-(E4b!D68-Q68))/(E4b!E68-E4b!D68) -> 0.2125 | AE68: =(E4b!F68-S68-(E4b!E68-R68))/(E4b!F68-E4b!E68) -> 0.05 | AF68: =(E4b!G68-T68-(E4b!F68-S68))/(E4b!G68-E4b!F68) -> 0.15 | AG68: =(E4b!H68-U68-(E4b!G68-T68))/(E4b!H68-E4b!G68) -> 0.1 | AH68: =(E4b!I68-V68-(E4b!H68-U68))/(E4b!I68-E4b!H68) -> 0.2 | AI68: =(E4b!J68-W68-(E4b!I68-V68))/(E4b!J68-E4b!I68) -> 0.15 | ... AM68: =(E4b!N68-AA68-(E4b!M68-Z68))/(E4b!N68-E4b!M68) -> 0.2006
A69: 2091 | B69: =B68+(B$78-B$58)/20 -> 0 | C69: =C68+(C$78-C$58)/20 -> 0 | D69: =D68+(D$78-D$58)/20 -> 0 | E69: =E68+(E$78-E$58)/20 -> 0.05 | F69: =F68+(F$78-F$58)/20 -> 0.05 | G69: =G68+(G$78-G$58)/20 -> 0.1 | H69: =H68+(H$78-H$58)/20 -> 0.1 | I69: =I68+(I$78-I$58)/20 -> 0.15 | ... M69: =M68+(M$78-M$58)/20 -> 0.2 | O69: =(1-B69)*E4b!B69 -> 3 | P69: =(1-C69)*E4b!C69 -> 4 | Q69: =(1-D69)*E4b!D69 -> 6.45 | R69: =(1-E69)*E4b!E69 -> 8.0275 | S69: =(1-F69)*E4b!F69 -> 9.5 | T69: =(1-G69)*E4b!G69 -> 18 | U69: =(1-H69)*E4b!H69 -> 45 | V69: =(1-I69)*E4b!I69 -> 85 | ... Z69: =(1-M69)*E4b!M69 -> 4000 | AA69: 3 | AB69: =(E4b!C69-P69-(E4b!B69-O69))/(E4b!C69-E4b!B69) -> 0 | AC69: =(E4b!D69-Q69-(E4b!C69-P69))/(E4b!D69-E4b!C69) -> 0 | AD69: =(E4b!E69-R69-(E4b!D69-Q69))/(E4b!E69-E4b!D69) -> 0.21125 | AE69: =(E4b!F69-S69-(E4b!E69-R69))/(E4b!F69-E4b!E69) -> 0.05 | AF69: =(E4b!G69-T69-(E4b!F69-S69))/(E4b!G69-E4b!F69) -> 0.15 | AG69: =(E4b!H69-U69-(E4b!G69-T69))/(E4b!H69-E4b!G69) -> 0.1 | AH69: =(E4b!I69-V69-(E4b!H69-U69))/(E4b!I69-E4b!H69) -> 0.2 | AI69: =(E4b!J69-W69-(E4b!I69-V69))/(E4b!J69-E4b!I69) -> 0.15 | ... AM69: =(E4b!N69-AA69-(E4b!M69-Z69))/(E4b!N69-E4b!M69) -> 0.2006
A70: 2092 | B70: =B69+(B$78-B$58)/20 -> 0 | C70: =C69+(C$78-C$58)/20 -> 0 | D70: =D69+(D$78-D$58)/20 -> 0 | E70: =E69+(E$78-E$58)/20 -> 0.05 | F70: =F69+(F$78-F$58)/20 -> 0.05 | G70: =G69+(G$78-G$58)/20 -> 0.1 | H70: =H69+(H$78-H$58)/20 -> 0.1 | I70: =I69+(I$78-I$58)/20 -> 0.15 | ... M70: =M69+(M$78-M$58)/20 -> 0.2 | O70: =(1-B70)*E4b!B70 -> 3 | P70: =(1-C70)*E4b!C70 -> 4 | Q70: =(1-D70)*E4b!D70 -> 6.4 | R70: =(1-E70)*E4b!E70 -> 7.98 | S70: =(1-F70)*E4b!F70 -> 9.5 | T70: =(1-G70)*E4b!G70 -> 18 | U70: =(1-H70)*E4b!H70 -> 45 | V70: =(1-I70)*E4b!I70 -> 85 | ... Z70: =(1-M70)*E4b!M70 -> 4000 | AA70: 3 | AB70: =(E4b!C70-P70-(E4b!B70-O70))/(E4b!C70-E4b!B70) -> 0 | AC70: =(E4b!D70-Q70-(E4b!C70-P70))/(E4b!D70-E4b!C70) -> 0 | AD70: =(E4b!E70-R70-(E4b!D70-Q70))/(E4b!E70-E4b!D70) -> 0.21 | AE70: =(E4b!F70-S70-(E4b!E70-R70))/(E4b!F70-E4b!E70) -> 0.05 | AF70: =(E4b!G70-T70-(E4b!F70-S70))/(E4b!G70-E4b!F70) -> 0.15 | AG70: =(E4b!H70-U70-(E4b!G70-T70))/(E4b!H70-E4b!G70) -> 0.1 | AH70: =(E4b!I70-V70-(E4b!H70-U70))/(E4b!I70-E4b!H70) -> 0.2 | AI70: =(E4b!J70-W70-(E4b!I70-V70))/(E4b!J70-E4b!I70) -> 0.15 | ... AM70: =(E4b!N70-AA70-(E4b!M70-Z70))/(E4b!N70-E4b!M70) -> 0.2006
... A77: 2099 | B77: =B76+(B$78-B$58)/20 -> 0 | C77: =C76+(C$78-C$58)/20 -> 0 | D77: =D76+(D$78-D$58)/20 -> 0 | E77: =E76+(E$78-E$58)/20 -> 0.05 | F77: =F76+(F$78-F$58)/20 -> 0.05 | G77: =G76+(G$78-G$58)/20 -> 0.1 | H77: =H76+(H$78-H$58)/20 -> 0.1 | I77: =I76+(I$78-I$58)/20 -> 0.15 | ... M77: =M76+(M$78-M$58)/20 -> 0.2 | O77: =(1-B77)*E4b!B77 -> 3 | P77: =(1-C77)*E4b!C77 -> 4 | Q77: =(1-D77)*E4b!D77 -> 6.05 | R77: =(1-E77)*E4b!E77 -> 7.6475 | S77: =(1-F77)*E4b!F77 -> 9.5 | T77: =(1-G77)*E4b!G77 -> 18 | U77: =(1-H77)*E4b!H77 -> 45 | V77: =(1-I77)*E4b!I77 -> 85 | ... Z77: =(1-M77)*E4b!M77 -> 4000 | AA77: 3 | AB77: =(E4b!C77-P77-(E4b!B77-O77))/(E4b!C77-E4b!B77) -> 0 | AC77: =(E4b!D77-Q77-(E4b!C77-P77))/(E4b!D77-E4b!C77) -> 0 | AD77: =(E4b!E77-R77-(E4b!D77-Q77))/(E4b!E77-E4b!D77) -> 0.20125 | AE77: =(E4b!F77-S77-(E4b!E77-R77))/(E4b!F77-E4b!E77) -> 0.05 | AF77: =(E4b!G77-T77-(E4b!F77-S77))/(E4b!G77-E4b!F77) -> 0.15 | AG77: =(E4b!H77-U77-(E4b!G77-T77))/(E4b!H77-E4b!G77) -> 0.1 | AH77: =(E4b!I77-V77-(E4b!H77-U77))/(E4b!I77-E4b!H77) -> 0.2 | AI77: =(E4b!J77-W77-(E4b!I77-V77))/(E4b!J77-E4b!I77) -> 0.15 | ... AM77: =(E4b!N77-AA77-(E4b!M77-Z77))/(E4b!N77-E4b!M77) -> 0.2006
A78: 2100 | B78: 0 | C78: 0 | D78: 0 | E78: 0.05 | F78: 0.05 | G78: 0.1 | H78: 0.1 | I78: 0.15 | J78: 0.15 | K78: 0.2 | L78: 0.2 | M78: 0.2 | O78: =(1-B78)*E4b!B78 -> 3 | P78: =(1-C78)*E4b!C78 -> 4 | Q78: =(1-D78)*E4b!D78 -> 6 | R78: =(1-E78)*E4b!E78 -> 7.6 | S78: =(1-F78)*E4b!F78 -> 9.5 | T78: =(1-G78)*E4b!G78 -> 18 | U78: =(1-H78)*E4b!H78 -> 45 | V78: =(1-I78)*E4b!I78 -> 85 | ... Z78: =(1-M78)*E4b!M78 -> 4000 | AA78: 3 | AB78: =(E4b!C78-P78-(E4b!B78-O78))/(E4b!C78-E4b!B78) -> 0 | AC78: =(E4b!D78-Q78-(E4b!C78-P78))/(E4b!D78-E4b!C78) -> 0 | AD78: =(E4b!E78-R78-(E4b!D78-Q78))/(E4b!E78-E4b!D78) -> 0.2 | AE78: =(E4b!F78-S78-(E4b!E78-R78))/(E4b!F78-E4b!E78) -> 0.05 | AF78: =(E4b!G78-T78-(E4b!F78-S78))/(E4b!G78-E4b!F78) -> 0.15 | AG78: =(E4b!H78-U78-(E4b!G78-T78))/(E4b!H78-E4b!G78) -> 0.1 | AH78: =(E4b!I78-V78-(E4b!H78-U78))/(E4b!I78-E4b!H78) -> 0.2 | AI78: =(E4b!J78-W78-(E4b!I78-V78))/(E4b!J78-E4b!I78) -> 0.15 | ... AM78: =(E4b!N78-AA78-(E4b!M78-Z78))/(E4b!N78-E4b!M78) -> 0.2006

Sheet E5t
A1: Income Tax Schedules (Effective Tax Rates): Series for Stata Import | O1: After-tax income | AB1: Marginal tax rates
AA2: Non-monotonic marginal tax rates
A3: year | B3: ty1 | C3: ty2 | D3: ty3 | E3: ty4 | F3: ty5 | G3: ty6 | H3: ty7 | I3: ty8 | J3: ty9 | K3: ty10 | L3: ty11 | M3: ty12
A4: 2026 | B4: =TE5f!$C7 -> 0 | C4: =TE5f!$C8 -> 0 | D4: =TE5f!$C9 -> 0.05 | E4: =TE5f!$C10 -> 0.1 | F4: =TE5f!$C11 -> 0.15 | G4: =TE5f!$C12 -> 0.2 | H4: =TE5f!$C13 -> 0.4 | I4: =TE5f!$C14 -> 0.5 | J4: =TE5f!$C15 -> 0.6 | K4: =TE5f!$C16 -> 0.7 | L4: =TE5f!$C17 -> 0.8 | M4: =TE5f!$C18 -> 0.9 | O4: =(1-B4)*E4b!B4 -> 5 | P4: =(1-C4)*E5b!C4 -> 7 | Q4: =(1-D4)*E5b!D4 -> 9.5 | R4: =(1-E4)*E5b!E4 -> 10.8 | S4: =(1-F4)*E5b!F4 -> 12.75 | T4: =(1-G4)*E5b!G4 -> 16 | U4: =(1-H4)*E5b!H4 -> 30 | V4: =(1-I4)*E5b!I4 -> 50 | W4: =(1-J4)*E5b!J4 -> 80 | ... Z4: =(1-M4)*E5b!M4 -> 500 | AB4: =(E5b!C4-P4-(E5b!B4-O4))/(E5b!C4-E5b!B4) -> 0 | AC4: =(E5b!D4-Q4-(E5b!C4-P4))/(E5b!D4-E5b!C4) -> 0.16666667 | AD4: =(E5b!E4-R4-(E5b!D4-Q4))/(E5b!E4-E5b!D4) -> 0.35 | AE4: =(E5b!F4-S4-(E5b!E4-R4))/(E5b!F4-E5b!E4) -> 0.35 | AF4: =(E5b!G4-T4-(E5b!F4-S4))/(E5b!G4-E5b!F4) -> 0.35 | AG4: =(E5b!H4-U4-(E5b!G4-T4))/(E5b!H4-E5b!G4) -> 0.53333333 | AH4: =(E5b!I4-V4-(E5b!H4-U4))/(E5b!I4-E5b!H4) -> 0.6 | AI4: =(E5b!J4-W4-(E5b!I4-V4))/(E5b!J4-E5b!I4) -> 0.7 | ... AL4: =(E5b!M4-Z4-(E5b!L4-Y4))/(E5b!M4-E5b!L4) -> 0.925
A5: 2027 | B5: =B4+(B$13-B$4)/9 -> 0 | C5: =C4+(C$13-C$4)/9 -> 0 | D5: =D4+(D$13-D$4)/9 -> 0.061111111 | E5: =E4+(E$13-E$4)/9 -> 0.11111111 | F5: =F4+(F$13-F$4)/9 -> 0.16111111 | G5: =G4+(G$13-G$4)/9 -> 0.21111111 | H5: =H4+(H$13-H$4)/9 -> 0.4 | I5: =I4+(I$13-I$4)/9 -> 0.5 | ... M5: =M4+(M$13-M$4)/9 -> 0.9 | O5: =(1-B5)*E5b!B5 -> 4.8888889 | P5: =(1-C5)*E5b!C5 -> 6.8888889 | Q5: =(1-D5)*E5b!D5 -> 9.1802469 | R5: =(1-E5)*E5b!E5 -> 10.469136 | S5: =(1-F5)*E5b!F5 -> 12.583333 | T5: =(1-G5)*E5b!G5 -> 15.777778 | U5: =(1-H5)*E5b!H5 -> 30 | V5: =(1-I5)*E5b!I5 -> 50 | ... Z5: =(1-M5)*E5b!M5 -> 500 | AA5: 1 | AB5: =(E5b!C5-P5-(E5b!B5-O5))/(E5b!C5-E5b!B5) -> 0 | AC5: =(E5b!D5-Q5-(E5b!C5-P5))/(E5b!D5-E5b!C5) -> 0.20683761 | AD5: =(E5b!E5-R5-(E5b!D5-Q5))/(E5b!E5-E5b!D5) -> 0.35555556 | AE5: =(E5b!F5-S5-(E5b!E5-R5))/(E5b!F5-E5b!E5) -> 0.34386973 | AF5: =(E5b!G5-T5-(E5b!F5-S5))/(E5b!G5-E5b!F5) -> 0.36111111 | AG5: =(E5b!H5-U5-(E5b!G5-T5))/(E5b!H5-E5b!G5) -> 0.52592593 | AH5: =(E5b!I5-V5-(E5b!H5-U5))/(E5b!I5-E5b!H5) -> 0.6 | AI5: =(E5b!J5-W5-(E5b!I5-V5))/(E5b!J5-E5b!I5) -> 0.7 | ... AL5: =(E5b!M5-Z5-(E5b!L5-Y5))/(E5b!M5-E5b!L5) -> 0.925
A6: 2028 | B6: =B5+(B$13-B$4)/9 -> 0 | C6: =C5+(C$13-C$4)/9 -> 0 | D6: =D5+(D$13-D$4)/9 -> 0.072222222 | E6: =E5+(E$13-E$4)/9 -> 0.12222222 | F6: =F5+(F$13-F$4)/9 -> 0.17222222 | G6: =G5+(G$13-G$4)/9 -> 0.22222222 | H6: =H5+(H$13-H$4)/9 -> 0.4 | I6: =I5+(I$13-I$4)/9 -> 0.5 | ... M6: =M5+(M$13-M$4)/9 -> 0.9 | O6: =(1-B6)*E5b!B6 -> 4.7777778 | P6: =(1-C6)*E5b!C6 -> 6.7777778 | Q6: =(1-D6)*E5b!D6 -> 8.8654321 | R6: =(1-E6)*E5b!E6 -> 10.14321 | S6: =(1-F6)*E5b!F6 -> 12.416667 | T6: =(1-G6)*E5b!G6 -> 15.555556 | U6: =(1-H6)*E5b!H6 -> 30 | V6: =(1-I6)*E5b!I6 -> 50 | ... Z6: =(1-M6)*E5b!M6 -> 500 | AA6: 1 | AB6: =(E5b!C6-P6-(E5b!B6-O6))/(E5b!C6-E5b!B6) -> 0 | AC6: =(E5b!D6-Q6-(E5b!C6-P6))/(E5b!D6-E5b!C6) -> 0.24844444 | AD6: =(E5b!E6-R6-(E5b!D6-Q6))/(E5b!E6-E5b!D6) -> 0.36111111 | AE6: =(E5b!F6-S6-(E5b!E6-R6))/(E5b!F6-E5b!E6) -> 0.33996416 | AF6: =(E5b!G6-T6-(E5b!F6-S6))/(E5b!G6-E5b!F6) -> 0.37222222 | AG6: =(E5b!H6-U6-(E5b!G6-T6))/(E5b!H6-E5b!G6) -> 0.51851852 | AH6: =(E5b!I6-V6-(E5b!H6-U6))/(E5b!I6-E5b!H6) -> 0.6 | AI6: =(E5b!J6-W6-(E5b!I6-V6))/(E5b!J6-E5b!I6) -> 0.7 | ... AL6: =(E5b!M6-Z6-(E5b!L6-Y6))/(E5b!M6-E5b!L6) -> 0.925
A7: 2029 | B7: =B6+(B$13-B$4)/9 -> 0 | C7: =C6+(C$13-C$4)/9 -> 0 | D7: =D6+(D$13-D$4)/9 -> 0.083333333 | E7: =E6+(E$13-E$4)/9 -> 0.13333333 | F7: =F6+(F$13-F$4)/9 -> 0.18333333 | G7: =G6+(G$13-G$4)/9 -> 0.23333333 | H7: =H6+(H$13-H$4)/9 -> 0.4 | I7: =I6+(I$13-I$4)/9 -> 0.5 | ... M7: =M6+(M$13-M$4)/9 -> 0.9 | O7: =(1-B7)*E5b!B7 -> 4.6666667 | P7: =(1-C7)*E5b!C7 -> 6.6666667 | Q7: =(1-D7)*E5b!D7 -> 8.5555556 | R7: =(1-E7)*E5b!E7 -> 9.8222222 | S7: =(1-F7)*E5b!F7 -> 12.25 | T7: =(1-G7)*E5b!G7 -> 15.333333 | U7: =(1-H7)*E5b!H7 -> 30 | V7: =(1-I7)*E5b!I7 -> 50 | ... Z7: =(1-M7)*E5b!M7 -> 500 | AA7: 1 | AB7: =(E5b!C7-P7-(E5b!B7-O7))/(E5b!C7-E5b!B7) -> 0 | AC7: =(E5b!D7-Q7-(E5b!C7-P7))/(E5b!D7-E5b!C7) -> 0.29166667 | AD7: =(E5b!E7-R7-(E5b!D7-Q7))/(E5b!E7-E5b!D7) -> 0.36666667 | AE7: =(E5b!F7-S7-(E5b!E7-R7))/(E5b!F7-E5b!E7) -> 0.33787879 | AF7: =(E5b!G7-T7-(E5b!F7-S7))/(E5b!G7-E5b!F7) -> 0.38333333 | AG7: =(E5b!H7-U7-(E5b!G7-T7))/(E5b!H7-E5b!G7) -> 0.51111111 | AH7: =(E5b!I7-V7-(E5b!H7-U7))/(E5b!I7-E5b!H7) -> 0.6 | AI7: =(E5b!J7-W7-(E5b!I7-V7))/(E5b!J7-E5b!I7) -> 0.7 | ... AL7: =(E5b!M7-Z7-(E5b!L7-Y7))/(E5b!M7-E5b!L7) -> 0.925
A8: 2030 | B8: =B7+(B$13-B$4)/9 -> 0 | C8: =C7+(C$13-C$4)/9 -> 0 | D8: =D7+(D$13-D$4)/9 -> 0.094444444 | E8: =E7+(E$13-E$4)/9 -> 0.14444444 | F8: =F7+(F$13-F$4)/9 -> 0.19444444 | G8: =G7+(G$13-G$4)/9 -> 0.24444444 | H8: =H7+(H$13-H$4)/9 -> 0.4 | I8: =I7+(I$13-I$4)/9 -> 0.5 | ... M8: =M7+(M$13-M$4)/9 -> 0.9 | O8: =(1-B8)*E5b!B8 -> 4.5555556 | P8: =(1-C8)*E5b!C8 -> 6.5555556 | Q8: =(1-D8)*E5b!D8 -> 8.2506173 | R8: =(1-E8)*E5b!E8 -> 9.5061728 | S8: =(1-F8)*E5b!F8 -> 12.083333 | T8: =(1-G8)*E5b!G8 -> 15.111111 | U8: =(1-H8)*E5b!H8 -> 30 | V8: =(1-I8)*E5b!I8 -> 50 | ... Z8: =(1-M8)*E5b!M8 -> 500 | AA8: 1 | AB8: =(E5b!C8-P8-(E5b!B8-O8))/(E5b!C8-E5b!B8) -> 0 | AC8: =(E5b!D8-Q8-(E5b!C8-P8))/(E5b!D8-E5b!C8) -> 0.33671498 | AD8: =(E5b!E8-R8-(E5b!D8-Q8))/(E5b!E8-E5b!D8) -> 0.37222222 | AE8: =(E5b!F8-S8-(E5b!E8-R8))/(E5b!F8-E5b!E8) -> 0.33730159 | AF8: =(E5b!G8-T8-(E5b!F8-S8))/(E5b!G8-E5b!F8) -> 0.39444444 | AG8: =(E5b!H8-U8-(E5b!G8-T8))/(E5b!H8-E5b!G8) -> 0.5037037 | AH8: =(E5b!I8-V8-(E5b!H8-U8))/(E5b!I8-E5b!H8) -> 0.6 | AI8: =(E5b!J8-W8-(E5b!I8-V8))/(E5b!J8-E5b!I8) -> 0.7 | ... AL8: =(E5b!M8-Z8-(E5b!L8-Y8))/(E5b!M8-E5b!L8) -> 0.925
A9: 2031 | B9: =B8+(B$13-B$4)/9 -> 0 | C9: =C8+(C$13-C$4)/9 -> 0 | D9: =D8+(D$13-D$4)/9 -> 0.10555556 | E9: =E8+(E$13-E$4)/9 -> 0.15555556 | F9: =F8+(F$13-F$4)/9 -> 0.20555556 | G9: =G8+(G$13-G$4)/9 -> 0.25555556 | H9: =H8+(H$13-H$4)/9 -> 0.4 | I9: =I8+(I$13-I$4)/9 -> 0.5 | ... M9: =M8+(M$13-M$4)/9 -> 0.9 | O9: =(1-B9)*E5b!B9 -> 4.4444444 | P9: =(1-C9)*E5b!C9 -> 6.4444444 | Q9: =(1-D9)*E5b!D9 -> 7.9506173 | R9: =(1-E9)*E5b!E9 -> 9.1950617 | S9: =(1-F9)*E5b!F9 -> 11.916667 | T9: =(1-G9)*E5b!G9 -> 14.888889 | U9: =(1-H9)*E5b!H9 -> 30 | V9: =(1-I9)*E5b!I9 -> 50 | ... Z9: =(1-M9)*E5b!M9 -> 500 | AA9: 1 | AB9: =(E5b!C9-P9-(E5b!B9-O9))/(E5b!C9-E5b!B9) -> 0 | AC9: =(E5b!D9-Q9-(E5b!C9-P9))/(E5b!D9-E5b!C9) -> 0.38383838 | AD9: =(E5b!E9-R9-(E5b!D9-Q9))/(E5b!E9-E5b!D9) -> 0.37777778 | AE9: =(E5b!F9-S9-(E5b!E9-R9))/(E5b!F9-E5b!E9) -> 0.33798799 | AF9: =(E5b!G9-T9-(E5b!F9-S9))/(E5b!G9-E5b!F9) -> 0.40555556 | AG9: =(E5b!H9-U9-(E5b!G9-T9))/(E5b!H9-E5b!G9) -> 0.4962963 | AH9: =(E5b!I9-V9-(E5b!H9-U9))/(E5b!I9-E5b!H9) -> 0.6 | AI9: =(E5b!J9-W9-(E5b!I9-V9))/(E5b!J9-E5b!I9) -> 0.7 | ... AL9: =(E5b!M9-Z9-(E5b!L9-Y9))/(E5b!M9-E5b!L9) -> 0.925
A10: 2032 | B10: =B9+(B$13-B$4)/9 -> 0 | C10: =C9+(C$13-C$4)/9 -> 0 | D10: =D9+(D$13-D$4)/9 -> 0.11666667 | E10: =E9+(E$13-E$4)/9 -> 0.16666667 | F10: =F9+(F$13-F$4)/9 -> 0.21666667 | G10: =G9+(G$13-G$4)/9 -> 0.26666667 | H10: =H9+(H$13-H$4)/9 -> 0.4 | I10: =I9+(I$13-I$4)/9 -> 0.5 | ... M10: =M9+(M$13-M$4)/9 -> 0.9 | O10: =(1-B10)*E5b!B10 -> 4.3333333 | P10: =(1-C10)*E5b!C10 -> 6.3333333 | Q10: =(1-D10)*E5b!D10 -> 7.6555556 | R10: =(1-E10)*E5b!E10 -> 8.8888889 | S10: =(1-F10)*E5b!F10 -> 11.75 | T10: =(1-G10)*E5b!G10 -> 14.666667 | U10: =(1-H10)*E5b!H10 -> 30 | V10: =(1-I10)*E5b!I10 -> 50 | ... Z10: =(1-M10)*E5b!M10 -> 500 | AA10: 2 | AB10: =(E5b!C10-P10-(E5b!B10-O10))/(E5b!C10-E5b!B10) -> 0 | AC10: =(E5b!D10-Q10-(E5b!C10-P10))/(E5b!D10-E5b!C10) -> 0.43333333 | AD10: =(E5b!E10-R10-(E5b!D10-Q10))/(E5b!E10-E5b!D10) -> 0.38333333 | AE10: =(E5b!F10-S10-(E5b!E10-R10))/(E5b!F10-E5b!E10) -> 0.33974359 | AF10: =(E5b!G10-T10-(E5b!F10-S10))/(E5b!G10-E5b!F10) -> 0.41666667 | AG10: =(E5b!H10-U10-(E5b!G10-T10))/(E5b!H10-E5b!G10) -> 0.48888889 | AH10: =(E5b!I10-V10-(E5b!H10-U10))/(E5b!I10-E5b!H10) -> 0.6 | AI10: =(E5b!J10-W10-(E5b!I10-V10))/(E5b!J10-E5b!I10) -> 0.7 | ... AL10: =(E5b!M10-Z10-(E5b!L10-Y10))/(E5b!M10-E5b!L10) -> 0.925
A11: 2033 | B11: =B10+(B$13-B$4)/9 -> 0 | C11: =C10+(C$13-C$4)/9 -> 0 | D11: =D10+(D$13-D$4)/9 -> 0.12777778 | E11: =E10+(E$13-E$4)/9 -> 0.17777778 | F11: =F10+(F$13-F$4)/9 -> 0.22777778 | G11: =G10+(G$13-G$4)/9 -> 0.27777778 | H11: =H10+(H$13-H$4)/9 -> 0.4 | I11: =I10+(I$13-I$4)/9 -> 0.5 | ... M11: =M10+(M$13-M$4)/9 -> 0.9 | O11: =(1-B11)*E5b!B11 -> 4.2222222 | P11: =(1-C11)*E5b!C11 -> 6.2222222 | Q11: =(1-D11)*E5b!D11 -> 7.3654321 | R11: =(1-E11)*E5b!E11 -> 8.5876543 | S11: =(1-F11)*E5b!F11 -> 11.583333 | T11: =(1-G11)*E5b!G11 -> 14.444444 | U11: =(1-H11)*E5b!H11 -> 30 | V11: =(1-I11)*E5b!I11 -> 50 | ... Z11: =(1-M11)*E5b!M11 -> 500 | AA11: 2 | AB11: =(E5b!C11-P11-(E5b!B11-O11))/(E5b!C11-E5b!B11) -> 0 | AC11: =(E5b!D11-Q11-(E5b!C11-P11))/(E5b!D11-E5b!C11) -> 0.48555556 | AD11: =(E5b!E11-R11-(E5b!D11-Q11))/(E5b!E11-E5b!D11) -> 0.38888889 | AE11: =(E5b!F11-S11-(E5b!E11-R11))/(E5b!F11-E5b!E11) -> 0.34241192 | AF11: =(E5b!G11-T11-(E5b!F11-S11))/(E5b!G11-E5b!F11) -> 0.42777778 | AG11: =(E5b!H11-U11-(E5b!G11-T11))/(E5b!H11-E5b!G11) -> 0.48148148 | AH11: =(E5b!I11-V11-(E5b!H11-U11))/(E5b!I11-E5b!H11) -> 0.6 | AI11: =(E5b!J11-W11-(E5b!I11-V11))/(E5b!J11-E5b!I11) -> 0.7 | ... AL11: =(E5b!M11-Z11-(E5b!L11-Y11))/(E5b!M11-E5b!L11) -> 0.925
A12: 2034 | B12: =B11+(B$13-B$4)/9 -> 0 | C12: =C11+(C$13-C$4)/9 -> 0 | D12: =D11+(D$13-D$4)/9 -> 0.13888889 | E12: =E11+(E$13-E$4)/9 -> 0.18888889 | F12: =F11+(F$13-F$4)/9 -> 0.23888889 | G12: =G11+(G$13-G$4)/9 -> 0.28888889 | H12: =H11+(H$13-H$4)/9 -> 0.4 | I12: =I11+(I$13-I$4)/9 -> 0.5 | ... M12: =M11+(M$13-M$4)/9 -> 0.9 | O12: =(1-B12)*E5b!B12 -> 4.1111111 | P12: =(1-C12)*E5b!C12 -> 6.1111111 | Q12: =(1-D12)*E5b!D12 -> 7.0802469 | R12: =(1-E12)*E5b!E12 -> 8.291358 | S12: =(1-F12)*E5b!F12 -> 11.416667 | T12: =(1-G12)*E5b!G12 -> 14.222222 | U12: =(1-H12)*E5b!H12 -> 30 | V12: =(1-I12)*E5b!I12 -> 50 | ... Z12: =(1-M12)*E5b!M12 -> 500 | AA12: 2 | AB12: =(E5b!C12-P12-(E5b!B12-O12))/(E5b!C12-E5b!B12) -> 0 | AC12: =(E5b!D12-Q12-(E5b!C12-P12))/(E5b!D12-E5b!C12) -> 0.54093567 | AD12: =(E5b!E12-R12-(E5b!D12-Q12))/(E5b!E12-E5b!D12) -> 0.39444444 | AE12: =(E5b!F12-S12-(E5b!E12-R12))/(E5b!F12-E5b!E12) -> 0.34586563 | AF12: =(E5b!G12-T12-(E5b!F12-S12))/(E5b!G12-E5b!F12) -> 0.43888889 | AG12: =(E5b!H12-U12-(E5b!G12-T12))/(E5b!H12-E5b!G12) -> 0.47407407 | AH12: =(E5b!I12-V12-(E5b!H12-U12))/(E5b!I12-E5b!H12) -> 0.6 | AI12: =(E5b!J12-W12-(E5b!I12-V12))/(E5b!J12-E5b!I12) -> 0.7 | ... AL12: =(E5b!M12-Z12-(E5b!L12-Y12))/(E5b!M12-E5b!L12) -> 0.925
A13: 2035 | B13: 0 | C13: 0 | D13: 0.15 | E13: 0.2 | F13: 0.25 | G13: 0.3 | H13: 0.4 | I13: 0.5 | J13: 0.6 | K13: 0.7 | L13: 0.8 | M13: 0.9 | O13: =(1-B13)*E5b!B13 -> 4 | P13: =(1-C13)*E5b!C13 -> 6 | Q13: =(1-D13)*E5b!D13 -> 6.8 | R13: =(1-E13)*E5b!E13 -> 8 | S13: =(1-F13)*E5b!F13 -> 11.25 | T13: =(1-G13)*E5b!G13 -> 14 | U13: =(1-H13)*E5b!H13 -> 30 | V13: =(1-I13)*E5b!I13 -> 50 | ... Z13: =(1-M13)*E5b!M13 -> 500 | AA13: 2 | AB13: =(E5b!C13-P13-(E5b!B13-O13))/(E5b!C13-E5b!B13) -> 0 | AC13: =(E5b!D13-Q13-(E5b!C13-P13))/(E5b!D13-E5b!C13) -> 0.6 | AD13: =(E5b!E13-R13-(E5b!D13-Q13))/(E5b!E13-E5b!D13) -> 0.4 | AE13: =(E5b!F13-S13-(E5b!E13-R13))/(E5b!F13-E5b!E13) -> 0.35 | AF13: =(E5b!G13-T13-(E5b!F13-S13))/(E5b!G13-E5b!F13) -> 0.45 | AG13: =(E5b!H13-U13-(E5b!G13-T13))/(E5b!H13-E5b!G13) -> 0.46666667 | AH13: =(E5b!I13-V13-(E5b!H13-U13))/(E5b!I13-E5b!H13) -> 0.6 | AI13: =(E5b!J13-W13-(E5b!I13-V13))/(E5b!J13-E5b!I13) -> 0.7 | ... AL13: =(E5b!M13-Z13-(E5b!L13-Y13))/(E5b!M13-E5b!L13) -> 0.925
A14: 2036 | B14: =B13+(B$28-B$13)/15 -> 0 | C14: =C13+(C$28-C$13)/15 -> 0 | D14: =D13+(D$28-D$13)/15 -> 0.15 | E14: =E13+(E$28-E$13)/15 -> 0.2 | F14: =F13+(F$28-F$13)/15 -> 0.25 | G14: =G13+(G$28-G$13)/15 -> 0.3 | H14: =H13+(H$28-H$13)/15 -> 0.4 | I14: =I13+(I$28-I$13)/15 -> 0.5 | ... M14: =M13+(M$28-M$13)/15 -> 0.9 | O14: =(1-B14)*E5b!B14 -> 3.9333333 | P14: =(1-C14)*E5b!C14 -> 5.8666667 | Q14: =(1-D14)*E5b!D14 -> 6.6866667 | R14: =(1-E14)*E5b!E14 -> 7.8933333 | S14: =(1-F14)*E5b!F14 -> 11.1 | T14: =(1-G14)*E5b!G14 -> 14 | U14: =(1-H14)*E5b!H14 -> 30 | V14: =(1-I14)*E5b!I14 -> 50 | ... Z14: =(1-M14)*E5b!M14 -> 500 | AA14: 2 | AB14: =(E5b!C14-P14-(E5b!B14-O14))/(E5b!C14-E5b!B14) -> 0 | AC14: =(E5b!D14-Q14-(E5b!C14-P14))/(E5b!D14-E5b!C14) -> 0.59 | AD14: =(E5b!E14-R14-(E5b!D14-Q14))/(E5b!E14-E5b!D14) -> 0.39666667 | AE14: =(E5b!F14-S14-(E5b!E14-R14))/(E5b!F14-E5b!E14) -> 0.35 | AF14: =(E5b!G14-T14-(E5b!F14-S14))/(E5b!G14-E5b!F14) -> 0.44230769 | AG14: =(E5b!H14-U14-(E5b!G14-T14))/(E5b!H14-E5b!G14) -> 0.46666667 | AH14: =(E5b!I14-V14-(E5b!H14-U14))/(E5b!I14-E5b!H14) -> 0.6 | AI14: =(E5b!J14-W14-(E5b!I14-V14))/(E5b!J14-E5b!I14) -> 0.7 | ... AL14: =(E5b!M14-Z14-(E5b!L14-Y14))/(E5b!M14-E5b!L14) -> 0.925
A15: 2037 | B15: =B14+(B$28-B$13)/15 -> 0 | C15: =C14+(C$28-C$13)/15 -> 0 | D15: =D14+(D$28-D$13)/15 -> 0.15 | E15: =E14+(E$28-E$13)/15 -> 0.2 | F15: =F14+(F$28-F$13)/15 -> 0.25 | G15: =G14+(G$28-G$13)/15 -> 0.3 | H15: =H14+(H$28-H$13)/15 -> 0.4 | I15: =I14+(I$28-I$13)/15 -> 0.5 | ... M15: =M14+(M$28-M$13)/15 -> 0.9 | O15: =(1-B15)*E5b!B15 -> 3.8666667 | P15: =(1-C15)*E5b!C15 -> 5.7333333 | Q15: =(1-D15)*E5b!D15 -> 6.5733333 | R15: =(1-E15)*E5b!E15 -> 7.7866667 | S15: =(1-F15)*E5b!F15 -> 10.95 | T15: =(1-G15)*E5b!G15 -> 14 | U15: =(1-H15)*E5b!H15 -> 30 | V15: =(1-I15)*E5b!I15 -> 50 | ... Z15: =(1-M15)*E5b!M15 -> 500 | AA15: 2 | AB15: =(E5b!C15-P15-(E5b!B15-O15))/(E5b!C15-E5b!B15) -> 0 | AC15: =(E5b!D15-Q15-(E5b!C15-P15))/(E5b!D15-E5b!C15) -> 0.58 | AD15: =(E5b!E15-R15-(E5b!D15-Q15))/(E5b!E15-E5b!D15) -> 0.39333333 | AE15: =(E5b!F15-S15-(E5b!E15-R15))/(E5b!F15-E5b!E15) -> 0.35 | AF15: =(E5b!G15-T15-(E5b!F15-S15))/(E5b!G15-E5b!F15) -> 0.43518519 | AG15: =(E5b!H15-U15-(E5b!G15-T15))/(E5b!H15-E5b!G15) -> 0.46666667 | AH15: =(E5b!I15-V15-(E5b!H15-U15))/(E5b!I15-E5b!H15) -> 0.6 | AI15: =(E5b!J15-W15-(E5b!I15-V15))/(E5b!J15-E5b!I15) -> 0.7 | ... AL15: =(E5b!M15-Z15-(E5b!L15-Y15))/(E5b!M15-E5b!L15) -> 0.925
A16: 2038 | B16: =B15+(B$28-B$13)/15 -> 0 | C16: =C15+(C$28-C$13)/15 -> 0 | D16: =D15+(D$28-D$13)/15 -> 0.15 | E16: =E15+(E$28-E$13)/15 -> 0.2 | F16: =F15+(F$28-F$13)/15 -> 0.25 | G16: =G15+(G$28-G$13)/15 -> 0.3 | H16: =H15+(H$28-H$13)/15 -> 0.4 | I16: =I15+(I$28-I$13)/15 -> 0.5 | ... M16: =M15+(M$28-M$13)/15 -> 0.9 | O16: =(1-B16)*E5b!B16 -> 3.8 | P16: =(1-C16)*E5b!C16 -> 5.6 | Q16: =(1-D16)*E5b!D16 -> 6.46 | R16: =(1-E16)*E5b!E16 -> 7.68 | S16: =(1-F16)*E5b!F16 -> 10.8 | T16: =(1-G16)*E5b!G16 -> 14 | U16: =(1-H16)*E5b!H16 -> 30 | V16: =(1-I16)*E5b!I16 -> 50 | ... Z16: =(1-M16)*E5b!M16 -> 500 | AA16: 2 | AB16: =(E5b!C16-P16-(E5b!B16-O16))/(E5b!C16-E5b!B16) -> 0 | AC16: =(E5b!D16-Q16-(E5b!C16-P16))/(E5b!D16-E5b!C16) -> 0.57 | AD16: =(E5b!E16-R16-(E5b!D16-Q16))/(E5b!E16-E5b!D16) -> 0.39 | AE16: =(E5b!F16-S16-(E5b!E16-R16))/(E5b!F16-E5b!E16) -> 0.35 | AF16: =(E5b!G16-T16-(E5b!F16-S16))/(E5b!G16-E5b!F16) -> 0.42857143 | AG16: =(E5b!H16-U16-(E5b!G16-T16))/(E5b!H16-E5b!G16) -> 0.46666667 | AH16: =(E5b!I16-V16-(E5b!H16-U16))/(E5b!I16-E5b!H16) -> 0.6 | AI16: =(E5b!J16-W16-(E5b!I16-V16))/(E5b!J16-E5b!I16) -> 0.7 | ... AL16: =(E5b!M16-Z16-(E5b!L16-Y16))/(E5b!M16-E5b!L16) -> 0.925
A17: 2039 | B17: =B16+(B$28-B$13)/15 -> 0 | C17: =C16+(C$28-C$13)/15 -> 0 | D17: =D16+(D$28-D$13)/15 -> 0.15 | E17: =E16+(E$28-E$13)/15 -> 0.2 | F17: =F16+(F$28-F$13)/15 -> 0.25 | G17: =G16+(G$28-G$13)/15 -> 0.3 | H17: =H16+(H$28-H$13)/15 -> 0.4 | I17: =I16+(I$28-I$13)/15 -> 0.5 | ... M17: =M16+(M$28-M$13)/15 -> 0.9 | O17: =(1-B17)*E5b!B17 -> 3.7333333 | P17: =(1-C17)*E5b!C17 -> 5.4666667 | Q17: =(1-D17)*E5b!D17 -> 6.3466667 | R17: =(1-E17)*E5b!E17 -> 7.5733333 | S17: =(1-F17)*E5b!F17 -> 10.65 | T17: =(1-G17)*E5b!G17 -> 14 | U17: =(1-H17)*E5b!H17 -> 30 | V17: =(1-I17)*E5b!I17 -> 50 | ... Z17: =(1-M17)*E5b!M17 -> 500 | AA17: 2 | AB17: =(E5b!C17-P17-(E5b!B17-O17))/(E5b!C17-E5b!B17) -> 0 | AC17: =(E5b!D17-Q17-(E5b!C17-P17))/(E5b!D17-E5b!C17) -> 0.56 | AD17: =(E5b!E17-R17-(E5b!D17-Q17))/(E5b!E17-E5b!D17) -> 0.38666667 | AE17: =(E5b!F17-S17-(E5b!E17-R17))/(E5b!F17-E5b!E17) -> 0.35 | AF17: =(E5b!G17-T17-(E5b!F17-S17))/(E5b!G17-E5b!F17) -> 0.42241379 | AG17: =(E5b!H17-U17-(E5b!G17-T17))/(E5b!H17-E5b!G17) -> 0.46666667 | AH17: =(E5b!I17-V17-(E5b!H17-U17))/(E5b!I17-E5b!H17) -> 0.6 | AI17: =(E5b!J17-W17-(E5b!I17-V17))/(E5b!J17-E5b!I17) -> 0.7 | ... AL17: =(E5b!M17-Z17-(E5b!L17-Y17))/(E5b!M17-E5b!L17) -> 0.925
A18: 2040 | B18: =B17+(B$28-B$13)/15 -> 0 | C18: =C17+(C$28-C$13)/15 -> 0 | D18: =D17+(D$28-D$13)/15 -> 0.15 | E18: =E17+(E$28-E$13)/15 -> 0.2 | F18: =F17+(F$28-F$13)/15 -> 0.25 | G18: =G17+(G$28-G$13)/15 -> 0.3 | H18: =H17+(H$28-H$13)/15 -> 0.4 | I18: =I17+(I$28-I$13)/15 -> 0.5 | ... M18: =M17+(M$28-M$13)/15 -> 0.9 | O18: =(1-B18)*E5b!B18 -> 3.6666667 | P18: =(1-C18)*E5b!C18 -> 5.3333333 | Q18: =(1-D18)*E5b!D18 -> 6.2333333 | R18: =(1-E18)*E5b!E18 -> 7.4666667 | S18: =(1-F18)*E5b!F18 -> 10.5 | T18: =(1-G18)*E5b!G18 -> 14 | U18: =(1-H18)*E5b!H18 -> 30 | V18: =(1-I18)*E5b!I18 -> 50 | ... Z18: =(1-M18)*E5b!M18 -> 500 | AA18: 2 | AB18: =(E5b!C18-P18-(E5b!B18-O18))/(E5b!C18-E5b!B18) -> 0 | AC18: =(E5b!D18-Q18-(E5b!C18-P18))/(E5b!D18-E5b!C18) -> 0.55 | AD18: =(E5b!E18-R18-(E5b!D18-Q18))/(E5b!E18-E5b!D18) -> 0.38333333 | AE18: =(E5b!F18-S18-(E5b!E18-R18))/(E5b!F18-E5b!E18) -> 0.35 | AF18: =(E5b!G18-T18-(E5b!F18-S18))/(E5b!G18-E5b!F18) -> 0.41666667 | AG18: =(E5b!H18-U18-(E5b!G18-T18))/(E5b!H18-E5b!G18) -> 0.46666667 | AH18: =(E5b!I18-V18-(E5b!H18-U18))/(E5b!I18-E5b!H18) -> 0.6 | AI18: =(E5b!J18-W18-(E5b!I18-V18))/(E5b!J18-E5b!I18) -> 0.7 | ... AL18: =(E5b!M18-Z18-(E5b!L18-Y18))/(E5b!M18-E5b!L18) -> 0.925
A19: 2041 | B19: =B18+(B$28-B$13)/15 -> 0 | C19: =C18+(C$28-C$13)/15 -> 0 | D19: =D18+(D$28-D$13)/15 -> 0.15 | E19: =E18+(E$28-E$13)/15 -> 0.2 | F19: =F18+(F$28-F$13)/15 -> 0.25 | G19: =G18+(G$28-G$13)/15 -> 0.3 | H19: =H18+(H$28-H$13)/15 -> 0.4 | I19: =I18+(I$28-I$13)/15 -> 0.5 | ... M19: =M18+(M$28-M$13)/15 -> 0.9 | O19: =(1-B19)*E5b!B19 -> 3.6 | P19: =(1-C19)*E5b!C19 -> 5.2 | Q19: =(1-D19)*E5b!D19 -> 6.12 | R19: =(1-E19)*E5b!E19 -> 7.36 | S19: =(1-F19)*E5b!F19 -> 10.35 | T19: =(1-G19)*E5b!G19 -> 14 | U19: =(1-H19)*E5b!H19 -> 30 | V19: =(1-I19)*E5b!I19 -> 50 | ... Z19: =(1-M19)*E5b!M19 -> 500 | AA19: 2 | AB19: =(E5b!C19-P19-(E5b!B19-O19))/(E5b!C19-E5b!B19) -> 0 | AC19: =(E5b!D19-Q19-(E5b!C19-P19))/(E5b!D19-E5b!C19) -> 0.54 | AD19: =(E5b!E19-R19-(E5b!D19-Q19))/(E5b!E19-E5b!D19) -> 0.38 | AE19: =(E5b!F19-S19-(E5b!E19-R19))/(E5b!F19-E5b!E19) -> 0.35 | AF19: =(E5b!G19-T19-(E5b!F19-S19))/(E5b!G19-E5b!F19) -> 0.41129032 | AG19: =(E5b!H19-U19-(E5b!G19-T19))/(E5b!H19-E5b!G19) -> 0.46666667 | AH19: =(E5b!I19-V19-(E5b!H19-U19))/(E5b!I19-E5b!H19) -> 0.6 | AI19: =(E5b!J19-W19-(E5b!I19-V19))/(E5b!J19-E5b!I19) -> 0.7 | ... AL19: =(E5b!M19-Z19-(E5b!L19-Y19))/(E5b!M19-E5b!L19) -> 0.925
A20: 2042 | B20: =B19+(B$28-B$13)/15 -> 0 | C20: =C19+(C$28-C$13)/15 -> 0 | D20: =D19+(D$28-D$13)/15 -> 0.15 | E20: =E19+(E$28-E$13)/15 -> 0.2 | F20: =F19+(F$28-F$13)/15 -> 0.25 | G20: =G19+(G$28-G$13)/15 -> 0.3 | H20: =H19+(H$28-H$13)/15 -> 0.4 | I20: =I19+(I$28-I$13)/15 -> 0.5 | ... M20: =M19+(M$28-M$13)/15 -> 0.9 | O20: =(1-B20)*E5b!B20 -> 3.5333333 | P20: =(1-C20)*E5b!C20 -> 5.0666667 | Q20: =(1-D20)*E5b!D20 -> 6.0066667 | R20: =(1-E20)*E5b!E20 -> 7.2533333 | S20: =(1-F20)*E5b!F20 -> 10.2 | T20: =(1-G20)*E5b!G20 -> 14 | U20: =(1-H20)*E5b!H20 -> 30 | V20: =(1-I20)*E5b!I20 -> 50 | ... Z20: =(1-M20)*E5b!M20 -> 500 | AA20: 2 | AB20: =(E5b!C20-P20-(E5b!B20-O20))/(E5b!C20-E5b!B20) -> 0 | AC20: =(E5b!D20-Q20-(E5b!C20-P20))/(E5b!D20-E5b!C20) -> 0.53 | AD20: =(E5b!E20-R20-(E5b!D20-Q20))/(E5b!E20-E5b!D20) -> 0.37666667 | AE20: =(E5b!F20-S20-(E5b!E20-R20))/(E5b!F20-E5b!E20) -> 0.35 | AF20: =(E5b!G20-T20-(E5b!F20-S20))/(E5b!G20-E5b!F20) -> 0.40625 | AG20: =(E5b!H20-U20-(E5b!G20-T20))/(E5b!H20-E5b!G20) -> 0.46666667 | AH20: =(E5b!I20-V20-(E5b!H20-U20))/(E5b!I20-E5b!H20) -> 0.6 | AI20: =(E5b!J20-W20-(E5b!I20-V20))/(E5b!J20-E5b!I20) -> 0.7 | ... AL20: =(E5b!M20-Z20-(E5b!L20-Y20))/(E5b!M20-E5b!L20) -> 0.925
A21: 2043 | B21: =B20+(B$28-B$13)/15 -> 0 | C21: =C20+(C$28-C$13)/15 -> 0 | D21: =D20+(D$28-D$13)/15 -> 0.15 | E21: =E20+(E$28-E$13)/15 -> 0.2 | F21: =F20+(F$28-F$13)/15 -> 0.25 | G21: =G20+(G$28-G$13)/15 -> 0.3 | H21: =H20+(H$28-H$13)/15 -> 0.4 | I21: =I20+(I$28-I$13)/15 -> 0.5 | ... M21: =M20+(M$28-M$13)/15 -> 0.9 | O21: =(1-B21)*E5b!B21 -> 3.4666667 | P21: =(1-C21)*E5b!C21 -> 4.9333333 | Q21: =(1-D21)*E5b!D21 -> 5.8933333 | R21: =(1-E21)*E5b!E21 -> 7.1466667 | S21: =(1-F21)*E5b!F21 -> 10.05 | T21: =(1-G21)*E5b!G21 -> 14 | U21: =(1-H21)*E5b!H21 -> 30 | V21: =(1-I21)*E5b!I21 -> 50 | ... Z21: =(1-M21)*E5b!M21 -> 500 | AA21: 2 | AB21: =(E5b!C21-P21-(E5b!B21-O21))/(E5b!C21-E5b!B21) -> 0 | AC21: =(E5b!D21-Q21-(E5b!C21-P21))/(E5b!D21-E5b!C21) -> 0.52 | AD21: =(E5b!E21-R21-(E5b!D21-Q21))/(E5b!E21-E5b!D21) -> 0.37333333 | AE21: =(E5b!F21-S21-(E5b!E21-R21))/(E5b!F21-E5b!E21) -> 0.35 | AF21: =(E5b!G21-T21-(E5b!F21-S21))/(E5b!G21-E5b!F21) -> 0.40151515 | AG21: =(E5b!H21-U21-(E5b!G21-T21))/(E5b!H21-E5b!G21) -> 0.46666667 | AH21: =(E5b!I21-V21-(E5b!H21-U21))/(E5b!I21-E5b!H21) -> 0.6 | AI21: =(E5b!J21-W21-(E5b!I21-V21))/(E5b!J21-E5b!I21) -> 0.7 | ... AL21: =(E5b!M21-Z21-(E5b!L21-Y21))/(E5b!M21-E5b!L21) -> 0.925
A22: 2044 | B22: =B21+(B$28-B$13)/15 -> 0 | C22: =C21+(C$28-C$13)/15 -> 0 | D22: =D21+(D$28-D$13)/15 -> 0.15 | E22: =E21+(E$28-E$13)/15 -> 0.2 | F22: =F21+(F$28-F$13)/15 -> 0.25 | G22: =G21+(G$28-G$13)/15 -> 0.3 | H22: =H21+(H$28-H$13)/15 -> 0.4 | I22: =I21+(I$28-I$13)/15 -> 0.5 | ... M22: =M21+(M$28-M$13)/15 -> 0.9 | O22: =(1-B22)*E5b!B22 -> 3.4 | P22: =(1-C22)*E5b!C22 -> 4.8 | Q22: =(1-D22)*E5b!D22 -> 5.78 | R22: =(1-E22)*E5b!E22 -> 7.04 | S22: =(1-F22)*E5b!F22 -> 9.9 | T22: =(1-G22)*E5b!G22 -> 14 | U22: =(1-H22)*E5b!H22 -> 30 | V22: =(1-I22)*E5b!I22 -> 50 | ... Z22: =(1-M22)*E5b!M22 -> 500 | AA22: 2 | AB22: =(E5b!C22-P22-(E5b!B22-O22))/(E5b!C22-E5b!B22) -> 0 | AC22: =(E5b!D22-Q22-(E5b!C22-P22))/(E5b!D22-E5b!C22) -> 0.51 | AD22: =(E5b!E22-R22-(E5b!D22-Q22))/(E5b!E22-E5b!D22) -> 0.37 | AE22: =(E5b!F22-S22-(E5b!E22-R22))/(E5b!F22-E5b!E22) -> 0.35 | AF22: =(E5b!G22-T22-(E5b!F22-S22))/(E5b!G22-E5b!F22) -> 0.39705882 | AG22: =(E5b!H22-U22-(E5b!G22-T22))/(E5b!H22-E5b!G22) -> 0.46666667 | AH22: =(E5b!I22-V22-(E5b!H22-U22))/(E5b!I22-E5b!H22) -> 0.6 | AI22: =(E5b!J22-W22-(E5b!I22-V22))/(E5b!J22-E5b!I22) -> 0.7 | ... AL22: =(E5b!M22-Z22-(E5b!L22-Y22))/(E5b!M22-E5b!L22) -> 0.925
A23: 2045 | B23: =B22+(B$28-B$13)/15 -> 0 | C23: =C22+(C$28-C$13)/15 -> 0 | D23: =D22+(D$28-D$13)/15 -> 0.15 | E23: =E22+(E$28-E$13)/15 -> 0.2 | F23: =F22+(F$28-F$13)/15 -> 0.25 | G23: =G22+(G$28-G$13)/15 -> 0.3 | H23: =H22+(H$28-H$13)/15 -> 0.4 | I23: =I22+(I$28-I$13)/15 -> 0.5 | ... M23: =M22+(M$28-M$13)/15 -> 0.9 | O23: =(1-B23)*E5b!B23 -> 3.3333333 | P23: =(1-C23)*E5b!C23 -> 4.6666667 | Q23: =(1-D23)*E5b!D23 -> 5.6666667 | R23: =(1-E23)*E5b!E23 -> 6.9333333 | S23: =(1-F23)*E5b!F23 -> 9.75 | T23: =(1-G23)*E5b!G23 -> 14 | U23: =(1-H23)*E5b!H23 -> 30 | V23: =(1-I23)*E5b!I23 -> 50 | ... Z23: =(1-M23)*E5b!M23 -> 500 | AA23: 2 | AB23: =(E5b!C23-P23-(E5b!B23-O23))/(E5b!C23-E5b!B23) -> 0 | AC23: =(E5b!D23-Q23-(E5b!C23-P23))/(E5b!D23-E5b!C23) -> 0.5 | AD23: =(E5b!E23-R23-(E5b!D23-Q23))/(E5b!E23-E5b!D23) -> 0.36666667 | AE23: =(E5b!F23-S23-(E5b!E23-R23))/(E5b!F23-E5b!E23) -> 0.35 | AF23: =(E5b!G23-T23-(E5b!F23-S23))/(E5b!G23-E5b!F23) -> 0.39285714 | AG23: =(E5b!H23-U23-(E5b!G23-T23))/(E5b!H23-E5b!G23) -> 0.46666667 | AH23: =(E5b!I23-V23-(E5b!H23-U23))/(E5b!I23-E5b!H23) -> 0.6 | AI23: =(E5b!J23-W23-(E5b!I23-V23))/(E5b!J23-E5b!I23) -> 0.7 | ... AL23: =(E5b!M23-Z23-(E5b!L23-Y23))/(E5b!M23-E5b!L23) -> 0.925
A24: 2046 | B24: =B23+(B$28-B$13)/15 -> 0 | C24: =C23+(C$28-C$13)/15 -> 0 | D24: =D23+(D$28-D$13)/15 -> 0.15 | E24: =E23+(E$28-E$13)/15 -> 0.2 | F24: =F23+(F$28-F$13)/15 -> 0.25 | G24: =G23+(G$28-G$13)/15 -> 0.3 | H24: =H23+(H$28-H$13)/15 -> 0.4 | I24: =I23+(I$28-I$13)/15 -> 0.5 | ... M24: =M23+(M$28-M$13)/15 -> 0.9 | O24: =(1-B24)*E5b!B24 -> 3.2666667 | P24: =(1-C24)*E5b!C24 -> 4.5333333 | Q24: =(1-D24)*E5b!D24 -> 5.5533333 | R24: =(1-E24)*E5b!E24 -> 6.8266667 | S24: =(1-F24)*E5b!F24 -> 9.6 | T24: =(1-G24)*E5b!G24 -> 14 | U24: =(1-H24)*E5b!H24 -> 30 | V24: =(1-I24)*E5b!I24 -> 50 | ... Z24: =(1-M24)*E5b!M24 -> 500 | AA24: 2 | AB24: =(E5b!C24-P24-(E5b!B24-O24))/(E5b!C24-E5b!B24) -> 0 | AC24: =(E5b!D24-Q24-(E5b!C24-P24))/(E5b!D24-E5b!C24) -> 0.49 | AD24: =(E5b!E24-R24-(E5b!D24-Q24))/(E5b!E24-E5b!D24) -> 0.36333333 | AE24: =(E5b!F24-S24-(E5b!E24-R24))/(E5b!F24-E5b!E24) -> 0.35 | AF24: =(E5b!G24-T24-(E5b!F24-S24))/(E5b!G24-E5b!F24) -> 0.38888889 | AG24: =(E5b!H24-U24-(E5b!G24-T24))/(E5b!H24-E5b!G24) -> 0.46666667 | AH24: =(E5b!I24-V24-(E5b!H24-U24))/(E5b!I24-E5b!H24) -> 0.6 | AI24: =(E5b!J24-W24-(E5b!I24-V24))/(E5b!J24-E5b!I24) -> 0.7 | ... AL24: =(E5b!M24-Z24-(E5b!L24-Y24))/(E5b!M24-E5b!L24) -> 0.925
A25: 2047 | B25: =B24+(B$28-B$13)/15 -> 0 | C25: =C24+(C$28-C$13)/15 -> 0 | D25: =D24+(D$28-D$13)/15 -> 0.15 | E25: =E24+(E$28-E$13)/15 -> 0.2 | F25: =F24+(F$28-F$13)/15 -> 0.25 | G25: =G24+(G$28-G$13)/15 -> 0.3 | H25: =H24+(H$28-H$13)/15 -> 0.4 | I25: =I24+(I$28-I$13)/15 -> 0.5 | ... M25: =M24+(M$28-M$13)/15 -> 0.9 | O25: =(1-B25)*E5b!B25 -> 3.2 | P25: =(1-C25)*E5b!C25 -> 4.4 | Q25: =(1-D25)*E5b!D25 -> 5.44 | R25: =(1-E25)*E5b!E25 -> 6.72 | S25: =(1-F25)*E5b!F25 -> 9.45 | T25: =(1-G25)*E5b!G25 -> 14 | U25: =(1-H25)*E5b!H25 -> 30 | V25: =(1-I25)*E5b!I25 -> 50 | ... Z25: =(1-M25)*E5b!M25 -> 500 | AA25: 2 | AB25: =(E5b!C25-P25-(E5b!B25-O25))/(E5b!C25-E5b!B25) -> 0 | AC25: =(E5b!D25-Q25-(E5b!C25-P25))/(E5b!D25-E5b!C25) -> 0.48 | AD25: =(E5b!E25-R25-(E5b!D25-Q25))/(E5b!E25-E5b!D25) -> 0.36 | AE25: =(E5b!F25-S25-(E5b!E25-R25))/(E5b!F25-E5b!E25) -> 0.35 | AF25: =(E5b!G25-T25-(E5b!F25-S25))/(E5b!G25-E5b!F25) -> 0.38513514 | AG25: =(E5b!H25-U25-(E5b!G25-T25))/(E5b!H25-E5b!G25) -> 0.46666667 | AH25: =(E5b!I25-V25-(E5b!H25-U25))/(E5b!I25-E5b!H25) -> 0.6 | AI25: =(E5b!J25-W25-(E5b!I25-V25))/(E5b!J25-E5b!I25) -> 0.7 | ... AL25: =(E5b!M25-Z25-(E5b!L25-Y25))/(E5b!M25-E5b!L25) -> 0.925
... A27: 2049 | B27: =B26+(B$28-B$13)/15 -> 0 | C27: =C26+(C$28-C$13)/15 -> 0 | D27: =D26+(D$28-D$13)/15 -> 0.15 | E27: =E26+(E$28-E$13)/15 -> 0.2 | F27: =F26+(F$28-F$13)/15 -> 0.25 | G27: =G26+(G$28-G$13)/15 -> 0.3 | H27: =H26+(H$28-H$13)/15 -> 0.4 | I27: =I26+(I$28-I$13)/15 -> 0.5 | ... M27: =M26+(M$28-M$13)/15 -> 0.9 | O27: =(1-B27)*E5b!B27 -> 3.0666667 | P27: =(1-C27)*E5b!C27 -> 4.1333333 | Q27: =(1-D27)*E5b!D27 -> 5.2133333 | R27: =(1-E27)*E5b!E27 -> 6.5066667 | S27: =(1-F27)*E5b!F27 -> 9.15 | T27: =(1-G27)*E5b!G27 -> 14 | U27: =(1-H27)*E5b!H27 -> 30 | V27: =(1-I27)*E5b!I27 -> 50 | ... Z27: =(1-M27)*E5b!M27 -> 500 | AA27: 2 | AB27: =(E5b!C27-P27-(E5b!B27-O27))/(E5b!C27-E5b!B27) -> 0 | AC27: =(E5b!D27-Q27-(E5b!C27-P27))/(E5b!D27-E5b!C27) -> 0.46 | AD27: =(E5b!E27-R27-(E5b!D27-Q27))/(E5b!E27-E5b!D27) -> 0.35333333 | AE27: =(E5b!F27-S27-(E5b!E27-R27))/(E5b!F27-E5b!E27) -> 0.35 | AF27: =(E5b!G27-T27-(E5b!F27-S27))/(E5b!G27-E5b!F27) -> 0.37820513 | AG27: =(E5b!H27-U27-(E5b!G27-T27))/(E5b!H27-E5b!G27) -> 0.46666667 | AH27: =(E5b!I27-V27-(E5b!H27-U27))/(E5b!I27-E5b!H27) -> 0.6 | AI27: =(E5b!J27-W27-(E5b!I27-V27))/(E5b!J27-E5b!I27) -> 0.7 | ... AL27: =(E5b!M27-Z27-(E5b!L27-Y27))/(E5b!M27-E5b!L27) -> 0.925
A28: 2050 | B28: 0 | C28: 0 | D28: 0.15 | E28: 0.2 | F28: 0.25 | G28: 0.3 | H28: 0.4 | I28: 0.5 | J28: 0.6 | K28: 0.7 | L28: 0.8 | M28: 0.9 | O28: =(1-B28)*E5b!B28 -> 3 | P28: =(1-C28)*E5b!C28 -> 4 | Q28: =(1-D28)*E5b!D28 -> 5.1 | R28: =(1-E28)*E5b!E28 -> 6.4 | S28: =(1-F28)*E5b!F28 -> 9 | T28: =(1-G28)*E5b!G28 -> 14 | U28: =(1-H28)*E5b!H28 -> 30 | V28: =(1-I28)*E5b!I28 -> 50 | ... Z28: =(1-M28)*E5b!M28 -> 500 | AA28: 1 | AB28: =(E5b!C28-P28-(E5b!B28-O28))/(E5b!C28-E5b!B28) -> 0 | AC28: =(E5b!D28-Q28-(E5b!C28-P28))/(E5b!D28-E5b!C28) -> 0.45 | AD28: =(E5b!E28-R28-(E5b!D28-Q28))/(E5b!E28-E5b!D28) -> 0.35 | AE28: =(E5b!F28-S28-(E5b!E28-R28))/(E5b!F28-E5b!E28) -> 0.35 | AF28: =(E5b!G28-T28-(E5b!F28-S28))/(E5b!G28-E5b!F28) -> 0.375 | AG28: =(E5b!H28-U28-(E5b!G28-T28))/(E5b!H28-E5b!G28) -> 0.46666667 | AH28: =(E5b!I28-V28-(E5b!H28-U28))/(E5b!I28-E5b!H28) -> 0.6 | AI28: =(E5b!J28-W28-(E5b!I28-V28))/(E5b!J28-E5b!I28) -> 0.7 | ... AL28: =(E5b!M28-Z28-(E5b!L28-Y28))/(E5b!M28-E5b!L28) -> 0.925
A29: 2051 | B29: =B28+(B$48-B$28)/20 -> 0 | C29: =C28+(C$48-C$28)/20 -> 0 | D29: =D28+(D$48-D$28)/20 -> 0.1525 | E29: =E28+(E$48-E$28)/20 -> 0.2025 | F29: =F28+(F$48-F$28)/20 -> 0.2525 | G29: =G28+(G$48-G$28)/20 -> 0.305 | H29: =H28+(H$48-H$28)/20 -> 0.405 | I29: =I28+(I$48-I$28)/20 -> 0.505 | ... M29: =M28+(M$48-M$28)/20 -> 0.9 | O29: =(1-B29)*E5b!B29 -> 3 | P29: =(1-C29)*E5b!C29 -> 4 | Q29: =(1-D29)*E5b!D29 -> 5.042625 | R29: =(1-E29)*E5b!E29 -> 6.340125 | S29: =(1-F29)*E5b!F29 -> 8.89525 | T29: =(1-G29)*E5b!G29 -> 13.9 | U29: =(1-H29)*E5b!H29 -> 29.75 | V29: =(1-I29)*E5b!I29 -> 49.5 | ... Z29: =(1-M29)*E5b!M29 -> 500 | AA29: 1 | AB29: =(E5b!C29-P29-(E5b!B29-O29))/(E5b!C29-E5b!B29) -> 0 | AC29: =(E5b!D29-Q29-(E5b!C29-P29))/(E5b!D29-E5b!C29) -> 0.46532051 | AD29: =(E5b!E29-R29-(E5b!D29-Q29))/(E5b!E29-E5b!D29) -> 0.35125 | AE29: =(E5b!F29-S29-(E5b!E29-R29))/(E5b!F29-E5b!E29) -> 0.35313291 | AF29: =(E5b!G29-T29-(E5b!F29-S29))/(E5b!G29-E5b!F29) -> 0.38212963 | AG29: =(E5b!H29-U29-(E5b!G29-T29))/(E5b!H29-E5b!G29) -> 0.47166667 | AH29: =(E5b!I29-V29-(E5b!H29-U29))/(E5b!I29-E5b!H29) -> 0.605 | AI29: =(E5b!J29-W29-(E5b!I29-V29))/(E5b!J29-E5b!I29) -> 0.705 | ... AL29: =(E5b!M29-Z29-(E5b!L29-Y29))/(E5b!M29-E5b!L29) -> 0.925
A30: 2052 | B30: =B29+(B$48-B$28)/20 -> 0 | C30: =C29+(C$48-C$28)/20 -> 0 | D30: =D29+(D$48-D$28)/20 -> 0.155 | E30: =E29+(E$48-E$28)/20 -> 0.205 | F30: =F29+(F$48-F$28)/20 -> 0.255 | G30: =G29+(G$48-G$28)/20 -> 0.31 | H30: =H29+(H$48-H$28)/20 -> 0.41 | I30: =I29+(I$48-I$28)/20 -> 0.51 | ... M30: =M29+(M$48-M$28)/20 -> 0.9 | O30: =(1-B30)*E5b!B30 -> 3 | P30: =(1-C30)*E5b!C30 -> 4 | Q30: =(1-D30)*E5b!D30 -> 4.9855 | R30: =(1-E30)*E5b!E30 -> 6.2805 | S30: =(1-F30)*E5b!F30 -> 8.791 | T30: =(1-G30)*E5b!G30 -> 13.8 | U30: =(1-H30)*E5b!H30 -> 29.5 | V30: =(1-I30)*E5b!I30 -> 49 | ... Z30: =(1-M30)*E5b!M30 -> 500 | AA30: 1 | AB30: =(E5b!C30-P30-(E5b!B30-O30))/(E5b!C30-E5b!B30) -> 0 | AC30: =(E5b!D30-Q30-(E5b!C30-P30))/(E5b!D30-E5b!C30) -> 0.48131579 | AD30: =(E5b!E30-R30-(E5b!D30-Q30))/(E5b!E30-E5b!D30) -> 0.3525 | AE30: =(E5b!F30-S30-(E5b!E30-R30))/(E5b!F30-E5b!E30) -> 0.35628205 | AF30: =(E5b!G30-T30-(E5b!F30-S30))/(E5b!G30-E5b!F30) -> 0.38914634 | AG30: =(E5b!H30-U30-(E5b!G30-T30))/(E5b!H30-E5b!G30) -> 0.47666667 | AH30: =(E5b!I30-V30-(E5b!H30-U30))/(E5b!I30-E5b!H30) -> 0.61 | AI30: =(E5b!J30-W30-(E5b!I30-V30))/(E5b!J30-E5b!I30) -> 0.71 | ... AL30: =(E5b!M30-Z30-(E5b!L30-Y30))/(E5b!M30-E5b!L30) -> 0.925
A31: 2053 | B31: =B30+(B$48-B$28)/20 -> 0 | C31: =C30+(C$48-C$28)/20 -> 0 | D31: =D30+(D$48-D$28)/20 -> 0.1575 | E31: =E30+(E$48-E$28)/20 -> 0.2075 | F31: =F30+(F$48-F$28)/20 -> 0.2575 | G31: =G30+(G$48-G$28)/20 -> 0.315 | H31: =H30+(H$48-H$28)/20 -> 0.415 | I31: =I30+(I$48-I$28)/20 -> 0.515 | ... M31: =M30+(M$48-M$28)/20 -> 0.9 | O31: =(1-B31)*E5b!B31 -> 3 | P31: =(1-C31)*E5b!C31 -> 4 | Q31: =(1-D31)*E5b!D31 -> 4.928625 | R31: =(1-E31)*E5b!E31 -> 6.221125 | S31: =(1-F31)*E5b!F31 -> 8.68725 | T31: =(1-G31)*E5b!G31 -> 13.7 | U31: =(1-H31)*E5b!H31 -> 29.25 | V31: =(1-I31)*E5b!I31 -> 48.5 | ... Z31: =(1-M31)*E5b!M31 -> 500 | AA31: 1 | AB31: =(E5b!C31-P31-(E5b!B31-O31))/(E5b!C31-E5b!B31) -> 0 | AC31: =(E5b!D31-Q31-(E5b!C31-P31))/(E5b!D31-E5b!C31) -> 0.49804054 | AD31: =(E5b!E31-R31-(E5b!D31-Q31))/(E5b!E31-E5b!D31) -> 0.35375 | AE31: =(E5b!F31-S31-(E5b!E31-R31))/(E5b!F31-E5b!E31) -> 0.35944805 | AF31: =(E5b!G31-T31-(E5b!F31-S31))/(E5b!G31-E5b!F31) -> 0.39605422 | AG31: =(E5b!H31-U31-(E5b!G31-T31))/(E5b!H31-E5b!G31) -> 0.48166667 | AH31: =(E5b!I31-V31-(E5b!H31-U31))/(E5b!I31-E5b!H31) -> 0.615 | AI31: =(E5b!J31-W31-(E5b!I31-V31))/(E5b!J31-E5b!I31) -> 0.715 | ... AL31: =(E5b!M31-Z31-(E5b!L31-Y31))/(E5b!M31-E5b!L31) -> 0.925
A32: 2054 | B32: =B31+(B$48-B$28)/20 -> 0 | C32: =C31+(C$48-C$28)/20 -> 0 | D32: =D31+(D$48-D$28)/20 -> 0.16 | E32: =E31+(E$48-E$28)/20 -> 0.21 | F32: =F31+(F$48-F$28)/20 -> 0.26 | G32: =G31+(G$48-G$28)/20 -> 0.32 | H32: =H31+(H$48-H$28)/20 -> 0.42 | I32: =I31+(I$48-I$28)/20 -> 0.52 | ... M32: =M31+(M$48-M$28)/20 -> 0.9 | O32: =(1-B32)*E5b!B32 -> 3 | P32: =(1-C32)*E5b!C32 -> 4 | Q32: =(1-D32)*E5b!D32 -> 4.872 | R32: =(1-E32)*E5b!E32 -> 6.162 | S32: =(1-F32)*E5b!F32 -> 8.584 | T32: =(1-G32)*E5b!G32 -> 13.6 | U32: =(1-H32)*E5b!H32 -> 29 | V32: =(1-I32)*E5b!I32 -> 48 | ... Z32: =(1-M32)*E5b!M32 -> 500 | AA32: 1 | AB32: =(E5b!C32-P32-(E5b!B32-O32))/(E5b!C32-E5b!B32) -> 0 | AC32: =(E5b!D32-Q32-(E5b!C32-P32))/(E5b!D32-E5b!C32) -> 0.51555556 | AD32: =(E5b!E32-R32-(E5b!D32-Q32))/(E5b!E32-E5b!D32) -> 0.355 | AE32: =(E5b!F32-S32-(E5b!E32-R32))/(E5b!F32-E5b!E32) -> 0.36263158 | AF32: =(E5b!G32-T32-(E5b!F32-S32))/(E5b!G32-E5b!F32) -> 0.40285714 | AG32: =(E5b!H32-U32-(E5b!G32-T32))/(E5b!H32-E5b!G32) -> 0.48666667 | AH32: =(E5b!I32-V32-(E5b!H32-U32))/(E5b!I32-E5b!H32) -> 0.62 | AI32: =(E5b!J32-W32-(E5b!I32-V32))/(E5b!J32-E5b!I32) -> 0.72 | ... AL32: =(E5b!M32-Z32-(E5b!L32-Y32))/(E5b!M32-E5b!L32) -> 0.925
A33: 2055 | B33: =B32+(B$48-B$28)/20 -> 0 | C33: =C32+(C$48-C$28)/20 -> 0 | D33: =D32+(D$48-D$28)/20 -> 0.1625 | E33: =E32+(E$48-E$28)/20 -> 0.2125 | F33: =F32+(F$48-F$28)/20 -> 0.2625 | G33: =G32+(G$48-G$28)/20 -> 0.325 | H33: =H32+(H$48-H$28)/20 -> 0.425 | I33: =I32+(I$48-I$28)/20 -> 0.525 | ... M33: =M32+(M$48-M$28)/20 -> 0.9 | O33: =(1-B33)*E5b!B33 -> 3 | P33: =(1-C33)*E5b!C33 -> 4 | Q33: =(1-D33)*E5b!D33 -> 4.815625 | R33: =(1-E33)*E5b!E33 -> 6.103125 | S33: =(1-F33)*E5b!F33 -> 8.48125 | T33: =(1-G33)*E5b!G33 -> 13.5 | U33: =(1-H33)*E5b!H33 -> 28.75 | V33: =(1-I33)*E5b!I33 -> 47.5 | ... Z33: =(1-M33)*E5b!M33 -> 500 | AA33: 1 | AB33: =(E5b!C33-P33-(E5b!B33-O33))/(E5b!C33-E5b!B33) -> 0 | AC33: =(E5b!D33-Q33-(E5b!C33-P33))/(E5b!D33-E5b!C33) -> 0.53392857 | AD33: =(E5b!E33-R33-(E5b!D33-Q33))/(E5b!E33-E5b!D33) -> 0.35625 | AE33: =(E5b!F33-S33-(E5b!E33-R33))/(E5b!F33-E5b!E33) -> 0.36583333 | AF33: =(E5b!G33-T33-(E5b!F33-S33))/(E5b!G33-E5b!F33) -> 0.40955882 | AG33: =(E5b!H33-U33-(E5b!G33-T33))/(E5b!H33-E5b!G33) -> 0.49166667 | AH33: =(E5b!I33-V33-(E5b!H33-U33))/(E5b!I33-E5b!H33) -> 0.625 | AI33: =(E5b!J33-W33-(E5b!I33-V33))/(E5b!J33-E5b!I33) -> 0.725 | ... AL33: =(E5b!M33-Z33-(E5b!L33-Y33))/(E5b!M33-E5b!L33) -> 0.925
A34: 2056 | B34: =B33+(B$48-B$28)/20 -> 0 | C34: =C33+(C$48-C$28)/20 -> 0 | D34: =D33+(D$48-D$28)/20 -> 0.165 | E34: =E33+(E$48-E$28)/20 -> 0.215 | F34: =F33+(F$48-F$28)/20 -> 0.265 | G34: =G33+(G$48-G$28)/20 -> 0.33 | H34: =H33+(H$48-H$28)/20 -> 0.43 | I34: =I33+(I$48-I$28)/20 -> 0.53 | ... M34: =M33+(M$48-M$28)/20 -> 0.9 | O34: =(1-B34)*E5b!B34 -> 3 | P34: =(1-C34)*E5b!C34 -> 4 | Q34: =(1-D34)*E5b!D34 -> 4.7595 | R34: =(1-E34)*E5b!E34 -> 6.0445 | S34: =(1-F34)*E5b!F34 -> 8.379 | T34: =(1-G34)*E5b!G34 -> 13.4 | U34: =(1-H34)*E5b!H34 -> 28.5 | V34: =(1-I34)*E5b!I34 -> 47 | ... Z34: =(1-M34)*E5b!M34 -> 500 | AA34: 1 | AB34: =(E5b!C34-P34-(E5b!B34-O34))/(E5b!C34-E5b!B34) -> 0 | AC34: =(E5b!D34-Q34-(E5b!C34-P34))/(E5b!D34-E5b!C34) -> 0.55323529 | AD34: =(E5b!E34-R34-(E5b!D34-Q34))/(E5b!E34-E5b!D34) -> 0.3575 | AE34: =(E5b!F34-S34-(E5b!E34-R34))/(E5b!F34-E5b!E34) -> 0.36905405 | AF34: =(E5b!G34-T34-(E5b!F34-S34))/(E5b!G34-E5b!F34) -> 0.41616279 | AG34: =(E5b!H34-U34-(E5b!G34-T34))/(E5b!H34-E5b!G34) -> 0.49666667 | AH34: =(E5b!I34-V34-(E5b!H34-U34))/(E5b!I34-E5b!H34) -> 0.63 | AI34: =(E5b!J34-W34-(E5b!I34-V34))/(E5b!J34-E5b!I34) -> 0.73 | ... AL34: =(E5b!M34-Z34-(E5b!L34-Y34))/(E5b!M34-E5b!L34) -> 0.925
A35: 2057 | B35: =B34+(B$48-B$28)/20 -> 0 | C35: =C34+(C$48-C$28)/20 -> 0 | D35: =D34+(D$48-D$28)/20 -> 0.1675 | E35: =E34+(E$48-E$28)/20 -> 0.2175 | F35: =F34+(F$48-F$28)/20 -> 0.2675 | G35: =G34+(G$48-G$28)/20 -> 0.335 | H35: =H34+(H$48-H$28)/20 -> 0.435 | I35: =I34+(I$48-I$28)/20 -> 0.535 | ... M35: =M34+(M$48-M$28)/20 -> 0.9 | O35: =(1-B35)*E5b!B35 -> 3 | P35: =(1-C35)*E5b!C35 -> 4 | Q35: =(1-D35)*E5b!D35 -> 4.703625 | R35: =(1-E35)*E5b!E35 -> 5.986125 | S35: =(1-F35)*E5b!F35 -> 8.27725 | T35: =(1-G35)*E5b!G35 -> 13.3 | U35: =(1-H35)*E5b!H35 -> 28.25 | V35: =(1-I35)*E5b!I35 -> 46.5 | ... Z35: =(1-M35)*E5b!M35 -> 500 | AA35: 1 | AB35: =(E5b!C35-P35-(E5b!B35-O35))/(E5b!C35-E5b!B35) -> 0 | AC35: =(E5b!D35-Q35-(E5b!C35-P35))/(E5b!D35-E5b!C35) -> 0.57356061 | AD35: =(E5b!E35-R35-(E5b!D35-Q35))/(E5b!E35-E5b!D35) -> 0.35875 | AE35: =(E5b!F35-S35-(E5b!E35-R35))/(E5b!F35-E5b!E35) -> 0.37229452 | AF35: =(E5b!G35-T35-(E5b!F35-S35))/(E5b!G35-E5b!F35) -> 0.42267241 | AG35: =(E5b!H35-U35-(E5b!G35-T35))/(E5b!H35-E5b!G35) -> 0.50166667 | AH35: =(E5b!I35-V35-(E5b!H35-U35))/(E5b!I35-E5b!H35) -> 0.635 | AI35: =(E5b!J35-W35-(E5b!I35-V35))/(E5b!J35-E5b!I35) -> 0.735 | ... AL35: =(E5b!M35-Z35-(E5b!L35-Y35))/(E5b!M35-E5b!L35) -> 0.925
A36: 2058 | B36: =B35+(B$48-B$28)/20 -> 0 | C36: =C35+(C$48-C$28)/20 -> 0 | D36: =D35+(D$48-D$28)/20 -> 0.17 | E36: =E35+(E$48-E$28)/20 -> 0.22 | F36: =F35+(F$48-F$28)/20 -> 0.27 | G36: =G35+(G$48-G$28)/20 -> 0.34 | H36: =H35+(H$48-H$28)/20 -> 0.44 | I36: =I35+(I$48-I$28)/20 -> 0.54 | ... M36: =M35+(M$48-M$28)/20 -> 0.9 | O36: =(1-B36)*E5b!B36 -> 3 | P36: =(1-C36)*E5b!C36 -> 4 | Q36: =(1-D36)*E5b!D36 -> 4.648 | R36: =(1-E36)*E5b!E36 -> 5.928 | S36: =(1-F36)*E5b!F36 -> 8.176 | T36: =(1-G36)*E5b!G36 -> 13.2 | U36: =(1-H36)*E5b!H36 -> 28 | V36: =(1-I36)*E5b!I36 -> 46 | ... Z36: =(1-M36)*E5b!M36 -> 500 | AA36: 1 | AB36: =(E5b!C36-P36-(E5b!B36-O36))/(E5b!C36-E5b!B36) -> 0 | AC36: =(E5b!D36-Q36-(E5b!C36-P36))/(E5b!D36-E5b!C36) -> 0.595 | AD36: =(E5b!E36-R36-(E5b!D36-Q36))/(E5b!E36-E5b!D36) -> 0.36 | AE36: =(E5b!F36-S36-(E5b!E36-R36))/(E5b!F36-E5b!E36) -> 0.37555556 | AF36: =(E5b!G36-T36-(E5b!F36-S36))/(E5b!G36-E5b!F36) -> 0.42909091 | AG36: =(E5b!H36-U36-(E5b!G36-T36))/(E5b!H36-E5b!G36) -> 0.50666667 | AH36: =(E5b!I36-V36-(E5b!H36-U36))/(E5b!I36-E5b!H36) -> 0.64 | AI36: =(E5b!J36-W36-(E5b!I36-V36))/(E5b!J36-E5b!I36) -> 0.74 | ... AL36: =(E5b!M36-Z36-(E5b!L36-Y36))/(E5b!M36-E5b!L36) -> 0.925
A37: 2059 | B37: =B36+(B$48-B$28)/20 -> 0 | C37: =C36+(C$48-C$28)/20 -> 0 | D37: =D36+(D$48-D$28)/20 -> 0.1725 | E37: =E36+(E$48-E$28)/20 -> 0.2225 | F37: =F36+(F$48-F$28)/20 -> 0.2725 | G37: =G36+(G$48-G$28)/20 -> 0.345 | H37: =H36+(H$48-H$28)/20 -> 0.445 | I37: =I36+(I$48-I$28)/20 -> 0.545 | ... M37: =M36+(M$48-M$28)/20 -> 0.9 | O37: =(1-B37)*E5b!B37 -> 3 | P37: =(1-C37)*E5b!C37 -> 4 | Q37: =(1-D37)*E5b!D37 -> 4.592625 | R37: =(1-E37)*E5b!E37 -> 5.870125 | S37: =(1-F37)*E5b!F37 -> 8.07525 | T37: =(1-G37)*E5b!G37 -> 13.1 | U37: =(1-H37)*E5b!H37 -> 27.75 | V37: =(1-I37)*E5b!I37 -> 45.5 | ... Z37: =(1-M37)*E5b!M37 -> 500 | AA37: 1 | AB37: =(E5b!C37-P37-(E5b!B37-O37))/(E5b!C37-E5b!B37) -> 0 | AC37: =(E5b!D37-Q37-(E5b!C37-P37))/(E5b!D37-E5b!C37) -> 0.61766129 | AD37: =(E5b!E37-R37-(E5b!D37-Q37))/(E5b!E37-E5b!D37) -> 0.36125 | AE37: =(E5b!F37-S37-(E5b!E37-R37))/(E5b!F37-E5b!E37) -> 0.37883803 | AF37: =(E5b!G37-T37-(E5b!F37-S37))/(E5b!G37-E5b!F37) -> 0.43542135 | AG37: =(E5b!H37-U37-(E5b!G37-T37))/(E5b!H37-E5b!G37) -> 0.51166667 | AH37: =(E5b!I37-V37-(E5b!H37-U37))/(E5b!I37-E5b!H37) -> 0.645 | AI37: =(E5b!J37-W37-(E5b!I37-V37))/(E5b!J37-E5b!I37) -> 0.745 | ... AL37: =(E5b!M37-Z37-(E5b!L37-Y37))/(E5b!M37-E5b!L37) -> 0.925
A38: 2060 | B38: =B37+(B$48-B$28)/20 -> 0 | C38: =C37+(C$48-C$28)/20 -> 0 | D38: =D37+(D$48-D$28)/20 -> 0.175 | E38: =E37+(E$48-E$28)/20 -> 0.225 | F38: =F37+(F$48-F$28)/20 -> 0.275 | G38: =G37+(G$48-G$28)/20 -> 0.35 | H38: =H37+(H$48-H$28)/20 -> 0.45 | I38: =I37+(I$48-I$28)/20 -> 0.55 | ... M38: =M37+(M$48-M$28)/20 -> 0.9 | O38: =(1-B38)*E5b!B38 -> 3 | P38: =(1-C38)*E5b!C38 -> 4 | Q38: =(1-D38)*E5b!D38 -> 4.5375 | R38: =(1-E38)*E5b!E38 -> 5.8125 | S38: =(1-F38)*E5b!F38 -> 7.975 | T38: =(1-G38)*E5b!G38 -> 13 | U38: =(1-H38)*E5b!H38 -> 27.5 | V38: =(1-I38)*E5b!I38 -> 45 | ... Z38: =(1-M38)*E5b!M38 -> 500 | AA38: 1 | AB38: =(E5b!C38-P38-(E5b!B38-O38))/(E5b!C38-E5b!B38) -> 0 | AC38: =(E5b!D38-Q38-(E5b!C38-P38))/(E5b!D38-E5b!C38) -> 0.64166667 | AD38: =(E5b!E38-R38-(E5b!D38-Q38))/(E5b!E38-E5b!D38) -> 0.3625 | AE38: =(E5b!F38-S38-(E5b!E38-R38))/(E5b!F38-E5b!E38) -> 0.38214286 | AF38: =(E5b!G38-T38-(E5b!F38-S38))/(E5b!G38-E5b!F38) -> 0.44166667 | AG38: =(E5b!H38-U38-(E5b!G38-T38))/(E5b!H38-E5b!G38) -> 0.51666667 | AH38: =(E5b!I38-V38-(E5b!H38-U38))/(E5b!I38-E5b!H38) -> 0.65 | AI38: =(E5b!J38-W38-(E5b!I38-V38))/(E5b!J38-E5b!I38) -> 0.75 | ... AL38: =(E5b!M38-Z38-(E5b!L38-Y38))/(E5b!M38-E5b!L38) -> 0.925
A39: 2061 | B39: =B38+(B$48-B$28)/20 -> 0 | C39: =C38+(C$48-C$28)/20 -> 0 | D39: =D38+(D$48-D$28)/20 -> 0.1775 | E39: =E38+(E$48-E$28)/20 -> 0.2275 | F39: =F38+(F$48-F$28)/20 -> 0.2775 | G39: =G38+(G$48-G$28)/20 -> 0.355 | H39: =H38+(H$48-H$28)/20 -> 0.455 | I39: =I38+(I$48-I$28)/20 -> 0.555 | ... M39: =M38+(M$48-M$28)/20 -> 0.9 | O39: =(1-B39)*E5b!B39 -> 3 | P39: =(1-C39)*E5b!C39 -> 4 | Q39: =(1-D39)*E5b!D39 -> 4.482625 | R39: =(1-E39)*E5b!E39 -> 5.755125 | S39: =(1-F39)*E5b!F39 -> 7.87525 | T39: =(1-G39)*E5b!G39 -> 12.9 | U39: =(1-H39)*E5b!H39 -> 27.25 | V39: =(1-I39)*E5b!I39 -> 44.5 | ... Z39: =(1-M39)*E5b!M39 -> 500 | AA39: 1 | AB39: =(E5b!C39-P39-(E5b!B39-O39))/(E5b!C39-E5b!B39) -> 0 | AC39: =(E5b!D39-Q39-(E5b!C39-P39))/(E5b!D39-E5b!C39) -> 0.66715517 | AD39: =(E5b!E39-R39-(E5b!D39-Q39))/(E5b!E39-E5b!D39) -> 0.36375 | AE39: =(E5b!F39-S39-(E5b!E39-R39))/(E5b!F39-E5b!E39) -> 0.38547101 | AF39: =(E5b!G39-T39-(E5b!F39-S39))/(E5b!G39-E5b!F39) -> 0.44782967 | AG39: =(E5b!H39-U39-(E5b!G39-T39))/(E5b!H39-E5b!G39) -> 0.52166667 | AH39: =(E5b!I39-V39-(E5b!H39-U39))/(E5b!I39-E5b!H39) -> 0.655 | AI39: =(E5b!J39-W39-(E5b!I39-V39))/(E5b!J39-E5b!I39) -> 0.755 | ... AL39: =(E5b!M39-Z39-(E5b!L39-Y39))/(E5b!M39-E5b!L39) -> 0.925
A40: 2062 | B40: =B39+(B$48-B$28)/20 -> 0 | C40: =C39+(C$48-C$28)/20 -> 0 | D40: =D39+(D$48-D$28)/20 -> 0.18 | E40: =E39+(E$48-E$28)/20 -> 0.23 | F40: =F39+(F$48-F$28)/20 -> 0.28 | G40: =G39+(G$48-G$28)/20 -> 0.36 | H40: =H39+(H$48-H$28)/20 -> 0.46 | I40: =I39+(I$48-I$28)/20 -> 0.56 | ... M40: =M39+(M$48-M$28)/20 -> 0.9 | O40: =(1-B40)*E5b!B40 -> 3 | P40: =(1-C40)*E5b!C40 -> 4 | Q40: =(1-D40)*E5b!D40 -> 4.428 | R40: =(1-E40)*E5b!E40 -> 5.698 | S40: =(1-F40)*E5b!F40 -> 7.776 | T40: =(1-G40)*E5b!G40 -> 12.8 | U40: =(1-H40)*E5b!H40 -> 27 | V40: =(1-I40)*E5b!I40 -> 44 | ... Z40: =(1-M40)*E5b!M40 -> 500 | AA40: 1 | AB40: =(E5b!C40-P40-(E5b!B40-O40))/(E5b!C40-E5b!B40) -> 0 | AC40: =(E5b!D40-Q40-(E5b!C40-P40))/(E5b!D40-E5b!C40) -> 0.69428571 | AD40: =(E5b!E40-R40-(E5b!D40-Q40))/(E5b!E40-E5b!D40) -> 0.365 | AE40: =(E5b!F40-S40-(E5b!E40-R40))/(E5b!F40-E5b!E40) -> 0.38882353 | AF40: =(E5b!G40-T40-(E5b!F40-S40))/(E5b!G40-E5b!F40) -> 0.45391304 | AG40: =(E5b!H40-U40-(E5b!G40-T40))/(E5b!H40-E5b!G40) -> 0.52666667 | AH40: =(E5b!I40-V40-(E5b!H40-U40))/(E5b!I40-E5b!H40) -> 0.66 | AI40: =(E5b!J40-W40-(E5b!I40-V40))/(E5b!J40-E5b!I40) -> 0.76 | ... AL40: =(E5b!M40-Z40-(E5b!L40-Y40))/(E5b!M40-E5b!L40) -> 0.925
... A47: 2069 | B47: =B46+(B$48-B$28)/20 -> 0 | C47: =C46+(C$48-C$28)/20 -> 0 | D47: =D46+(D$48-D$28)/20 -> 0.1975 | E47: =E46+(E$48-E$28)/20 -> 0.2475 | F47: =F46+(F$48-F$28)/20 -> 0.2975 | G47: =G46+(G$48-G$28)/20 -> 0.395 | H47: =H46+(H$48-H$28)/20 -> 0.495 | I47: =I46+(I$48-I$28)/20 -> 0.595 | ... M47: =M46+(M$48-M$28)/20 -> 0.9 | O47: =(1-B47)*E5b!B47 -> 3 | P47: =(1-C47)*E5b!C47 -> 4 | Q47: =(1-D47)*E5b!D47 -> 4.052625 | R47: =(1-E47)*E5b!E47 -> 5.305125 | S47: =(1-F47)*E5b!F47 -> 7.09525 | T47: =(1-G47)*E5b!G47 -> 12.1 | U47: =(1-H47)*E5b!H47 -> 25.25 | V47: =(1-I47)*E5b!I47 -> 40.5 | ... Z47: =(1-M47)*E5b!M47 -> 500 | AA47: 1 | AB47: =(E5b!C47-P47-(E5b!B47-O47))/(E5b!C47-E5b!B47) -> 0 | AC47: =(E5b!D47-Q47-(E5b!C47-P47))/(E5b!D47-E5b!C47) -> 0.94988095 | AD47: =(E5b!E47-R47-(E5b!D47-Q47))/(E5b!E47-E5b!D47) -> 0.37375 | AE47: =(E5b!F47-S47-(E5b!E47-R47))/(E5b!F47-E5b!E47) -> 0.41307377 | AF47: =(E5b!G47-T47-(E5b!F47-S47))/(E5b!G47-E5b!F47) -> 0.4944697 | AG47: =(E5b!H47-U47-(E5b!G47-T47))/(E5b!H47-E5b!G47) -> 0.56166667 | AH47: =(E5b!I47-V47-(E5b!H47-U47))/(E5b!I47-E5b!H47) -> 0.695 | AI47: =(E5b!J47-W47-(E5b!I47-V47))/(E5b!J47-E5b!I47) -> 0.795 | ... AL47: =(E5b!M47-Z47-(E5b!L47-Y47))/(E5b!M47-E5b!L47) -> 0.925
A48: 2070 | B48: 0 | C48: 0 | D48: 0.2 | E48: 0.25 | F48: 0.3 | G48: 0.4 | H48: 0.5 | I48: 0.6 | J48: 0.7 | K48: 0.75 | L48: 0.8 | M48: 0.9 | O48: =(1-B48)*E5b!B48 -> 3 | P48: =(1-C48)*E5b!C48 -> 4 | Q48: =(1-D48)*E5b!D48 -> 4 | R48: =(1-E48)*E5b!E48 -> 5.25 | S48: =(1-F48)*E5b!F48 -> 7 | T48: =(1-G48)*E5b!G48 -> 12 | U48: =(1-H48)*E5b!H48 -> 25 | V48: =(1-I48)*E5b!I48 -> 40 | ... Z48: =(1-M48)*E5b!M48 -> 500 | AA48: 1 | AB48: =(E5b!C48-P48-(E5b!B48-O48))/(E5b!C48-E5b!B48) -> 0 | AC48: =(E5b!D48-Q48-(E5b!C48-P48))/(E5b!D48-E5b!C48) -> 1 | AD48: =(E5b!E48-R48-(E5b!D48-Q48))/(E5b!E48-E5b!D48) -> 0.375 | AE48: =(E5b!F48-S48-(E5b!E48-R48))/(E5b!F48-E5b!E48) -> 0.41666667 | AF48: =(E5b!G48-T48-(E5b!F48-S48))/(E5b!G48-E5b!F48) -> 0.5 | AG48: =(E5b!H48-U48-(E5b!G48-T48))/(E5b!H48-E5b!G48) -> 0.56666667 | AH48: =(E5b!I48-V48-(E5b!H48-U48))/(E5b!I48-E5b!H48) -> 0.7 | AI48: =(E5b!J48-W48-(E5b!I48-V48))/(E5b!J48-E5b!I48) -> 0.8 | ... AL48: =(E5b!M48-Z48-(E5b!L48-Y48))/(E5b!M48-E5b!L48) -> 0.925
A49: 2071 | B49: =B48+(B$58-B$48)/10 -> 0 | C49: =C48+(C$58-C$48)/10 -> 0 | D49: =D48+(D$58-D$48)/10 -> 0.205 | E49: =E48+(E$58-E$48)/10 -> 0.255 | F49: =F48+(F$58-F$48)/10 -> 0.31 | G49: =G48+(G$58-G$48)/10 -> 0.41 | H49: =H48+(H$58-H$48)/10 -> 0.51 | I49: =I48+(I$58-I$48)/10 -> 0.61 | ... M49: =M48+(M$58-M$48)/10 -> 0.9 | O49: =(1-B49)*E5b!B49 -> 3 | P49: =(1-C49)*E5b!C49 -> 4 | Q49: =(1-D49)*E5b!D49 -> 3.975 | R49: =(1-E49)*E5b!E49 -> 5.215 | S49: =(1-F49)*E5b!F49 -> 6.9 | T49: =(1-G49)*E5b!G49 -> 11.8 | U49: =(1-H49)*E5b!H49 -> 24.5 | V49: =(1-I49)*E5b!I49 -> 39 | ... Z49: =(1-M49)*E5b!M49 -> 500 | AA49: 1 | AB49: =(E5b!C49-P49-(E5b!B49-O49))/(E5b!C49-E5b!B49) -> 0 | AC49: =(E5b!D49-Q49-(E5b!C49-P49))/(E5b!D49-E5b!C49) -> 1.025 | AD49: =(E5b!E49-R49-(E5b!D49-Q49))/(E5b!E49-E5b!D49) -> 0.38 | AE49: =(E5b!F49-S49-(E5b!E49-R49))/(E5b!F49-E5b!E49) -> 0.43833333 | AF49: =(E5b!G49-T49-(E5b!F49-S49))/(E5b!G49-E5b!F49) -> 0.51 | AG49: =(E5b!H49-U49-(E5b!G49-T49))/(E5b!H49-E5b!G49) -> 0.57666667 | AH49: =(E5b!I49-V49-(E5b!H49-U49))/(E5b!I49-E5b!H49) -> 0.71 | AI49: =(E5b!J49-W49-(E5b!I49-V49))/(E5b!J49-E5b!I49) -> 0.8 | ... AL49: =(E5b!M49-Z49-(E5b!L49-Y49))/(E5b!M49-E5b!L49) -> 0.92375
A50: 2072 | B50: =B49+(B$58-B$48)/10 -> 0 | C50: =C49+(C$58-C$48)/10 -> 0 | D50: =D49+(D$58-D$48)/10 -> 0.21 | E50: =E49+(E$58-E$48)/10 -> 0.26 | F50: =F49+(F$58-F$48)/10 -> 0.32 | G50: =G49+(G$58-G$48)/10 -> 0.42 | H50: =H49+(H$58-H$48)/10 -> 0.52 | I50: =I49+(I$58-I$48)/10 -> 0.62 | ... M50: =M49+(M$58-M$48)/10 -> 0.9 | O50: =(1-B50)*E5b!B50 -> 3 | P50: =(1-C50)*E5b!C50 -> 4 | Q50: =(1-D50)*E5b!D50 -> 3.95 | R50: =(1-E50)*E5b!E50 -> 5.18 | S50: =(1-F50)*E5b!F50 -> 6.8 | T50: =(1-G50)*E5b!G50 -> 11.6 | U50: =(1-H50)*E5b!H50 -> 24 | V50: =(1-I50)*E5b!I50 -> 38 | ... Z50: =(1-M50)*E5b!M50 -> 500 | AA50: 1 | AB50: =(E5b!C50-P50-(E5b!B50-O50))/(E5b!C50-E5b!B50) -> 0 | AC50: =(E5b!D50-Q50-(E5b!C50-P50))/(E5b!D50-E5b!C50) -> 1.05 | AD50: =(E5b!E50-R50-(E5b!D50-Q50))/(E5b!E50-E5b!D50) -> 0.385 | AE50: =(E5b!F50-S50-(E5b!E50-R50))/(E5b!F50-E5b!E50) -> 0.46 | AF50: =(E5b!G50-T50-(E5b!F50-S50))/(E5b!G50-E5b!F50) -> 0.52 | AG50: =(E5b!H50-U50-(E5b!G50-T50))/(E5b!H50-E5b!G50) -> 0.58666667 | AH50: =(E5b!I50-V50-(E5b!H50-U50))/(E5b!I50-E5b!H50) -> 0.72 | AI50: =(E5b!J50-W50-(E5b!I50-V50))/(E5b!J50-E5b!I50) -> 0.8 | ... AL50: =(E5b!M50-Z50-(E5b!L50-Y50))/(E5b!M50-E5b!L50) -> 0.9225
A51: 2073 | B51: =B50+(B$58-B$48)/10 -> 0 | C51: =C50+(C$58-C$48)/10 -> 0 | D51: =D50+(D$58-D$48)/10 -> 0.215 | E51: =E50+(E$58-E$48)/10 -> 0.265 | F51: =F50+(F$58-F$48)/10 -> 0.33 | G51: =G50+(G$58-G$48)/10 -> 0.43 | H51: =H50+(H$58-H$48)/10 -> 0.53 | I51: =I50+(I$58-I$48)/10 -> 0.63 | ... M51: =M50+(M$58-M$48)/10 -> 0.9 | O51: =(1-B51)*E5b!B51 -> 3 | P51: =(1-C51)*E5b!C51 -> 4 | Q51: =(1-D51)*E5b!D51 -> 3.925 | R51: =(1-E51)*E5b!E51 -> 5.145 | S51: =(1-F51)*E5b!F51 -> 6.7 | T51: =(1-G51)*E5b!G51 -> 11.4 | U51: =(1-H51)*E5b!H51 -> 23.5 | V51: =(1-I51)*E5b!I51 -> 37 | ... Z51: =(1-M51)*E5b!M51 -> 500 | AA51: 1 | AB51: =(E5b!C51-P51-(E5b!B51-O51))/(E5b!C51-E5b!B51) -> 0 | AC51: =(E5b!D51-Q51-(E5b!C51-P51))/(E5b!D51-E5b!C51) -> 1.075 | AD51: =(E5b!E51-R51-(E5b!D51-Q51))/(E5b!E51-E5b!D51) -> 0.39 | AE51: =(E5b!F51-S51-(E5b!E51-R51))/(E5b!F51-E5b!E51) -> 0.48166667 | AF51: =(E5b!G51-T51-(E5b!F51-S51))/(E5b!G51-E5b!F51) -> 0.53 | AG51: =(E5b!H51-U51-(E5b!G51-T51))/(E5b!H51-E5b!G51) -> 0.59666667 | AH51: =(E5b!I51-V51-(E5b!H51-U51))/(E5b!I51-E5b!H51) -> 0.73 | AI51: =(E5b!J51-W51-(E5b!I51-V51))/(E5b!J51-E5b!I51) -> 0.8 | ... AL51: =(E5b!M51-Z51-(E5b!L51-Y51))/(E5b!M51-E5b!L51) -> 0.92125
A52: 2074 | B52: =B51+(B$58-B$48)/10 -> 0 | C52: =C51+(C$58-C$48)/10 -> 0 | D52: =D51+(D$58-D$48)/10 -> 0.22 | E52: =E51+(E$58-E$48)/10 -> 0.27 | F52: =F51+(F$58-F$48)/10 -> 0.34 | G52: =G51+(G$58-G$48)/10 -> 0.44 | H52: =H51+(H$58-H$48)/10 -> 0.54 | I52: =I51+(I$58-I$48)/10 -> 0.64 | ... M52: =M51+(M$58-M$48)/10 -> 0.9 | O52: =(1-B52)*E5b!B52 -> 3 | P52: =(1-C52)*E5b!C52 -> 4 | Q52: =(1-D52)*E5b!D52 -> 3.9 | R52: =(1-E52)*E5b!E52 -> 5.11 | S52: =(1-F52)*E5b!F52 -> 6.6 | T52: =(1-G52)*E5b!G52 -> 11.2 | U52: =(1-H52)*E5b!H52 -> 23 | V52: =(1-I52)*E5b!I52 -> 36 | ... Z52: =(1-M52)*E5b!M52 -> 500 | AA52: 1 | AB52: =(E5b!C52-P52-(E5b!B52-O52))/(E5b!C52-E5b!B52) -> 0 | AC52: =(E5b!D52-Q52-(E5b!C52-P52))/(E5b!D52-E5b!C52) -> 1.1 | AD52: =(E5b!E52-R52-(E5b!D52-Q52))/(E5b!E52-E5b!D52) -> 0.395 | AE52: =(E5b!F52-S52-(E5b!E52-R52))/(E5b!F52-E5b!E52) -> 0.50333333 | AF52: =(E5b!G52-T52-(E5b!F52-S52))/(E5b!G52-E5b!F52) -> 0.54 | AG52: =(E5b!H52-U52-(E5b!G52-T52))/(E5b!H52-E5b!G52) -> 0.60666667 | AH52: =(E5b!I52-V52-(E5b!H52-U52))/(E5b!I52-E5b!H52) -> 0.74 | AI52: =(E5b!J52-W52-(E5b!I52-V52))/(E5b!J52-E5b!I52) -> 0.8 | ... AL52: =(E5b!M52-Z52-(E5b!L52-Y52))/(E5b!M52-E5b!L52) -> 0.92
